Workbook

Sheet Post-conf leads (Round 2)
A1: First Name | B1: Last Name | C1: Email Address | D1: Company Name | E1: Title | F1: Mobile Phone Number | G1: Device used to scan badge | H1: Contact Owner | I1: Email Sent (Y/N) Date? | J1: LinkedIn Sent/Connected (Y/N) Date? | K1: Called (Y/N) Date? | L1: Lead Score | M1: Role of this person | N1: DURING-Summit notes | O1: DURING-summit follow-up notes | P1: POST-Summit Follow-up Notes | Q1: POST-Summit Follow-up Jira tickets | R1: POST-Summit lead qual & follow-up planning done | S1: POST-Summit follow-ups done (week of Oct 21-25) | T1: ZoomInfo follow-up Jan 2025 | U1: Call target, Jan 2025 | V1: Called Jan 2025 | W1: Sent LinkedIN Invite 2025Apr | X1: Created date/time US/Eastern | Y1: Qualified | Z1: Is the person currently evaluating solutions related to [specific problem/industry]? | AA1: What is the timeframe for choosing a solution? | AB1: Is there a budget for this business need? | AC1: Work Phone Number | AD1: Work City | AE1: Work State | AF1: Lead Transcription Status | AG1: Lead Source | AH1: Last Update US/Eastern | AI1: What State do you reside in: | AJ1: Country you reside in: | AK1: Sponsorship Level | AL1: Event Sponsor
A2: Catherine Toth | C2: cathy.toth@acatoim.com | D2: Acato Information Management LLC | H2: Hari | L2: 1 | N2: Collected contact info after last day SAFe gov session | T2: TRUE | U2: FALSE | V2: FALSE | W2: FALSE
A3: Bill Toth | C3: bill.toth@acatoim.com | D3: Acato Information Management LLC | H3: Hari | L3: 1 | N3: Collected contact info after last day SAFe gov session | T3: TRUE | U3: FALSE | V3: FALSE
A4: Alexander Miner | C4: alexander.r.miner@frb.gov | D4: agile coach | H4: Hari | L4: 1 | N4: Collected contact info after last day SAFe gov session | T4: TRUE | U4: FALSE | V4: FALSE
A5: Bhavani | B5: Krishnan | C5: bhavani.krishnan@agilevelocity.com | D5: Agile Velocity | E5: Enterprise Agile Coach | F5: 571.246.0602 | G5: iPad Mini (LSA/Keith) / Kurt's iPhone (personal) | H5: Kurt | L5: 4 | M5: Budget authority | N5: Looking for partnership opportunity. Spoke to Kurt. They are in the commercial space and interact with cyber security. They are very interested in looking at their women owned an 8a. Spoke with her and their chief revenue officer James Hawks. | O5: Other: X | P5: EMAIL_PARTNER_HIGH: Send email asking for follow-up discussion. Setup further discussion on how we can partner and help one another by leveraging their 8a. Meeting scheduled for 10/24/2024 to explore strategic plan and partnering with her and James Hawks | R5: TRUE | S5: TRUE | T5: TRUE | U5: FALSE | V5: FALSE | X5: =DATE(2024,10,15)+TIME(10,49,18) -> 45580.451 | Y5: Yes | AG5: Scanned | AH5: =DATE(2024,10,15)+TIME(11,2,31) -> 45580.46 | AI5: Virginia | AJ5: United States | AK5: Large Solution | AL5: Yes
A6: Erin | B6: Mcclain | C6: erinmccaslun@agilityhealth.com | D6: Agility Health | E6: VP Partner Development | G6: Kurt's iPhone (personal) | H6: Kurt / Mike | I6: Connected - Need to follow-up on way ahead on IP and the NDA | J6: Connected | L6: 4 | M6: Other: Partner builder and go to market strategist | N6: Aaron was very interested in helping us use their wheel system and then helping to find ways that we can go to market and lean into each others pipelines and how we can jump on various things together | O6: Other: Do presentation to help develop our strategy to go after work together, Send Literature, Schedule Demo | P6: EMAIL_PARTNER_HIGH: Send email asking for follow-up discussion. Discussed with Mike and there might be further opportunities for us to synch up on using their wheel system and add further capabilities. Follow-up with a call and explore opportunities together. Meeting scheduled for 10/24/2024 to explore strategic plan and partnering | R6: TRUE | S6: TRUE | T6: TRUE | U6: FALSE | V6: FALSE | X6: =DATE(2024,10,15)+TIME(13,0,54) -> 45580.542 | Y6: Yes | Z6: Yes | AA6: Not Applicable | AB6: Not Applicable | AF6: completed | AG6: Business card | AH6: =DATE(2024,10,15)+TIME(19,37,10) -> 45580.817 | AK6: Large Solution | AL6: Yes
A7: Trevor | B7: Methena | C7: trevor.methena@allegion.com | D7: Allegion | E7: Release Train Engineer | F7: 5124176356 | G7: Christy's iPhone (personal) | H7: Christy | L7: 2 | M7: Influencer | N7: They are global company of IoT hardware and software. They are using agile practices and have done a lot of outsourcing overseas recently. | O7: Add to Mailing List | P7: Sent Initial Email - 23 Oct | R7: TRUE | S7: TRUE | T7: TRUE | U7: FALSE | V7: FALSE | X7: =DATE(2024,10,15)+TIME(10,39,50) -> 45580.444 | Y7: Yes | Z7: No | AG7: Scanned | AH7: =DATE(2024,10,15)+TIME(10,56,0) -> 45580.456 | AI7: Texas | AJ7: United States | AK7: Large Solution | AL7: Yes
A8: S. Hasnain | B8: Rizvi | C8: hasnain.rizvi@americannational.com | D8: American National Insurance | E8: Agile Transformation Lead | F8: 8184287768 | G8: iPad Mini (LSA/Keith) | H8: Dani | L8: 4 | M8: Decision maker | N8: Dani to schedule | O8: N/A | R8: FALSE | S8: FALSE | T8: TRUE | U8: TRUE | V8: TRUE | X8: =DATE(2024,10,15)+TIME(13,31,54) -> 45580.564 | Y8: Yes | Z8: Yes | AA8: Immediately | AG8: Scanned | AH8: =DATE(2024,10,15)+TIME(13,33,37) -> 45580.565 | AI8: Texas | AJ8: United States | AK8: Large Solution | AL8: Yes
A9: Puneeta | B9: Singh | C9: pusingh@americorps.gov | D9: AmeriCorps | E9: Project Manager | F9: 202-925-7552 | G9: iPad Mini (LSA/Keith) | H9: Christy | L9: 1 | P9: Sent Initial Email - 23 Oct | R9: TRUE | S9: TRUE | T9: TRUE | U9: FALSE | V9: FALSE | X9: =DATE(2024,10,16)+TIME(14,44,40) -> 45581.614 | Y9: No | AG9: Scanned | AH9: =DATE(2024,10,16)+TIME(14,44,46) -> 45581.614 | AI9: Virginia | AJ9: United States | AK9: Large Solution | AL9: Yes
A10: Puneeta Singh | C10: pusingh@americorps.gov | D10: Americorps | H10: Hari | L10: 1 | N10: Collected contact info after last day SAFe gov session | T10: TRUE | U10: FALSE | V10: FALSE
A11: Jamie | B11: Shopland | C11: jamie.shopland@amtrak.com | D11: Amtrak | E11: Director, Agile Transformation | F11: 3013057640 | G11: iPad Mini (LSA/Keith) | H11: Mike | L11: 4 | M11: Other: Unknown | N11: Enter to win prize. Recorded video. | O11: N/A | P11: send AFRL, R&D experience related template TEMPLATE_CLIENT_HIGH and attach LPM talkbook pdf Mention that we have experience with tranportation at California DOT, have case studies for this if interested | R11: FALSE | S11: FALSE | T11: TRUE | U11: TRUE | V11: TRUE | X11: =DATE(2024,10,15)+TIME(7,58,41) -> 45580.332 | Y11: Yes | Z11: No | AG11: Scanned | AH11: =DATE(2024,10,15)+TIME(8,0,21) -> 45580.334 | AI11: Maryland | AJ11: United States | AK11: Large Solution | AL11: Yes
A12: Thilakavathi | B12: Rajakumar | C12: thilakavathi210@gmail.com | D12: AT&T | E12: Solution Train Engineer | F12: 6782964234 | G12: iPad Tiny (LSA/Mike) | H12: Hari | L12: 1 | R12: FALSE | S12: FALSE | T12: TRUE | U12: FALSE | V12: FALSE | X12: =DATE(2024,10,16)+TIME(10,1,25) -> 45581.418 | Y12: No | AG12: Scanned | AH12: =DATE(2024,10,16)+TIME(10,14,3) -> 45581.426 | AI12: Georgia | AJ12: United States | AK12: Large Solution | AL12: Yes
A13: Bryan | B13: Smith | C13: bsmith3@atlassian.com | D13: Atlassian | E13: Jira Align Strategic Solution Sales Account Manager | F13: 720-830-6998 | G13: Christy's iPhone (personal) | H13: Christy | L13: 3 | M13: Other: jira align jira | N13: Spoke at lenght on JIRA Align and Atlassian suite | O13: Add to Mailing List | P13: Sent Initial Email - 23 Oct - connected on LinkedIn - no response to phone call left message for follow up conversation. | R13: TRUE | S13: TRUE | T13: TRUE | U13: FALSE | V13: FALSE | X13: =DATE(2024,10,14)+TIME(11,15,57) -> 45579.469 | Y13: Yes | Z13: No | AG13: Scanned | AH13: =DATE(2024,10,14)+TIME(11,16,53) -> 45579.47 | AI13: Colorado | AJ13: United States | AK13: Large Solution | AL13: Yes
A14: Mohammad Riad | B14: Hossan | C14: riad_hossan@bcbst.com | D14: BlueCross BlueShield of Tennessee, Inc | E14: Business Analyst | F14: 3098268972 | G14: iPad Mini (LSA/Keith) | H14: Hari | L14: 1 | R14: FALSE | S14: FALSE | T14: TRUE | U14: FALSE | V14: FALSE | X14: =DATE(2024,10,16)+TIME(10,28,34) -> 45581.437 | Y14: No | AG14: Scanned | AH14: =DATE(2024,10,16)+TIME(10,28,41) -> 45581.437 | AI14: Virginia | AJ14: United States | AK14: Large Solution | AL14: Yes
A15: Lisa Cohen | C15: cohen_lisa@bah.com | D15: Booz Allen Hamilton | H15: Hari | L15: 1 | N15: Collected contact info after last day SAFe gov session | T15: TRUE | U15: FALSE | V15: FALSE
A16: Jennifer Murillo | C16: murillo_jennifer@bah.com | D16: Booz Allen Hamilton | H16: Hari | L16: 1 | N16: Collected contact info after last day SAFe gov session | T16: TRUE | U16: FALSE | V16: FALSE
A17: Lynn Stevens | C17: stevens_lynn@bah.com | D17: Booz Allen Hamilton | H17: Hari | L17: 1 | N17: Collected contact info after last day SAFe gov session | T17: TRUE | U17: FALSE | V17: FALSE
A18: Paula Barbour | C18: barbour_paula@bah.com | D18: Booz Allen Hamilton | H18: Hari | L18: 1 | N18: Collected contact info after last day SAFe gov session | T18: TRUE | U18: FALSE | V18: FALSE
A19: Bonnie | B19: Soto | C19: soto_bonnie@bah.com | D19: Booz Allen Hamilton | E19: Technical Team Lead | F19: 2103241023 | G19: Taylor's iPhone (personal) | L19: 1 | R19: FALSE | S19: FALSE | T19: TRUE | U19: FALSE | V19: FALSE | X19: =DATE(2024,10,15)+TIME(13,24,0) -> 45580.558 | Y19: No | AG19: Scanned | AH19: =DATE(2024,10,15)+TIME(13,56,0) -> 45580.581 | AI19: Texas | AJ19: United States | AK19: Large Solution | AL19: Yes
A20: Jennifer Castro | C20: jennifer.castro@broadcom.com | D20: Broadcom | H20: Hari | L20: 1 | N20: Collected contact info after last day SAFe gov session | T20: TRUE | U20: FALSE | V20: FALSE
A21: Elonia | B21: Taylor | C21: elonia.taylor@bep.gov | D21: Bureau of Engraving and Printing | E21: Sr. IT Project Manager | F21: (817)528-1037 | G21: iPad Mini (LSA/Keith) | H21: Dani | L21: 5 | N21: Early in agile implementation; got SES ; want workshops and training. Lead for the program, Mike White introduced. Kurt - submitted RFI for agile coaching previously… Kurt has discussed BEP opportunities with Navy Gold Coast / Business Dev lead | R21: FALSE | S21: FALSE | T21: TRUE | U21: TRUE | V21: TRUE | X21: =DATE(2024,10,16)+TIME(13,58,44) -> 45581.582 | Y21: No | AG21: Scanned | AH21: =DATE(2024,10,16)+TIME(13,58,57) -> 45581.583 | AI21: Texas | AJ21: United States | AK21: Large Solution | AL21: Yes
A22: Steve | B22: Brylski | C22: steve.brylski@caci.com | D22: CACI | E22: Agile Transformation Leader/Coach | F22: (571) 291-7450 | G22: Mike's iPhone (personal) | H22: Mike | L22: 4 | M22: Influencer | N22: See Chris ham comments | O22: Add to Mailing List | Q22: none | R22: TRUE | S22: TRUE | T22: TRUE | U22: TRUE | V22: TRUE | X22: =DATE(2024,10,16)+TIME(13,21,24) -> 45581.557 | Y22: Yes | Z22: No | AG22: Scanned | AH22: =DATE(2024,10,17)+TIME(13,12,29) -> 45582.55 | AI22: Virginia | AJ22: United States | AK22: Large Solution | AL22: Yes
A23: Chris | B23: Ham | C23: chris.ham@caci.com | D23: CACI Inc. | E23: Agile Solution Factory Director | F23: 7036253263 | G23: Mike's iPhone (personal) | H23: Mike | L23: 4 | M23: Influencer | N23: They spoke to robin, robin mentioned LSA, they came to booth, gave them UX book, and they said they could ‘find a home’ for LSA | O23: Add to Mailing List | P23: EMAIL_PARTNER_HIGH: follow-up discussion; attach usual table insert; CC: Steve Brylski, Robin, Dani | Q23: none | R23: TRUE | S23: TRUE | T23: TRUE | U23: TRUE | V23: TRUE | X23: =DATE(2024,10,16)+TIME(13,21,29) -> 45581.557 | Y23: Yes | Z23: No | AG23: Scanned | AH23: =DATE(2024,10,17)+TIME(13,12,2) -> 45582.55 | AI23: Virginia | AJ23: United States | AK23: Large Solution | AL23: Yes
A24: Abdul Rasheed | B24: Shaik | C24: abdulrasheed.shaik@fepoc.com | D24: CareFirst | E24: Release Train Engineer | F24: 9493947591 | G24: Mike's iPhone (personal) | H24: Mike | L24: 4 | M24: Influencer | N24: Also has OPM as customer . Benefits for OPM. Was interested in various case studies and engaged | O24: Add to Mailing List | P24: EMAIL_PARTNER_MEDIUM: Send email asking for follow-up discussion; emphasize / call-out OPM case studies. Attach usual table insert | Q24: none | R24: TRUE | S24: TRUE | T24: TRUE | U24: TRUE | V24: FALSE | X24: =DATE(2024,10,15)+TIME(15,47,8) -> 45580.658 | Y24: Yes | Z24: No | AG24: Scanned | AH24: =DATE(2024,10,15)+TIME(17,38,59) -> 45580.735 | AI24: Virginia | AJ24: United States | AK24: Large Solution | AL24: Yes
A25: Hans | B25: Raj | C25: hans.raj@fepoc.com | D25: CareFirst BlueCross BlueShield (FEPOC) | E25: Lead Software Engineer/Team Coach | F25: 7038627951 | G25: iPad Mini (LSA/Mike) | H25: Larry | I25: Yes, on 11/26 | L25: 3 | M25: Influencer | N25: Gave book. Interested in AI and UX | O25: Add to Mailing List | R25: FALSE | S25: TRUE | T25: TRUE | U25: TRUE | V25: TRUE | X25: =DATE(2024,10,16)+TIME(10,21,17) -> 45581.431 | Y25: Yes | Z25: No | AG25: Scanned | AH25: =DATE(2024,10,16)+TIME(10,30,39) -> 45581.438 | AI25: Virginia | AJ25: United States | AK25: Large Solution | AL25: Yes
A26: Jalpa | B26: Purani | C26: N/A | D26: CGI | E26: Director | G26: Kurt's iPhone (personal) | H26: Kurt | I26: Connected - Discussed opportunities for SN work with CGI | J26: Connected on LinkedIn | L26: 4 | M26: Influencer | N26: She said she has a financial client that she’s working with . She is helping them with agile but really needs additional help with working with Service now. I told her I could get her connected with Craig and we can have a discussion on how we can bring all that together. | O26: Needs Technical Data, Send Literature, Add to Mailing List, Schedule Demo | P26: EMAIL_PARTNER_HIGH: Send email asking for follow-up discussion; emphasize. Setup a call to demo to discuss how we can help with SNOW. Include Craig, Mike and Kurt. 10/21: Sent email to reach out about a follow-on call. Waiting on her response and plan to follow-up Monday (10/28 if no response (KG) | R26: TRUE | S26: TRUE | T26: TRUE | U26: TRUE | V26: FALSE | X26: =DATE(2024,10,14)+TIME(15,4,39) -> 45579.628 | Y26: Yes | Z26: Yes | AA26: Within 3 months | AB26: Yes | AF26: completed | AG26: Business card | AH26: =DATE(2024,10,14)+TIME(16,49,32) -> 45579.701 | AK26: Large Solution | AL26: Yes
A27: Parag | B27: Gupta | C27: parag.gupta@cna.com | D27: CNA | E27: Director, Value Creation | F27: 4379254146 | G27: iPad Mini (LSA/Mike) | H27: Larry | I27: Yes, on 12/9 | L27: 4 | M27: Decision maker | N27: Transformation of legacy systems. Gave a book. | O27: Send Literature, Add to Mailing List | R27: FALSE | S27: TRUE | T27: TRUE | U27: TRUE | V27: TRUE | X27: =DATE(2024,10,16)+TIME(11,29,8) -> 45581.479 | Y27: Yes | Z27: No | AG27: Scanned | AH27: =DATE(2024,10,16)+TIME(11,56,20) -> 45581.497 | AJ27: Canada | AK27: Large Solution | AL27: Yes
A28: Benjamin Baghdadi | C28: bbaghdadi@cns.gov | D28: CNS | H28: Hari | L28: 1 | N28: Collected contact info after last day SAFe gov session | T28: TRUE | U28: FALSE | V28: FALSE
A29: Jacky | B29: Droushoudt | C29: jdroushoudt@pccwglobal.com | D29: Console Connect (HK) Limited | E29: AVP, Product Management (Scrum) | F29: +32494538194 | G29: Christy's iPhone (personal) | H29: Dani | L29: 4 | M29: Decision maker | N29: Was interested in what we do, wanted to stay in contact if there were stateside opprotunities. Dani and Christy both collaborated, Dani has been chatting with over LinkedIn… potentially wants a demo of the EEK presentation for his organization… Digital Transformation lead | O29: Add to Mailing List | R29: TRUE | S29: FALSE | T29: TRUE | U29: TRUE | V29: TRUE | X29: =DATE(2024,10,14)+TIME(11,1,54) -> 45579.46 | Y29: Yes | Z29: No | AG29: Scanned | AH29: =DATE(2024,10,14)+TIME(11,2,28) -> 45579.46 | AJ29: Hong Kong | AK29: Large Solution | AL29: Yes
A30: Praveen | B30: Goel | C30: praveen.goel@cprime.com | D30: cPrime | E30: SPCT, Transformation Leader, Agile Coach | F30: 2032311857 | G30: Mike's iPhone (personal) | H30: Mike | L30: 2 | M30: Other: SPCT learning about our approach | N30: hit-and-run, no real discussion | O30: Add to Mailing List | P30: EMAIL_PARTNER_LOW - nice meeting you, happy to discuss partnership opportuniites...; attach usual table insert | Q30: none | R30: TRUE | S30: TRUE | T30: TRUE | U30: FALSE | V30: FALSE | X30: =DATE(2024,10,15)+TIME(11,22,33) -> 45580.474 | Y30: Yes | Z30: No | AG30: Scanned | AH30: =DATE(2024,10,15)+TIME(11,23,24) -> 45580.475 | AI30: Connecticut | AJ30: United States | AK30: Large Solution | AL30: Yes
A31: Danny | B31: Debner | C31: danny.debner@cvent.com | D31: Cvent | G31: iPad Mini (LSA/Keith) | H31: Larry | N31: This is actually Saya Sone. I gave her a book. | R31: FALSE | S31: TRUE | T31: TRUE | U31: FALSE | V31: FALSE | X31: =DATE(2024,10,16)+TIME(15,35,32) -> 45581.65 | Y31: No | AG31: Scanned | AH31: =DATE(2024,10,16)+TIME(15,35,43) -> 45581.65 | AI31: Washington | AJ31: United States | AK31: Large Solution | AL31: Yes
A32: Richard | B32: Trice | C32: richard.w.trice.civ@health.mil | D32: DHMS/EIDS | E32: Product Manager | F32: 8304310550 | G32: iPad Mini (LSA/Keith) | H32: Christy | L32: 3 | P32: Requested LinkedIn connection - no response, called and left VM to set up meeting to reconnect | R32: TRUE | S32: TRUE | T32: TRUE | U32: FALSE | V32: FALSE | X32: =DATE(2024,10,15)+TIME(17,47,39) -> 45580.741 | Y32: No | AG32: Scanned | AH32: =DATE(2024,10,15)+TIME(17,47,51) -> 45580.742 | AI32: Texas | AJ32: United States | AK32: Large Solution | AL32: Yes
A33: Etienne | B33: LAVERDIERE | C33: elaverdiere@digitaltango.ca | D33: DIGITAL TANGO | E33: CEO | F33: +33 7 82 55 07 78 | G33: iPad Mini (LSA/Mike) | H33: Larry | I33: Yes, on 11/26 | L33: 3 | M33: Other: NA | N33: Interested in UX and design thinking | O33: Other: Gave a book to him | R33: FALSE | S33: TRUE | T33: TRUE | U33: FALSE | V33: FALSE | X33: =DATE(2024,10,15)+TIME(9,35,48) -> 45580.4 | Y33: Yes | Z33: No | AC33: 5145163100 | AG33: Scanned | AH33: =DATE(2024,10,15)+TIME(17,43,48) -> 45580.739 | AJ33: France | AK33: Large Solution | AL33: Yes
A34: Jacqueline | B34: Markot | C34: jackie.markot@discounttire.com | D34: Discount Tire | E34: Product Manager | F34: 4802627243 | G34: Taylor's iPhone (personal) | L34: 2 | M34: Influencer | N34: Looking for Ada Dash boarding and UX help. Looking for a consultant to come in and work with transparency in their organization. ￼ | O34: Other: Connect | R34: FALSE | S34: FALSE | T34: TRUE | U34: FALSE | V34: FALSE | X34: =DATE(2024,10,15)+TIME(10,48,25) -> 45580.45 | Y34: Yes | Z34: Yes | AA34: Within 3 months | AB34: Yes | AG34: Scanned | AH34: =DATE(2024,10,15)+TIME(10,58,54) -> 45580.458 | AI34: Arizona | AJ34: United States | AK34: Large Solution | AL34: Yes
A35: Blake Helander | C35: blake.helander@dodiis.mil | D35: DoD Product Manager | H35: Hari | L35: 1 | N35: Collected contact info after last day SAFe gov session | T35: TRUE | U35: FALSE | V35: FALSE
A36: Matt Lasater | C36: matt@egagedagility.com | D36: Engaged Agility | H36: Hari | L36: 1 | N36: Collected contact info after last day SAFe gov session | T36: TRUE | U36: FALSE | V36: FALSE
A37: Ken | B37: King | C37: ken.king@expleogroup.com | D37: Expleo Group | E37: Agile Coach | G37: Kurt's iPhone (personal) | H37: Dani | L37: 3 | M37: Influencer | N37: He works at Expleo Group in Dublin Ireland. He also is at Bank of America. He has a SP six, RT, SDP, LPM, PMP, ACP, RS @SP, agog Coach in Bank of America in Europe. | O37: Send Literature, Add to Mailing List | P37: EMAIL_PARTNER_HIGH: Send email asking for follow-up discussion; emphasize. As we connected, I found out that he had also met Mike Idengren at an event in Nashville.Nothing specific but may want to explore opportunites with him or/BoA further and share our work with FinTech | R37: TRUE | S37: TRUE | T37: TRUE | U37: FALSE | V37: FALSE | X37: =DATE(2024,10,14)+TIME(22,20,18) -> 45579.931 | Y37: Yes | Z37: No | AD37: Dublin | AE37: IE | AF37: completed | AG37: Business card | AH37: =DATE(2024,10,15)+TIME(2,39,18) -> 45580.111 | AK37: Large Solution | AL37: Yes
A38: Smita | B38: Saxena | C38: smita_x_saxena@fanniemae.com | D38: Fannie Mae | E38: Sr. Scrum Master | F38: 17039675748 | G38: iPad Mini (LSA/Mike) | H38: Larry | I38: Yes, on 11/26 | L38: 4 | M38: Other: Scrum master | N38: Wants to know what we do. Interest in ux | O38: Send Literature | R38: FALSE | S38: TRUE | T38: TRUE | U38: TRUE | V38: TRUE | X38: =DATE(2024,10,16)+TIME(10,12,31) -> 45581.425 | Y38: Yes | Z38: No | AG38: Scanned | AH38: =DATE(2024,10,16)+TIME(10,15,53) -> 45581.428 | AI38: Virginia | AJ38: United States | AK38: Large Solution | AL38: Yes
A39: Bethany Thomas | C39: bmthomas2@fbi.gov | D39: FBI | H39: Hari | L39: 1 | N39: Collected contact info after last day SAFe gov session | T39: TRUE | U39: FALSE | V39: FALSE
A40: Anitha | B40: Sankur | C40: anitha.sankur@atl.frb.org | D40: Federal Reserve Bank of Atlanta | E40: LEAN-Agile Coach | F40: 4232425695 | G40: iPad Mini (LSA/Mike) | H40: Hari | L40: 3 | M40: Other: Unknown | N40: Work with Mike - find out who got the SAFe ARCH training | O40: Add to Mailing List | R40: FALSE | S40: FALSE | T40: TRUE | U40: FALSE | V40: FALSE | X40: =DATE(2024,10,16)+TIME(12,3,2) -> 45581.502 | Y40: Yes | Z40: No | AG40: Scanned | AH40: =DATE(2024,10,16)+TIME(13,42,33) -> 45581.571 | AI40: Georgia | AJ40: United States | AK40: Large Solution | AL40: Yes
A41: Peter | B41: Pendergast | C41: peter.pendergast@gd-ms.com | D41: General Dynamics Mission System | G41: Kurt's iPhone (personal) | H41: Kurt | L41: 3 | M41: Influencer | N41: Seemed interesetd in discussing further around how we might e able to engage with GD on EA, SAFe and possibly SNOW. Nothing overly specific but may be a good way to further increase our possibility of working as a sub. | O41: Send Literature, Add to Mailing List, | P41: Some interest and discussion about pain points and/or LSA solution. Possibly setup an exploration call to pull more of their requirements or pain points out. | R41: TRUE | S41: TRUE | T41: TRUE | U41: FALSE | V41: FALSE | X41: =DATE(2024,10,15)+TIME(12,33,59) -> 45580.524 | Y41: No | AF41: transcription incomplete | AG41: Business card | AH41: =DATE(2024,10,15)+TIME(12,41,56) -> 45580.529 | AK41: Large Solution | AL41: Yes
A42: Evan | B42: Champagne | C42: evan.champagne@gd-ms.com | D42: General Dynamics Mission Systems | E42: Advanced Systems Engineer | G42: Kurt's iPhone (personal) | H42: Kurt | L42: 3 | M42: Influencer | N42: Seemed interesetd in discussing further around how we might e able to engage with GD on EA, SAFe and possibly SNOW. Nothing overly specific but may be a good way to further increase our possibility of working as a sub. | O42: Send Literature, Add to Mailing List, | P42: See Peter Pendergast | R42: TRUE | S42: TRUE | T42: TRUE | U42: FALSE | V42: FALSE | X42: =DATE(2024,10,15)+TIME(12,33,43) -> 45580.523 | Y42: No | AF42: completed | AG42: Business card | AH42: =DATE(2024,10,15)+TIME(12,39,34) -> 45580.527 | AK42: Large Solution | AL42: Yes
A43: Beth | B43: Hatter | C43: beth.hatter@genesisconsulting.com | D43: Genesis Consulting | E43: Director of Agile Coaching | F43: 434-272-9031 | G43: iPad Mini (LSA/Keith) | R43: FALSE | S43: FALSE | T43: TRUE | U43: FALSE | V43: FALSE | X43: =DATE(2024,10,16)+TIME(13,59,12) -> 45581.583 | Y43: No | AG43: Scanned | AH43: =DATE(2024,10,16)+TIME(13,59,21) -> 45581.583 | AI43: Washington | AJ43: United States | AK43: Large Solution | AL43: Yes
A44: Horace | B44: Lynch | C44: horacelynch@hotmail.com | D44: Georgia Pacific | E44: Scrum Master | F44: 9012922083 | G44: iPad Mini (LSA/Mike) | H44: Hari | L44: 2 | M44: Influencer | N44: (who talked to Horace Lynch?) | O44: Add to Mailing List | P44: send TEMPLATE_CLIENT_LOW | R44: FALSE | S44: FALSE | T44: TRUE | U44: FALSE | V44: FALSE | X44: =DATE(2024,10,16)+TIME(10,7,12) -> 45581.422 | Y44: Yes | Z44: No | AG44: Scanned | AH44: =DATE(2024,10,16)+TIME(10,32,37) -> 45581.439 | AI44: Georgia | AJ44: United States | AK44: Large Solution | AL44: Yes
A45: Joshua | B45: Seckel | C45: joshua.seckel@govcio.com | D45: GovCIO | E45: Vice President | F45: 5712282878 | G45: iPad Mini (LSA/Keith) | H45: Larry | I45: Yes, on 11/26 | L45: 3 | M45: Influencer | O45: Other: UX curious | R45: FALSE | S45: TRUE | T45: TRUE | U45: FALSE | V45: FALSE | X45: =DATE(2024,10,15)+TIME(10,9,53) -> 45580.424 | Y45: Yes | Z45: No | AG45: Scanned | AH45: =DATE(2024,10,15)+TIME(11,23,11) -> 45580.474 | AI45: Virginia | AJ45: United States | AK45: Large Solution | AL45: Yes
A46: Carmen | B46: Graver | C46: cgraver@graveragileinnovations.com | D46: Graver Agile Innovations, LLC | E46: Enterprise Agile Coach | F46: 7035595306 | G46: Mike's iPhone (personal) | H46: Mike | L46: 1 | M46: Other: None | N46: Little interest | O46: Add to Mailing List | P46: EMAIL_CLIENT_LOW - Send email asking for follow-up discussion; attach usual table insert | Q46: none | R46: TRUE | S46: TRUE | T46: TRUE | U46: FALSE | V46: FALSE | X46: =DATE(2024,10,15)+TIME(15,35,43) -> 45580.65 | Y46: Yes | Z46: No | AC46: 7035595306 | AG46: Scanned | AH46: =DATE(2024,10,15)+TIME(17,44,1) -> 45580.739 | AI46: Virginia | AJ46: United States | AK46: Large Solution | AL46: Yes
A47: Lesa | B47: Kennedy | C47: lesa_kennedy@glic.com | D47: Guardian Life Insurance | E47: Enterprise Methodology Coach | F47: 3474329075 | G47: iPad Mini (LSA/Keith) | H47: Dani | L47: 5 | M47: Influencer | N47: Send follow up on Business Teams needing support for agile implementation. | O47: Send Literature, Add to Mailing List | R47: FALSE | S47: FALSE | T47: TRUE | U47: TRUE | V47: TRUE | X47: =DATE(2024,10,15)+TIME(8,6,27) -> 45580.338 | Y47: Yes | Z47: Yes | AA47: Immediately | AB47: Yes | AG47: Scanned | AH47: =DATE(2024,10,15)+TIME(8,8,31) -> 45580.339 | AI47: New York | AJ47: United States | AK47: Large Solution | AL47: Yes
A48: Jason | B48: Morley | C48: jmorley@habitat.org | D48: Habitat for Humanity International | E48: Director, Business Intelligence | F48: 4049332885 | G48: Christy's iPhone (personal) | H48: Christy | L48: 2 | M48: Budget authority | N48: Using Agile to manage work across franchises for H4H. | O48: Add to Mailing List | P48: Sent Initial Email - 23 Oct | R48: TRUE | S48: TRUE | T48: TRUE | U48: FALSE | V48: FALSE | X48: =DATE(2024,10,15)+TIME(13,4,27) -> 45580.545 | Y48: Yes | Z48: No | AG48: Scanned | AH48: =DATE(2024,10,15)+TIME(13,4,41) -> 45580.545 | AI48: Georgia | AJ48: United States | AK48: Large Solution | AL48: Yes
A49: Bharat | B49: Shah | D49: HCLTech | E49: Practice Lead, Agile Transformation and CoE | G49: Kurt's iPhone (personal) | H49: Kurt | L49: 2 | M49: Other: RTE | N49: Large 220k global organization. Many areas that do a majority of what we do. | O49: Send Literature, Add to Mailing List | P49: Some discussion about pain points and/or LSA solutions;. Seemed to be well covered with a large pool of resources. Best possible opportunity may be if they need additional resources | R49: TRUE | S49: TRUE | T49: TRUE | U49: FALSE | V49: FALSE | X49: =DATE(2024,10,15)+TIME(14,58,45) -> 45580.624 | Y49: Yes | Z49: No | AF49: completed | AG49: Business card | AH49: =DATE(2024,10,15)+TIME(17,21,57) -> 45580.724 | AK49: Large Solution | AL49: Yes
A50: Rene | B50: Watts | C50: rene.watts@hcltech.com | D50: HCLTech | E50: Agile Coach | F50: 7206569957 | G50: iPad Mini (LSA/Mike) | H50: Kurt | L50: 1 | M50: Influencer | O50: Add to Mailing List | P50: Email sent | R50: TRUE | S50: TRUE | T50: TRUE | U50: FALSE | V50: FALSE | X50: =DATE(2024,10,15)+TIME(10,39,45) -> 45580.444 | Y50: Yes | Z50: No | AG50: Scanned | AH50: =DATE(2024,10,15)+TIME(17,43,48) -> 45580.739 | AI50: Florida | AJ50: United States | AK50: Large Solution | AL50: Yes
A51: Namrata | B51: Datta | C51: namrata.d@hcl.com | D51: HCLTech | E51: Director , Agile Coach, SPCT candidate | F51: 6479364342 | G51: Taylor's iPhone (personal) | H51: Kurt | L51: 1 | P51: Email sent | R51: TRUE | S51: TRUE | T51: TRUE | U51: FALSE | V51: FALSE | X51: =DATE(2024,10,15)+TIME(10,39,55) -> 45580.444 | Y51: No | AG51: Scanned | AH51: =DATE(2024,10,15)+TIME(10,39,58) -> 45580.444 | AJ51: Canada | AK51: Large Solution | AL51: Yes
A52: Rasheedat | B52: Osei- Acheampchg | C52: Sent LinkedIn Invite with Message | D52: IBM | E52: TSA Project Executive | G52: Kurt's iPhone (personal) | H52: Kurt | I52: Connected | J52: Connected on LinkedIn | L52: 3 | M52: Influencer | N52: We discussed that we are working to engage with IBM and recently spoke to IBM's small business liaison and there was alignment on how LSA could partner with IBM. Will likely pull in Rasheedat as needed for further opportuntiies at TSA | P52: Some interest and discussion about pain points and/or LSA solution | R52: TRUE | S52: TRUE | T52: TRUE | U52: FALSE | V52: FALSE | X52: =DATE(2024,10,15)+TIME(12,5,34) -> 45580.504 | Y52: No | AF52: completed | AG52: Business card | AH52: =DATE(2024,10,15)+TIME(12,12,31) -> 45580.509 | AK52: Large Solution | AL52: Yes
A53: Jed Hadley | C53: jed.hadley@ibm.com | D53: IBM consulting | H53: Hari | L53: 1 | N53: Collected contact info after last day SAFe gov session | T53: TRUE | U53: FALSE | V53: FALSE
A54: Daylon | B54: Walton | C54: daylon.walton@iconagility.com | D54: ICON Agility | E54: Agile Engagement | F54: 9728396263 | G54: Christy's iPhone (personal) | H54: Christy | L54: 2 | M54: Influencer | N54: Company is an Atlassian Platform Partner | O54: Add to Mailing List, Other: Is a lead solution person for ICON agility | P54: Sent Initial Email - 23 Oct - Meeting set for Monday 28 Oct | R54: TRUE | S54: TRUE | T54: TRUE | U54: FALSE | V54: FALSE | X54: =DATE(2024,10,15)+TIME(9,43,21) -> 45580.405 | Y54: Yes | Z54: No | AG54: Scanned | AH54: =DATE(2024,10,15)+TIME(9,44,1) -> 45580.406 | AI54: Texas | AJ54: United States | AK54: Large Solution | AL54: Yes
A55: Daylon | B55: Walton | C55: daylon.walton@iconagility.com | D55: Icon Agility Services | E55: Enterprise Business Agility Strategist | F55: 9728396263 | G55: Kurt's iPhone (personal) | H55: Christy | L55: 3 | M55: Influencer | N55: Primarily works in the Fintech space in the commercial industry. Works with several large well-known companies. ￼ Their primary businesses around agile coaching, approximately 99% of their business. | O55: Other: Agile coaching | P55: Some interest and discussion about pain points and/or LSA solution - LinkedIn connection called and left VM to set up meeting to reconnect | R55: TRUE | S55: TRUE | T55: TRUE | U55: FALSE | V55: FALSE | X55: =DATE(2024,10,14)+TIME(12,17,55) -> 45579.512 | Y55: Yes | Z55: Yes | AA55: Not Applicable | AB55: No | AD55: Dallas | AF55: completed | AG55: Business card | AH55: =DATE(2024,10,14)+TIME(12,27,58) -> 45579.519 | AK55: Large Solution | AL55: Yes
A56: Akiyo | B56: Urano | C56: akiyo.urano@iconatg.com | D56: Icon ATG | E56: Senior agile coach | F56: 7039739033 | G56: Mike's iPhone (personal) | H56: Mike | L56: 3 | M56: Influencer | N56: Interested in case studies, probably just learning more | O56: Add to Mailing List | P56: EMAIL_PARTNER_LOW | R56: TRUE | S56: TRUE | T56: TRUE | U56: FALSE | V56: FALSE | X56: =DATE(2024,10,15)+TIME(15,29,49) -> 45580.646 | Y56: Yes | Z56: No | AG56: Scanned | AH56: =DATE(2024,10,15)+TIME(17,41,17) -> 45580.737 | AI56: Virginia | AJ56: United States | AK56: Large Solution | AL56: Yes
A57: Alexandra | B57: Dudzinska | C57: aleksandra.dudzinska@gmail.com | D57: Independent | E57: PM | F57: 0031651133749 | G57: Taylor's iPhone (personal) | L57: 1 | R57: FALSE | S57: FALSE | T57: TRUE | U57: FALSE | V57: FALSE | X57: =DATE(2024,10,15)+TIME(10,25,25) -> 45580.434 | Y57: No | AG57: Scanned | AH57: =DATE(2024,10,15)+TIME(10,25,31) -> 45580.434 | AJ57: The Netherlands | AK57: Large Solution | AL57: Yes
A58: Vijay | B58: Reddy | C58: vijay.reddy@infosys.com | D58: Infosys Limited | E58: Enterprise Agile Transformation Coach | F58: 8474522777 | G58: iPad Mini (LSA/Keith) | H58: Larry | I58: Yes, on 11/26 | L58: 3 | M58: Influencer | N58: Larry gave website analysis for infosys.com…. Says he is also interested in EA services. Got book copy. | O58: Needs Technical Data, Send Literature | R58: FALSE | S58: TRUE | T58: TRUE | U58: FALSE | V58: FALSE | X58: =DATE(2024,10,15)+TIME(15,12,15) -> 45580.634 | Y58: Yes | Z58: No | AG58: Scanned | AH58: =DATE(2024,10,15)+TIME(15,18,2) -> 45580.638 | AI58: Illinois | AJ58: United States | AK58: Large Solution | AL58: Yes
A59: Doug Parente | C59: d.parente@itegratedintelsolutions.com | D59: Integrated Intel Solutions | H59: Hari | L59: 1 | N59: Collected contact info after last day SAFe gov session | T59: TRUE | U59: FALSE | V59: FALSE
A60: Greg Wallace | C60: gwallace@inteprosfed.com | D60: IntePros Federal | H60: Hari | L60: 1 | N60: Collected contact info after last day SAFe gov session | T60: TRUE | U60: FALSE | V60: FALSE
A61: Anastrasiia | B61: Tyshchenko | C61: atyshchenko@jackhenry.com | D61: Jack Henry | E61: Scrum Master | F61: 6158017760 | G61: iPad Mini (LSA/Mike) | H61: Hari | L61: 1 | M61: Influencer | N61: Was recorded for interview | O61: Add to Mailing List | R61: FALSE | S61: FALSE | T61: TRUE | U61: FALSE | V61: FALSE | X61: =DATE(2024,10,15)+TIME(10,16,47) -> 45580.428 | Y61: Yes | Z61: No | AG61: Scanned | AH61: =DATE(2024,10,15)+TIME(17,43,48) -> 45580.739 | AI61: Colorado | AJ61: United States | AK61: Large Solution | AL61: Yes
A62: Mark | B62: Moskovitz | C62: mark.moskovitz@jamf.com | D62: Jamf | E62: Director, Agile Delivery | F62: 312-718-6062 | G62: Christy's iPhone (personal) | H62: Christy | L62: 1 | M62: Other: Jamf | N62: Security software focused on Mac OS - we used to use this. | O62: Add to Mailing List | P62: Sent Initial Email - 23 Oct | R62: TRUE | S62: TRUE | T62: TRUE | U62: FALSE | V62: FALSE | X62: =DATE(2024,10,14)+TIME(16,37,47) -> 45579.693 | Y62: Yes | Z62: No | AG62: Scanned | AH62: =DATE(2024,10,14)+TIME(16,38,19) -> 45579.693 | AI62: New Jersey | AJ62: United States | AK62: Large Solution | AL62: Yes
A63: Alan | B63: Hammond | C63: alan.hammond@chase.com | D63: JPMorgan Chase | E63: VP Technology | F63: 6146200281 | G63: Mike's iPhone (personal) | H63: Mike | L63: 4 | M63: Decision maker | N63: Quick discussion , follow up if possible on Digital Formula , need to learn more about pain points | O63: Add to Mailing List | P63: EMAIL_CLIENT_HIGH - Send email asking for follow-up discussion; recapd discussion, especially pain points discussed; attach usual table insert | R63: TRUE | S63: TRUE | T63: TRUE | U63: TRUE | V63: TRUE | X63: =DATE(2024,10,15)+TIME(10,31,11) -> 45580.438 | Y63: Yes | Z63: No | AG63: Scanned | AH63: =DATE(2024,10,15)+TIME(11,6,41) -> 45580.463 | AI63: Ohio | AJ63: United States | AK63: Large Solution | AL63: Yes
A64: Brenda | B64: Dixon | C64: bspatt04@gmail.com | D64: Kapitus | E64: Scrum Master | F64: 5712135904 | G64: Taylor's iPhone (personal) | H64: Dani | L64: 4 | M64: Influencer | N64: Small business lending firm. Excited about the agile/EA combined approach. Excited about assessments | O64: Send Literature, Add to Mailing List, Other: Contact | P64: sending case studies and reaching out to explore pain points | R64: FALSE | S64: FALSE | T64: TRUE | U64: TRUE | V64: TRUE | X64: =DATE(2024,10,15)+TIME(11,38,2) -> 45580.485 | Y64: Yes | Z64: Yes | AA64: Immediately | AB64: Yes | AG64: Scanned | AH64: =DATE(2024,10,15)+TIME(11,47,58) -> 45580.492 | AI64: Virginia | AJ64: United States | AK64: Large Solution | AL64: Yes
A65: Michael Gerke | C65: michael.gerke@l3harris.com | D65: L3 Harris | H65: Hari | L65: 1 | N65: Collected contact info after last day SAFe gov session | T65: TRUE | U65: FALSE | V65: FALSE
A66: Nick | B66: Reidy | C66: nick.reidy@allegion.com | D66: L3Harris | E66: Software Manager, Release Train Engineer | F66: 7196455300 | G66: iPad Mini (LSA/Keith) | H66: Dani | L66: 1 | M66: Decision maker | N66: Video. Friend of Dani and Shawn. | O66: N/A | R66: FALSE | S66: FALSE | T66: TRUE | U66: FALSE | V66: FALSE | X66: =DATE(2024,10,15)+TIME(9,3,16) -> 45580.377 | Y66: Yes | Z66: No | AG66: Scanned | AH66: =DATE(2024,10,15)+TIME(9,3,47) -> 45580.378 | AI66: Colorado | AJ66: United States | AK66: Large Solution | AL66: Yes
A67: Bruce | B67: Nix | C67: bruce.nix@nttdata.com | D67: Launch by NTT DATA | E67: Specialty Client Partner | F67: 19016056996 | G67: iPad Mini (LSA/Keith) | H67: Larry | I67: Email bounced 11/26 | L67: 3 | M67: Budget authority | N67: Gave a book | O67: Other: Connect | R67: FALSE | S67: TRUE | T67: TRUE | U67: FALSE | V67: FALSE | X67: =DATE(2024,10,15)+TIME(14,13,17) -> 45580.593 | Y67: Yes | Z67: No | AG67: Scanned | AH67: =DATE(2024,10,15)+TIME(14,15,47) -> 45580.594 | AI67: Alabama | AJ67: United States | AK67: Large Solution | AL67: Yes
A68: Josiah | B68: Smith | C68: smith@josiahsvision.com | D68: Learning Tree International | E68: Marketing Project Manager | F68: 3018483510 | G68: iPad Mini (LSA/Keith) | L68: 1 | M68: Influencer | O68: Add to Mailing List | R68: FALSE | S68: FALSE | T68: TRUE | U68: FALSE | V68: FALSE | X68: =DATE(2024,10,16)+TIME(12,40,27) -> 45581.528 | Y68: Yes | Z68: No | AG68: Scanned | AH68: =DATE(2024,10,16)+TIME(13,4,15) -> 45581.545 | AI68: Maryland | AJ68: United States | AK68: Large Solution | AL68: Yes
A69: Joseph | B69: Marina | C69: jmarina@lmi.org | D69: LMI | E69: Fellow, Agile Coach | F69: 2107731114 | G69: iPad Mini (LSA/Keith) | H69: Larry | I69: Yes, on 11/26 | L69: 4 | M69: Influencer | N69: Gave a book | O69: Other: UX quantification needs , add to linkedin | R69: FALSE | S69: TRUE | T69: TRUE | U69: TRUE | V69: TRUE | X69: =DATE(2024,10,15)+TIME(10,14,53) -> 45580.427 | Y69: Yes | Z69: Yes | AA69: Not Applicable | AB69: Not Applicable | AG69: Scanned | AH69: =DATE(2024,10,15)+TIME(11,22,24) -> 45580.474 | AI69: Texas | AJ69: United States | AK69: Large Solution | AL69: Yes
A70: Lauren | B70: Chambers | C70: lauren.e.chambers@lmco.com | D70: Lockheed Martin | E70: Release Train Engineer | F70: 7203855764 | G70: Christy's iPhone (personal) | H70: Christy | L70: 2 | M70: Influencer | N70: Works onsite supporting customers for LM; also was in SAFe gov session | O70: Add to Mailing List, Other: Wants slides from Eek | P70: Sent Initial Email - 23 Oct | R70: TRUE | S70: TRUE | T70: TRUE | U70: FALSE | V70: FALSE | X70: =DATE(2024,10,14)+TIME(11,2,32) -> 45579.46 | Y70: Yes | Z70: No | AG70: Scanned | AH70: =DATE(2024,10,14)+TIME(11,3,30) -> 45579.461 | AI70: Colorado | AJ70: United States | AK70: Large Solution | AL70: Yes
A71: Lynn Johnson | C71: lynn.johnson@mag.us | D71: MAG Aerospace | H71: Hari | L71: 1 | N71: Collected contact info after last day SAFe gov session | T71: TRUE | U71: FALSE | V71: FALSE
A72: Michelle Hauer | C72: mshauer@mt.gov | D72: MT DOT | H72: Hari | L72: 1 | N72: Collected contact info after last day SAFe gov session | T72: TRUE | U72: FALSE | V72: FALSE
A73: Shenandoah Speers | C73: shenandoah.speers@nasa.gov | D73: NASA | H73: Hari | L73: 1 | N73: Collected contact info after last day SAFe gov session | T73: TRUE | U73: FALSE | V73: FALSE
A74: Denise | B74: Amling | C74: denise.t.amling@nasa.gov | D74: NASA | E74: Agile Coach | F74: 9493105907 | G74: iPad Mini (LSA/Keith) | H74: Mike | L74: 4 | M74: Influencer | N74: Took the app rat assessment. Working on beginning stages of a new app inventory system at nasa. Curious if alfabet is fedramp. Follow up with her. | O74: Add to Mailing List, Schedule Demo | P74: Keith sent email to Denise. | Q74: Do I need one? | R74: TRUE | S74: TRUE | T74: TRUE | U74: TRUE | V74: TRUE | X74: =DATE(2024,10,15)+TIME(11,59,16) -> 45580.499 | Y74: Yes | Z74: Yes | AA74: Not Applicable | AB74: Not Applicable | AG74: Scanned | AH74: =DATE(2024,10,15)+TIME(12,15,10) -> 45580.511 | AI74: Virginia | AJ74: United States | AK74: Large Solution | AL74: Yes
A75: Cori | B75: Creran | C75: cori.creran@nationalgrid.com | D75: National Grid | E75: Manager, Portfolio Planning | F75: 603-801-2139 | G75: Mike's iPhone (personal) | H75: Mike | L75: 5 | N75: See William Leach | P75: cc on William email | Q75: see william | R75: TRUE | S75: TRUE | T75: TRUE | U75: TRUE | V75: TRUE | X75: =DATE(2024,10,17)+TIME(14,28,3) -> 45582.603 | Y75: No | AG75: Scanned | AH75: =DATE(2024,10,17)+TIME(14,28,9) -> 45582.603 | AI75: New Hampshire | AJ75: United States | AK75: Large Solution | AL75: Yes
A76: William | B76: Leach | C76: william.leach@nationalgrid.com | D76: National Grid | E76: Director | F76: 4806202483 | G76: Mike's iPhone (personal) | H76: Mike | L76: 5 | N76: Met during LPM workshop day. Discussed their lean portfolio re-organization approach on the flipchart, and listened to their pain points around getting data from Alfabet. Discussed that an effective EA should help summarize key data for LPM dev/maintenance activities, and William sent me an email asking for an example of a model-based portfolio canvas | P76: EMAIL_CLIENT_CUSTOM - Develop demo assets in ARIS. Make the messaging easy to consume, e.g., 2page talkbook, follow-up with email and call(s) to get a meeting for next steps. Cc: Cori, Dani, Christy | Q76: https://leanscaledarchitects.atlassian.net/browse/PIPE-396 | R76: TRUE | S76: TRUE | T76: TRUE | U76: TRUE | V76: TRUE | X76: =DATE(2024,10,17)+TIME(14,27,51) -> 45582.603 | Y76: No | AG76: Scanned | AH76: =DATE(2024,10,17)+TIME(14,27,58) -> 45582.603 | AI76: New York | AJ76: United States | AK76: Large Solution | AL76: Yes
A77: Dave | B77: Turner | C77: david.p.turner.civ@us.navy.mil | D77: NAVAIR | E77: Release Manager | G77: Kurt's iPhone (personal) /Taylor's iPhone (personal) | H77: Mike | L77: 5 | M77: Influencer | N77: Replacing Kimberly Wade. Know each other for a long time. Needs help with tooling. Retired 26 year marine who retired in 2013.. At China Lake. From Canton Ohio. (KG) | O77: Needs Technical Data, Send Literature, Add to Mailing List, Schedule Demo | P77: Do not contact at this time, work through chain of command, starting with Kim. Hot near-term demand / follow-up interest indicated, could lead to opportunities <60 days. Kimberly / Dave will ask for a follow-up meeting on week of Oct 21. NOTE: Mike already sent promised case study (automated quads) over LinkedIn Mike and Dani had call today (10/23) with Kimberly and Dave to reengage on moving this forward (KG) | Q77: none | R77: TRUE | S77: TRUE | T77: TRUE | U77: TRUE | V77: TRUE | X77: =DATE(2024,10,15)+TIME(16,31,50) -> 45580.689 | Y77: Yes | Z77: Yes | AA77: Within 3 months | AB77: Not Applicable | AF77: completed | AG77: Business card | AH77: =DATE(2024,10,15)+TIME(17,19,30) -> 45580.722 | AK77: Large Solution | AL77: Yes
A78: Lindsey | B78: Benson | C78: lindsey.a.benson2.civ@us.navy.mil | D78: NAVAIR | E78: RTE | F78: 760-793-8291 | G78: iPad Mini (LSA/Keith) | H78: Mike | L78: 5 | P78: Do not contact at this time , work through chain of command, starting with Kim | Q78: none | R78: TRUE | S78: TRUE | T78: TRUE | U78: FALSE | V78: FALSE | X78: =DATE(2024,10,16)+TIME(10,14,55) -> 45581.427 | Y78: No | AG78: Scanned | AH78: =DATE(2024,10,16)+TIME(10,15,0) -> 45581.427 | AI78: California | AJ78: United States | AK78: Large Solution | AL78: Yes
A79: Samuel | B79: Celestine | C79: samuel.r.celestine.civ@us.navy.mil | D79: NAVAIR | E79: RTE | F79: RTE | G79: iPad Mini (LSA/Keith) | H79: Mike | L79: 5 | P79: Do not contact at this time , work through chain of command, starting with Kim | Q79: none | R79: TRUE | S79: TRUE | T79: TRUE | U79: FALSE | V79: FALSE | X79: =DATE(2024,10,16)+TIME(10,14,48) -> 45581.427 | Y79: No | AG79: Scanned | AH79: =DATE(2024,10,16)+TIME(10,14,54) -> 45581.427 | AI79: California | AJ79: United States | AK79: Large Solution | AL79: Yes
A80: Joshua | B80: Derouse | C80: joshua.m.derousse.civ@us.navy.mil | D80: NAVAIR | E80: Mission System PM | F80: Mission System PM | G80: iPad Mini (LSA/Keith) | H80: Mike | L80: 5 | P80: Do not contact at this time , work through chain of command, starting with Kim | Q80: none | R80: TRUE | S80: TRUE | T80: TRUE | U80: FALSE | V80: FALSE | X80: =DATE(2024,10,16)+TIME(10,15,0) -> 45581.427 | Y80: No | AG80: Scanned | AH80: =DATE(2024,10,16)+TIME(10,15,5) -> 45581.427 | AI80: California | AJ80: United States | AK80: Large Solution | AL80: Yes
A81: Pierrette | B81: Njikang | C81: pierrette_njikang@navyfederal.org | D81: Navy Federal Credit Union | E81: Scrum Master | F81: 5716511147 | G81: Taylor's iPhone (personal) | H81: Mike | L81: 4 | M81: Influencer | N81: Likes the EA/Agile approach. Send case studies on GRC, modeling, quads, agile | O81: Send Literature, Add to Mailing List, Other: Contact | P81: They want to read/talk more about our case studies, specifically Process-Aligned Risk and Compliance Automation, Automated Quads, Agile Assessment and Improvement, Alfabet ITPM (Federated Bank), and Effective Agility. | R81: FALSE | S81: FALSE | T81: TRUE | U81: TRUE | V81: FALSE | X81: =DATE(2024,10,15)+TIME(10,17,21) -> 45580.429 | Y81: Yes | Z81: No | AG81: Scanned | AH81: =DATE(2024,10,17)+TIME(11,27,23) -> 45582.477 | AI81: Virginia | AJ81: United States | AK81: Large Solution | AL81: Yes
A82: Eva | B82: Owusu | C82: eva_owusu@navyfederal.org | D82: Navy Federal Credit Union | E82: Lead System Analyst | F82: 5715850177 | G82: Taylor's iPhone (personal) | H82: Mike | L82: 4 | M82: Influencer | N82: Likes the EA/Agile approach. Send case studies on GRC, modeling, quads, agile | O82: Send Literature, Add to Mailing List, Other: Contact | P82: They want to read/talk more about our case studies, specifically Process-Aligned Risk and Compliance Automation, Automated Quads, Agile Assessment and Improvement, Alfabet ITPM (Federated Bank), and Effective Agility. | R82: FALSE | S82: FALSE | T82: TRUE | U82: TRUE | V82: TRUE | X82: =DATE(2024,10,15)+TIME(10,17,35) -> 45580.429 | Y82: No | AG82: Scanned | AH82: =DATE(2024,10,15)+TIME(10,17,46) -> 45580.429 | AI82: Virginia | AJ82: United States | AK82: Large Solution | AL82: Yes
A83: Jessica | B83: Crocker | C83: jessica_crocker@navyfederal.org | D83: Navy Federal Credit Union | E83: Scrum Master | F83: 5716091755 | G83: Taylor's iPhone (personal) | H83: Mike | L83: 4 | M83: Influencer | N83: Likes the EA/Agile approach. Send case studies on GRC, modeling, quads, agile | O83: Send Literature, Add to Mailing List, Other: Contact | P83: They want to read/talk more about our case studies, specifically Process-Aligned Risk and Compliance Automation, Automated Quads, Agile Assessment and Improvement, Alfabet ITPM (Federated Bank), and Effective Agility. --- Requested LinkedIn Connection - no response to Inmail - called and left vm to reconnect | R83: FALSE | S83: FALSE | T83: TRUE | U83: TRUE | V83: FALSE | X83: =DATE(2024,10,17)+TIME(11,57,39) -> 45582.498 | Y83: No | AG83: Scanned | AH83: =DATE(2024,10,17)+TIME(11,57,43) -> 45582.498 | AI83: Maryland | AJ83: United States | AK83: Large Solution | AL83: Yes
A84: Sheila | B84: Olds | C84: solds@newscorp.com | D84: News Corp | E84: DIRECTOR, ENTERPRISE AGILE COACH | F84: 704-609-1838 | G84: iPad Mini (LSA/Keith) | H84: Christy | L84: 2 | P84: Sent Initial Email - 23 Oct | R84: TRUE | S84: TRUE | T84: TRUE | U84: FALSE | V84: FALSE | X84: =DATE(2024,10,16)+TIME(10,18,8) -> 45581.429 | Y84: No | AG84: Scanned | AH84: =DATE(2024,10,16)+TIME(10,27,47) -> 45581.436 | AI84: North Carolina | AJ84: United States | AK84: Large Solution | AL84: Yes
A85: Pras | B85: Khuon | C85: prasna.khuon@ngc.com | D85: Northrop Grumman | E85: Agile Coach | F85: 6307282488 | G85: Mike's iPhone (personal) | H85: Christy | L85: 2 | M85: Influencer | N85: Discussion of some high level LSA services , not sure of interest - collaborate with Dani | O85: Add to Mailing List | P85: Sent Initial Email - 23 Oct | R85: TRUE | S85: TRUE | T85: TRUE | U85: FALSE | V85: FALSE | X85: =DATE(2024,10,15)+TIME(15,17,9) -> 45580.637 | Y85: Yes | Z85: No | AG85: Scanned | AH85: =DATE(2024,10,15)+TIME(17,40,28) -> 45580.736 | AI85: Illinois | AJ85: United States | AK85: Large Solution | AL85: Yes
A86: Suzette | B86: Johnson | C86: suzette.johnson@ngc.com | D86: Northrop Grumman | E86: NG Fellow | F86: 410-746-7987 | G86: iPad Mini (LSA/Mike) | H86: Christy | L86: 5 | M86: Influencer | N86: Taylor - work with Dani to discuss this need with Suzette | O86: Add to Mailing List | P86: Reading between the lines, they need some process modeling/intelligence work too - LinkedIn connection - sent in mail - no response. --called and left VM to set up meeting to reconnect | R86: FALSE | S86: FALSE | T86: TRUE | U86: TRUE | V86: TRUE | X86: =DATE(2024,10,15)+TIME(11,14,41) -> 45580.469 | Y86: Yes | Z86: No | AG86: Scanned | AH86: =DATE(2024,10,15)+TIME(17,43,48) -> 45580.739 | AI86: Maryland | AJ86: United States | AK86: Large Solution | AL86: Yes
A87: Takenori | B87: Osada | C87: takenori.osada@nttdata.com | D87: NTT DATA Japan Corporation | E87: Tecnical Grade | F87: +818020151828 | G87: iPad Mini (LSA/Mike) | H87: Hari | L87: 1 | M87: Influencer | N87: Was in interview | O87: Add to Mailing List | R87: FALSE | S87: FALSE | T87: TRUE | U87: FALSE | V87: FALSE | X87: =DATE(2024,10,15)+TIME(10,33,22) -> 45580.44 | Y87: Yes | Z87: No | AG87: Scanned | AH87: =DATE(2024,10,15)+TIME(17,43,48) -> 45580.739 | AJ87: Japan | AK87: Large Solution | AL87: Yes
A88: Ajay Vohra | C88: ajvohra0!@gmail.com | D88: OCC | H88: Hari | L88: 1 | N88: Collected contact info after last day SAFe gov session | T88: TRUE | U88: FALSE | V88: FALSE
A89: Alyssa | B89: Catalano | C89: alyssa.catalano@panasonic.aero | D89: Panasonic Avionics | E89: Director -Project Management | F89: 949-690-8070 | G89: Mike's iPhone (personal) | H89: Mike | L89: 4 | M89: Influencer | N89: Met at lunch on LPM workshop day. Panasonic , developing entertainment systems for aircraft , got a few ARTs, leadership not getting agile , competing “frameworks”, software dev using it … advised on improving principle 7 & showing success in key areas, and making it less about frameworks and more about outcomes and results .. | O89: Add to Mailing List | P89: EMAIL_CLIENT_CUSTOM - Send the same LPM 2-page talkbook (National Grid) to Alyssa and see if that helps spark discussion around Panasonic pain points ; insert usual links table | Q89: https://leanscaledarchitects.atlassian.net/browse/PIPE-396 | R89: TRUE | S89: TRUE | T89: TRUE | U89: TRUE | V89: TRUE | X89: =DATE(2024,10,17)+TIME(13,1,48) -> 45582.543 | Y89: Yes | Z89: No | AG89: Scanned | AH89: =DATE(2024,10,17)+TIME(13,10,43) -> 45582.549 | AI89: California | AJ89: United States | AK89: Large Solution | AL89: Yes
A90: Dan Palmer | C90: dan.palmer@paradyme.us | D90: Paradyme | H90: Hari | L90: 1 | N90: Collected contact info after last day SAFe gov session | T90: TRUE | U90: FALSE | V90: FALSE
A91: Bruce | B91: Friedman | C91: bfriedman@peraton.com | D91: Peraton | E91: Agile Coach | G91: Kurt's iPhone (personal) | H91: Kurt | L91: 2 | M91: Other: Retired but teaches safe courses for Peraton | N91: Said Peraton is engaged with a lot of different government contracting work. He lives in Reston Virginia and said that they are doing work with NASA and Army. I will need to get a further contact to be able to connect and get a stronger lead. | O91: Other: Said he could connect me to other contacts | P91: Some discussion about pain points and/or LSA solution. He really couldn't speak to what else we could help Peraton with but he may be a possible connection on helping with connecting us to Peraton as a way into the Missile Defense Agency. | R91: TRUE | S91: TRUE | T91: TRUE | U91: FALSE | V91: FALSE | X91: =DATE(2024,10,14)+TIME(15,10,3) -> 45579.632 | Y91: Yes | Z91: No | AF91: completed | AG91: Business card | AH91: =DATE(2024,10,14)+TIME(16,49,8) -> 45579.701 | AK91: Large Solution | AL91: Yes
A92: Catherine | B92: Yeagle | C92: cdyeagle@gmail.com | D92: Phaedon | E92: Product Manager / Owner | F92: 5713315860 | G92: Christy's iPhone (personal) | H92: Christy | L92: 2 | M92: Other: Agile Practitioner | N92: Spoke about company phaedon and they are using agile, so may be more of a potential for partnership/teaming later on work. | P92: Sent Initial Email - 23 Oct | R92: TRUE | S92: TRUE | T92: TRUE | U92: FALSE | V92: FALSE | X92: =DATE(2024,10,15)+TIME(10,48,35) -> 45580.45 | Y92: No | AG92: Scanned | AH92: =DATE(2024,10,15)+TIME(10,55,58) -> 45580.456 | AI92: Virginia | AJ92: United States | AK92: Large Solution | AL92: Yes
A93: Henry | B93: Jiang | C93: anke.jiang@plus3it.com | D93: Plus3 IT Solutions | E93: Release Train Engineer | F93: 2024688285 | G93: iPad Mini (LSA/Keith) | H93: Hari | L93: 1 | M93: Influencer | O93: Add to Mailing List | R93: FALSE | S93: FALSE | T93: TRUE | U93: FALSE | V93: FALSE | X93: =DATE(2024,10,16)+TIME(13,4,21) -> 45581.545 | Y93: Yes | Z93: No | AG93: Scanned | AH93: =DATE(2024,10,16)+TIME(13,4,35) -> 45581.545 | AI93: Virginia | AJ93: United States | AK93: Large Solution | AL93: Yes
A94: Todd | B94: Sheridan | C94: todd.sheridan@pnc.com | D94: PNC Bank | E94: Senior Agile Coach | F94: 720-454-6342 | G94: Christy's iPhone (personal) | H94: Christy | L94: 3 | M94: Influencer | N94: Little initial interest, but Mike to coordinate other contacts / angles in a response with Christy | O94: Add to Mailing List | P94: Sent Initial Email - 23 Oct - requested LinkedIn connection - no response, called and left VM to set up meeting to reconnect | R94: TRUE | S94: TRUE | T94: TRUE | U94: FALSE | V94: FALSE | X94: =DATE(2024,10,15)+TIME(13,25,2) -> 45580.559 | Y94: Yes | Z94: No | AA94: Not Applicable | AB94: Not Applicable | AG94: Scanned | AH94: =DATE(2024,10,15)+TIME(13,25,19) -> 45580.559 | AI94: Colorado | AJ94: United States | AK94: Large Solution | AL94: Yes
A95: Ken | B95: Presutti | C95: kenneth.presutti@pnc.com | D95: PNC Bank | E95: Coach | F95: (412) 607-0402 | G95: Kurt's iPhone (personal) | H95: Mike | L95: 3 | M95: Other: Agile Coach | N95: He works for PNC as an RTE and offered to help make connections. I mentioned we also have someone who has contacts at PNC but welcome any additional information | O95: Send Literature, Add to Mailing List | P95: Some interest and discussion about pain points and/or LSA solution. Connect with him to try to get further connection and discussions at PNC. | R95: TRUE | S95: TRUE | T95: TRUE | U95: TRUE | V95: TRUE | X95: =DATE(2024,10,14)+TIME(22,0,3) -> 45579.917 | Y95: Yes | Z95: No | AC95: +14124070402 | AF95: completed | AG95: Business card | AH95: =DATE(2024,10,15)+TIME(2,42,20) -> 45580.113 | AK95: Large Solution | AL95: Yes
A96: Harold | B96: Wagner | C96: harold.wagner@cprime.com | D96: Process Velocity, Inc. | E96: Principal Consultant | F96: 4693521366 | G96: iPad Mini (LSA/Keith) | H96: Keith | L96: 3 | M96: Other: SPC independent | N96: Was interested in our solutions overall. Independent safe trainer spc. Looking just to see how different companies can help on his projects when needed. | O96: Add to Mailing List | P96: Email sent | R96: TRUE | S96: TRUE | T96: TRUE | U96: FALSE | V96: FALSE | X96: =DATE(2024,10,15)+TIME(11,54,19) -> 45580.496 | Y96: Yes | Z96: No | AG96: Scanned | AH96: =DATE(2024,10,15)+TIME(11,58,41) -> 45580.499 | AI96: Texas | AJ96: United States | AK96: Large Solution | AL96: Yes
A97: Angela | B97: Campbell | C97: angela.campbell@progress.com | D97: Progress Software | E97: Senior Director of Transformation | F97: 6035828980 | G97: iPad Tiny (LSA/Mike) | H97: Hari | L97: 4 | M97: Influencer | O97: Needs Technical Data, Add to Mailing List | P97: Progress Software Corporation is an American public company that produces software for creating and deploying business applications. Founded in Burlington, Massachusetts with offices in 16 countries, the company posted revenues of $531.3 million in 2021 and employs approximately 2100 people. Send general TEMPLATE_CUSTOMER_HIGH (4/5 template) with LPM talkbook pdf Send draft to Mike/Dani for feedback | R97: FALSE | S97: FALSE | T97: TRUE | U97: TRUE | V97: TRUE | X97: =DATE(2024,10,16)+TIME(10,8,5) -> 45581.422 | Y97: Yes | Z97: Yes | AA97: Not Applicable | AB97: Not Applicable | AG97: Scanned | AH97: =DATE(2024,10,16)+TIME(10,14,3) -> 45581.426 | AI97: Massachusetts | AJ97: United States | AK97: Large Solution | AL97: Yes
A98: Kimberly | B98: Bogden | C98: bogden_kim@hotmail.com | D98: Prudential | E98: Lead, Scrum Master | F98: 908-468-9585 | G98: Mike's iPhone (personal) | H98: Mike | L98: 2 | M98: Other: Just chatting about their already mature ARTs | N98: Seemed to have an answer for everything , didn’t need help …? | O98: Add to Mailing List, Other: AD | P98: EMAIL_CLIENT_LOW - Send email asking for follow-up discussion; attach usual table insert | R98: TRUE | S98: TRUE | T98: TRUE | U98: TRUE | V98: TRUE | X98: =DATE(2024,10,15)+TIME(10,39,45) -> 45580.444 | Y98: Yes | Z98: No | AG98: Scanned | AH98: =DATE(2024,10,15)+TIME(11,5,32) -> 45580.462 | AI98: New Jersey | AJ98: United States | AK98: Large Solution | AL98: Yes
A99: Melody | B99: Gil | C99: melody.gil@prudential.com | D99: Prudential | E99: Scrum Master | F99: +12019605202 | G99: iPad Mini (LSA/Keith) | H99: Mike | L99: 1 | M99: Influencer | O99: Add to Mailing List | R99: TRUE | S99: TRUE | T99: TRUE | U99: TRUE | V99: FALSE | X99: =DATE(2024,10,16)+TIME(12,37,19) -> 45581.526 | Y99: Yes | AG99: Scanned | AH99: =DATE(2024,10,16)+TIME(12,37,53) -> 45581.526 | AI99: New Jersey | AJ99: United States | AK99: Large Solution | AL99: Yes
A100: Donald | B100: Brown | C100: donald.brown@prudential.com | D100: Prudential Financial | E100: Release Train Engineer | F100: 862-703-6566 | G100: iPad Tiny (LSA/Mike) | H100: Mike | L100: 3 | M100: Other: RTE | N100: Gave copy of robins book. He is heavily focused on devops. Mike thought he was just curious and fishing for a job. | O100: Send Literature | P100: EMAIL_CLIENT_LOW - Send email asking for follow-up discussion; attach usual table insert | R100: TRUE | S100: TRUE | T100: TRUE | U100: TRUE | V100: TRUE | X100: =DATE(2024,10,16)+TIME(10,10,32) -> 45581.424 | Y100: Yes | AG100: Scanned | AH100: =DATE(2024,10,16)+TIME(10,14,3) -> 45581.426 | AI100: Pennsylvania | AJ100: United States | AK100: Large Solution | AL100: Yes
...

Sheet Post-conf leads (Round 1)
A1: First Name | B1: Last Name | C1: Email Address | D1: Company Name | E1: Title | F1: Mobile Phone Number | G1: Device used to scan badge | H1: Contact Owner | I1: Role of this person | J1: DURING-Summit notes | K1: Lead Score | L1: DURING-summit follow-up notes | M1: POST-Summit Follow-up Notes | N1: POST-Summit Follow-up Jira tickets | O1: POST-Summit lead qual & follow-up planning done | P1: POST-Summit follow-ups done (week of Oct 21-25) | Q1: Created date/time US/Eastern | R1: Qualified | S1: Is the person currently evaluating solutions related to [specific problem/industry]? | T1: What is the timeframe for choosing a solution? | U1: Is there a budget for this business need? | V1: Work Phone Number | W1: Work City | X1: Work State | Y1: Lead Transcription Status | Z1: Lead Source | AA1: Last Update US/Eastern | AB1: What State do you reside in: | AC1: Country you reside in: | AD1: Sponsorship Level | AE1: Event Sponsor
A2: Dave | B2: Turner | C2: david.p.turner.civ@us.navy.mil | D2: NAVAIR | E2: Release Manager | G2: Kurt's iPhone (personal) /Taylor's iPhone (personal) | H2: Kurt | I2: Influencer | J2: Replacing Kimberly Wade. Know each other for a long time. Needs help with tooling. Retired 26 year marine who retired in 2013.. At China Lake. From Canton Ohio. (KG) | K2: 5 | L2: Needs Technical Data, Send Literature, Add to Mailing List, Schedule Demo | M2: Do not contact at this time, work through chain of command, starting with Kim. Hot near-term demand / follow-up interest indicated, could lead to opportunities <60 days. Kimberly / Dave will ask for a follow-up meeting on week of Oct 21. NOTE: Mike already sent promised case study (automated quads) over LinkedIn Mike and Dani had call today (10/23) with Kimberly and Dave to reengage on moving this forward (KG) | N2: none | O2: TRUE | P2: TRUE | Q2: =DATE(2024,10,15)+TIME(16,31,50) -> 45580.689 | R2: Yes | S2: Yes | T2: Within 3 months | U2: Not Applicable | Y2: completed | Z2: Business card | AA2: =DATE(2024,10,15)+TIME(17,19,30) -> 45580.722 | AD2: Large Solution | AE2: Yes
A3: Gerd | B3: Wessling | C3: gerd.wessling@scagilize.de | D3: Scagilize GmbH | E3: Founder & Managing Director | F3: +491704445773 | G3: Christy's iPhone (personal) / Kurt's Iphone (personal) | H3: Christy | I3: Budget authority | J3: Wants to do LinkedIn posts with content. Owner of the company. Interested in expanding his operations globally. He wanted our slides from Eek Monsters presentation and was to tag us in a linked in post | K3: 5 | L3: Other: Send slides Wants to expand globally with his agile operations. Based in Germany | M3: EMAIL_PARTNER_HIGH: Send email asking for follow-up discussion. Dani sent Gerd our slides and Gerd included us in a LinkedIn post. Seemed very interested in what we do and is interested in expanding his operations gloally. Let's connect on how we can get inserted into the expansion plan. - is going to do the outreach. Dani sent the EEK slides to him and he is looking to expand his operations globally using LSA as a partner (KG)- Sent Email and have meeting set for Thursday morning for initial touch point- good initial meeting - Gerd will reach out to set up meeting in next few weeks to follow up and continue establishing networking opporotunities. ( https://www.scagilize.de/en-gb) | O3: TRUE | P3: TRUE | Q3: =DATE(2024,10,14)+TIME(11,4,21) -> 45579.461 | R3: Yes | S3: Yes | Z3: Scanned | AA3: =DATE(2024,10,14)+TIME(11,5,43) -> 45579.462 | AC3: Germany | AD3: Large Solution | AE3: Yes
A4: Elonia | B4: Taylor | C4: elonia.taylor@bep.gov | D4: Bureau of Engraving and Printing | E4: Sr. IT Project Manager | F4: (817)528-1037 | G4: iPad Mini (LSA/Keith) | H4: Dani | J4: Early in agile implementation; got SES ; want workshops and training. Lead for the program, Mike White introduced. Kurt - submitted RFI for agile coaching previously… Kurt has discussed BEP opportunities with Navy Gold Coast / Business Dev lead | K4: 5 | O4: FALSE | P4: FALSE | Q4: =DATE(2024,10,16)+TIME(13,58,44) -> 45581.582 | R4: No | Z4: Scanned | AA4: =DATE(2024,10,16)+TIME(13,58,57) -> 45581.583 | AB4: Texas | AC4: United States | AD4: Large Solution | AE4: Yes
A5: Lesa | B5: Kennedy | C5: lesa_kennedy@glic.com | D5: Guardian Life Insurance | E5: Enterprise Methodology Coach | F5: 3474329075 | G5: iPad Mini (LSA/Keith) | H5: Dani | I5: Influencer | J5: Send follow up on Business Teams needing support for agile implementation. | K5: 5 | L5: Send Literature, Add to Mailing List | O5: FALSE | P5: FALSE | Q5: =DATE(2024,10,15)+TIME(8,6,27) -> 45580.338 | R5: Yes | S5: Yes | T5: Immediately | U5: Yes | Z5: Scanned | AA5: =DATE(2024,10,15)+TIME(8,8,31) -> 45580.339 | AB5: New York | AC5: United States | AD5: Large Solution | AE5: Yes
A6: Cori | B6: Creran | C6: cori.creran@nationalgrid.com | D6: National Grid | E6: Manager, Portfolio Planning | F6: 603-801-2139 | G6: Mike's iPhone (personal) | H6: Mike | J6: See William Leach | K6: 5 | M6: cc on William email | N6: see william | O6: TRUE | P6: TRUE | Q6: =DATE(2024,10,17)+TIME(14,28,3) -> 45582.603 | R6: No | Z6: Scanned | AA6: =DATE(2024,10,17)+TIME(14,28,9) -> 45582.603 | AB6: New Hampshire | AC6: United States | AD6: Large Solution | AE6: Yes
A7: William | B7: Leach | C7: william.leach@nationalgrid.com | D7: National Grid | E7: Director | F7: 4806202483 | G7: Mike's iPhone (personal) | H7: Mike | J7: Met during LPM workshop day. Discussed their lean portfolio re-organization approach on the flipchart, and listened to their pain points around getting data from Alfabet. Discussed that an effective EA should help summarize key data for LPM dev/maintenance activities, and William sent me an email asking for an example of a model-based portfolio canvas | K7: 5 | M7: EMAIL_CLIENT_CUSTOM - Develop demo assets in ARIS. Make the messaging easy to consume, e.g., 2page talkbook, follow-up with email and call(s) to get a meeting for next steps. Cc: Cori, Dani, Christy | N7: https://leanscaledarchitects.atlassian.net/browse/PIPE-396 | O7: TRUE | P7: TRUE | Q7: =DATE(2024,10,17)+TIME(14,27,51) -> 45582.603 | R7: No | Z7: Scanned | AA7: =DATE(2024,10,17)+TIME(14,27,58) -> 45582.603 | AB7: New York | AC7: United States | AD7: Large Solution | AE7: Yes
A8: Lindsey | B8: Benson | C8: lindsey.a.benson2.civ@us.navy.mil | D8: NAVAIR | E8: RTE | F8: 760-793-8291 | G8: iPad Mini (LSA/Keith) | H8: Mike | K8: 5 | M8: Do not contact at this time , work through chain of command, starting with Kim | N8: none | O8: TRUE | P8: TRUE | Q8: =DATE(2024,10,16)+TIME(10,14,55) -> 45581.427 | R8: No | Z8: Scanned | AA8: =DATE(2024,10,16)+TIME(10,15,0) -> 45581.427 | AB8: California | AC8: United States | AD8: Large Solution | AE8: Yes
A9: Samuel | B9: Celestine | C9: samuel.r.celestine.civ@us.navy.mil | D9: NAVAIR | E9: RTE | F9: RTE | G9: iPad Mini (LSA/Keith) | H9: Mike | K9: 5 | M9: Do not contact at this time , work through chain of command, starting with Kim | N9: none | O9: TRUE | P9: TRUE | Q9: =DATE(2024,10,16)+TIME(10,14,48) -> 45581.427 | R9: No | Z9: Scanned | AA9: =DATE(2024,10,16)+TIME(10,14,54) -> 45581.427 | AB9: California | AC9: United States | AD9: Large Solution | AE9: Yes
A10: Joshua | B10: Derouse | C10: joshua.m.derousse.civ@us.navy.mil | D10: NAVAIR | E10: Mission System PM | F10: Mission System PM | G10: iPad Mini (LSA/Keith) | H10: Mike | K10: 5 | M10: Do not contact at this time , work through chain of command, starting with Kim | N10: none | O10: TRUE | P10: TRUE | Q10: =DATE(2024,10,16)+TIME(10,15,0) -> 45581.427 | R10: No | Z10: Scanned | AA10: =DATE(2024,10,16)+TIME(10,15,5) -> 45581.427 | AB10: California | AC10: United States | AD10: Large Solution | AE10: Yes
A11: Suzette | B11: Johnson | C11: suzette.johnson@ngc.com | D11: Northrop Grumman | E11: NG Fellow | F11: 410-746-7987 | G11: iPad Mini (LSA/Mike) | H11: Taylor | I11: Influencer | J11: Taylor - work with Dani to discuss this need with Suzette | K11: 5 | L11: Add to Mailing List | M11: Reading between the lines, they need some process modeling/intelligence work too | O11: FALSE | P11: FALSE | Q11: =DATE(2024,10,15)+TIME(11,14,41) -> 45580.469 | R11: Yes | S11: No | Z11: Scanned | AA11: =DATE(2024,10,15)+TIME(17,43,48) -> 45580.739 | AB11: Maryland | AC11: United States | AD11: Large Solution | AE11: Yes
A12: Parag | B12: Gupta | C12: parag.gupta@cna.com | D12: CNA | E12: Director, Value Creation | F12: 4379254146 | G12: iPad Mini (LSA/Mike) | H12: Larry | I12: Decision maker | J12: Transformation of legacy systems. Gave a book. | K12: 4 | L12: Send Literature, Add to Mailing List | O12: FALSE | P12: TRUE | Q12: =DATE(2024,10,16)+TIME(11,29,8) -> 45581.479 | R12: Yes | S12: No | Z12: Scanned | AA12: =DATE(2024,10,16)+TIME(11,56,20) -> 45581.497 | AC12: Canada | AD12: Large Solution | AE12: Yes
A13: Paul | B13: Gattis | C13: Bad email address. Sent a LinkedIn Connection | D13: AFSC/SWTP | G13: Kurt's iPhone (personal) | H13: Kurt | I13: Influencer | J13: He is a engineer for a software development department that they stood up. He’s looking to see about the various enterprise architecture and understanding how they’re spending on their IT investments. Also looking at helping to understand more about how they can potentially get the organization to more standardize around the actual way of doing business.￼ | K13: 4 | L13: Needs Technical Data, Send Literature, Add to Mailing List | M13: EMAIL_PARTNER_HIGH: Send email asking for follow-up discussion. Setup a follow-on conversation to help him assess a possible path forward and help the organization with stremlining their SDLC operations and bringing standardized approach to AFSC. 10/21: Sent a LinkedIn Connection since his email address bounced. Waiting on a reply but will follow-up on 10/28 if no response. | O13: TRUE | P13: FALSE | Q13: =DATE(2024,10,15)+TIME(11,49,59) -> 45580.493 | R13: Yes | S13: Yes | T13: Not Applicable | U13: Not Applicable | Y13: transcription incomplete | Z13: Business card | AA13: =DATE(2024,10,15)+TIME(12,19,45) -> 45580.514 | AD13: Large Solution | AE13: Yes
A14: Bhavani | B14: Krishnan | C14: bhavani.krishnan@agilevelocity.com | D14: Agile Velocity | E14: Enterprise Agile Coach | F14: 571.246.0602 | G14: iPad Mini (LSA/Keith) / Kurt's iPhone (personal) | H14: Kurt | I14: Budget authority | J14: Looking for partnership opportunity. Spoke to Kurt. They are in the commercial space and interact with cyber security. They are very interested in looking at their women owned an 8a. Spoke with her and their chief revenue officer James Hawks. | K14: 4 | L14: Other: X | M14: EMAIL_PARTNER_HIGH: Send email asking for follow-up discussion. Setup further discussion on how we can partner and help one another by leveraging their 8a. Meeting scheduled for 10/24/2024 to explore strategic plan and partnering with her and James Hawks | O14: TRUE | P14: TRUE | Q14: =DATE(2024,10,15)+TIME(10,49,18) -> 45580.451 | R14: Yes | Z14: Scanned | AA14: =DATE(2024,10,15)+TIME(11,2,31) -> 45580.46 | AB14: Virginia | AC14: United States | AD14: Large Solution | AE14: Yes
A15: S. Hasnain | B15: Rizvi | C15: hasnain.rizvi@americannational.com | D15: American National Insurance | E15: Agile Transformation Lead | F15: 8184287768 | G15: iPad Mini (LSA/Keith) | H15: Dani | I15: Decision maker | J15: Dani to schedule | K15: 4 | L15: N/A | O15: FALSE | P15: FALSE | Q15: =DATE(2024,10,15)+TIME(13,31,54) -> 45580.564 | R15: Yes | S15: Yes | T15: Immediately | Z15: Scanned | AA15: =DATE(2024,10,15)+TIME(13,33,37) -> 45580.565 | AB15: Texas | AC15: United States | AD15: Large Solution | AE15: Yes
A16: Steve | B16: Brylski | C16: steve.brylski@caci.com | D16: CACI | E16: Agile Transformation Leader/Coach | F16: (571) 291-7450 | G16: Mike's iPhone (personal) | H16: Mike | I16: Influencer | J16: See Chris ham comments | K16: 4 | L16: Add to Mailing List | N16: none | O16: TRUE | P16: TRUE | Q16: =DATE(2024,10,16)+TIME(13,21,24) -> 45581.557 | R16: Yes | S16: No | Z16: Scanned | AA16: =DATE(2024,10,17)+TIME(13,12,29) -> 45582.55 | AB16: Virginia | AC16: United States | AD16: Large Solution | AE16: Yes
A17: Chris | B17: Ham | C17: chris.ham@caci.com | D17: CACI Inc. | E17: Agile Solution Factory Director | F17: 7036253263 | G17: Mike's iPhone (personal) | H17: Mike | I17: Influencer | J17: They spoke to robin, robin mentioned LSA, they came to booth, gave them UX book, and they said they could ‘find a home’ for LSA | K17: 4 | L17: Add to Mailing List | M17: EMAIL_PARTNER_HIGH: follow-up discussion; attach usual table insert; CC: Steve Brylski, Robin, Dani | N17: none | O17: TRUE | P17: TRUE | Q17: =DATE(2024,10,16)+TIME(13,21,29) -> 45581.557 | R17: Yes | S17: No | Z17: Scanned | AA17: =DATE(2024,10,17)+TIME(13,12,2) -> 45582.55 | AB17: Virginia | AC17: United States | AD17: Large Solution | AE17: Yes
A18: Abdul Rasheed | B18: Shaik | C18: abdulrasheed.shaik@fepoc.com | D18: CareFirst | E18: Release Train Engineer | F18: 9493947591 | G18: Mike's iPhone (personal) | H18: Mike | I18: Influencer | J18: Also has OPM as customer . Benefits for OPM. Was interested in various case studies and engaged | K18: 4 | L18: Add to Mailing List | M18: EMAIL_PARTNER_MEDIUM: Send email asking for follow-up discussion; emphasize / call-out OPM case studies. Attach usual table insert | N18: none | O18: TRUE | P18: TRUE | Q18: =DATE(2024,10,15)+TIME(15,47,8) -> 45580.658 | R18: Yes | S18: No | Z18: Scanned | AA18: =DATE(2024,10,15)+TIME(17,38,59) -> 45580.735 | AB18: Virginia | AC18: United States | AD18: Large Solution | AE18: Yes
A19: Erin | B19: Mcclain | C19: erinmccaslun@agilityhealth.com | D19: Agility Health | E19: VP Partner Development | G19: Kurt's iPhone (personal) | H19: Kurt | I19: Other: Partner builder and go to market strategist | J19: Aaron was very interested in helping us use their wheel system and then helping to find ways that we can go to market and lean into each others pipelines and how we can jump on various things together | K19: 4 | L19: Other: Do presentation to help develop our strategy to go after work together, Send Literature, Schedule Demo | M19: EMAIL_PARTNER_HIGH: Send email asking for follow-up discussion. Discussed with Mike and there might be further opportunities for us to synch up on using their wheel system and add further capabilities. Follow-up with a call and explore opportunities together. Meeting scheduled for 10/24/2024 to explore strategic plan and partnering | O19: TRUE | P19: TRUE | Q19: =DATE(2024,10,15)+TIME(13,0,54) -> 45580.542 | R19: Yes | S19: Yes | T19: Not Applicable | U19: Not Applicable | Y19: completed | Z19: Business card | AA19: =DATE(2024,10,15)+TIME(19,37,10) -> 45580.817 | AD19: Large Solution | AE19: Yes
A20: Jacky | B20: Droushoudt | C20: jdroushoudt@pccwglobal.com | D20: Console Connect (HK) Limited | E20: AVP, Product Management (Scrum) | F20: +32494538194 | G20: Christy's iPhone (personal) | H20: Dani | I20: Decision maker | J20: Was interested in what we do, wanted to stay in contact if there were stateside opprotunities. Dani and Christy both collaborated, Dani has been chatting with over LinkedIn… potentially wants a demo of the EEK presentation for his organization… Digital Transformation lead | K20: 4 | L20: Add to Mailing List | O20: TRUE | P20: FALSE | Q20: =DATE(2024,10,14)+TIME(11,1,54) -> 45579.46 | R20: Yes | S20: No | Z20: Scanned | AA20: =DATE(2024,10,14)+TIME(11,2,28) -> 45579.46 | AC20: Hong Kong | AD20: Large Solution | AE20: Yes
A21: Brenda | B21: Dixon | C21: bspatt04@gmail.com | D21: Kapitus | E21: Scrum Master | F21: 5712135904 | G21: Taylor's iPhone (personal) | H21: Taylor | I21: Influencer | J21: Small business lending firm. Excited about the agile/EA combined approach. Excited about assessments | K21: 4 | L21: Send Literature, Add to Mailing List, Other: Contact | M21: sending case studies and reaching out to explore pain points | O21: FALSE | P21: FALSE | Q21: =DATE(2024,10,15)+TIME(11,38,2) -> 45580.485 | R21: Yes | S21: Yes | T21: Immediately | U21: Yes | Z21: Scanned | AA21: =DATE(2024,10,15)+TIME(11,47,58) -> 45580.492 | AB21: Virginia | AC21: United States | AD21: Large Solution | AE21: Yes
A22: Alan | B22: Hammond | C22: alan.hammond@chase.com | D22: JPMorgan Chase | E22: VP Technology | F22: 6146200281 | G22: Mike's iPhone (personal) | H22: Mike | I22: Decision maker | J22: Quick discussion , follow up if possible on Digital Formula , need to learn more about pain points | K22: 4 | L22: Add to Mailing List | M22: EMAIL_CLIENT_HIGH - Send email asking for follow-up discussion; recapd discussion, especially pain points discussed; attach usual table insert | O22: TRUE | P22: TRUE | Q22: =DATE(2024,10,15)+TIME(10,31,11) -> 45580.438 | R22: Yes | S22: No | Z22: Scanned | AA22: =DATE(2024,10,15)+TIME(11,6,41) -> 45580.463 | AB22: Ohio | AC22: United States | AD22: Large Solution | AE22: Yes
A23: Jessica | B23: Crocker | C23: jessica_crocker@navyfederal.org | D23: Navy Federal Credit Union | E23: Scrum Master | F23: 5716091755 | G23: Taylor's iPhone (personal) | H23: Taylor | I23: Influencer | J23: Likes the EA/Agile approach. Send case studies on GRC, modeling, quads, agile | K23: 4 | L23: Send Literature, Add to Mailing List, Other: Contact | M23: They want to read/talk more about our case studies, specifically Process-Aligned Risk and Compliance Automation, Automated Quads, Agile Assessment and Improvement, Alfabet ITPM (Federated Bank), and Effective Agility. | O23: FALSE | P23: FALSE | Q23: =DATE(2024,10,17)+TIME(11,57,39) -> 45582.498 | R23: No | Z23: Scanned | AA23: =DATE(2024,10,17)+TIME(11,57,43) -> 45582.498 | AB23: Maryland | AC23: United States | AD23: Large Solution | AE23: Yes
A24: Joseph | B24: Marina | C24: jmarina@lmi.org | D24: LMI | E24: Fellow, Agile Coach | F24: 2107731114 | G24: iPad Mini (LSA/Keith) | H24: Larry | I24: Influencer | J24: Gave a book | K24: 4 | L24: Other: UX quantification needs , add to linkedin | O24: FALSE | P24: TRUE | Q24: =DATE(2024,10,15)+TIME(10,14,53) -> 45580.427 | R24: Yes | S24: Yes | T24: Not Applicable | U24: Not Applicable | Z24: Scanned | AA24: =DATE(2024,10,15)+TIME(11,22,24) -> 45580.474 | AB24: Texas | AC24: United States | AD24: Large Solution | AE24: Yes
A25: Denise | B25: Amling | C25: denise.t.amling@nasa.gov | D25: NASA | E25: Agile Coach | F25: 9493105907 | G25: iPad Mini (LSA/Keith) | H25: Keith | I25: Influencer | J25: Took the app rat assessment. Working on beginning stages of a new app inventory system at nasa. Curious if alfabet is fedramp. Follow up with her. | K25: 4 | L25: Add to Mailing List, Schedule Demo | M25: Keith sent email to Denise. | N25: Do I need one? | O25: TRUE | P25: TRUE | Q25: =DATE(2024,10,15)+TIME(11,59,16) -> 45580.499 | R25: Yes | S25: Yes | T25: Not Applicable | U25: Not Applicable | Z25: Scanned | AA25: =DATE(2024,10,15)+TIME(12,15,10) -> 45580.511 | AB25: Virginia | AC25: United States | AD25: Large Solution | AE25: Yes
A26: Pierrette | B26: Njikang | C26: pierrette_njikang@navyfederal.org | D26: Navy Federal Credit Union | E26: Scrum Master | F26: 5716511147 | G26: Taylor's iPhone (personal) | H26: Taylor | I26: Influencer | J26: Likes the EA/Agile approach. Send case studies on GRC, modeling, quads, agile | K26: 4 | L26: Send Literature, Add to Mailing List, Other: Contact | M26: They want to read/talk more about our case studies, specifically Process-Aligned Risk and Compliance Automation, Automated Quads, Agile Assessment and Improvement, Alfabet ITPM (Federated Bank), and Effective Agility. | O26: FALSE | P26: FALSE | Q26: =DATE(2024,10,15)+TIME(10,17,21) -> 45580.429 | R26: Yes | S26: No | Z26: Scanned | AA26: =DATE(2024,10,17)+TIME(11,27,23) -> 45582.477 | AB26: Virginia | AC26: United States | AD26: Large Solution | AE26: Yes
A27: Jalpa | B27: Purani | D27: CGI | E27: Director | G27: Kurt's iPhone (personal) | H27: Kurt | I27: Influencer | J27: She said she has a financial client that she’s working with . She is helping them with agile but really needs additional help with working with Service now. I told her I could get her connected with Craig and we can have a discussion on how we can bring all that together. | K27: 4 | L27: Needs Technical Data, Send Literature, Add to Mailing List, Schedule Demo | M27: EMAIL_PARTNER_HIGH: Send email asking for follow-up discussion; emphasize. Setup a call to demo to discuss how we can help with SNOW. Include Craig, Mike and Kurt. 10/21: Sent email to reach out about a follow-on call. Waiting on her response and plan to follow-up Monday (10/28 if no response (KG) | O27: TRUE | P27: TRUE | Q27: =DATE(2024,10,14)+TIME(15,4,39) -> 45579.628 | R27: Yes | S27: Yes | T27: Within 3 months | U27: Yes | Y27: completed | Z27: Business card | AA27: =DATE(2024,10,14)+TIME(16,49,32) -> 45579.701 | AD27: Large Solution | AE27: Yes
A28: Janeen | B28: Osselborn | C28: janeen.osselborn@servicenow.com | D28: ServiceNow | E28: Advisory Solution Consultant | G28: Kurt's iPhone (personal) | H28: Kurt | I28: Influencer | J28: The service now Team stopped by. They wanted to look at their EA told that they just released and use in SPM portfolio management element of it along with service now. Very interested in what we have to offer. They said they’ll stop back by later. | K28: 4 | L28: Needs Technical Data, Send Literature, Add to Mailing List, Current Customer, Schedule Demo | M28: EMAIL_PARTNER_HIGH: Send email asking for follow-up discussion. See Fred Champlain. Sent email to reach out about a follow-on call. Waiting on her response and plan to follow-up Monday (10/28 if no response (KG) | O28: TRUE | P28: TRUE | Q28: =DATE(2024,10,15)+TIME(15,44,8) -> 45580.656 | R28: Yes | S28: Yes | T28: Within 3 months | U28: Yes | Y28: completed | Z28: Business card | AA28: =DATE(2024,10,15)+TIME(17,20,50) -> 45580.723 | AD28: Large Solution | AE28: Yes
A29: Eva | B29: Owusu | C29: eva_owusu@navyfederal.org | D29: Navy Federal Credit Union | E29: Lead System Analyst | F29: 5715850177 | G29: Taylor's iPhone (personal) | H29: Taylor | I29: Influencer | J29: Likes the EA/Agile approach. Send case studies on GRC, modeling, quads, agile | K29: 4 | L29: Send Literature, Add to Mailing List, Other: Contact | M29: They want to read/talk more about our case studies, specifically Process-Aligned Risk and Compliance Automation, Automated Quads, Agile Assessment and Improvement, Alfabet ITPM (Federated Bank), and Effective Agility. | O29: FALSE | P29: FALSE | Q29: =DATE(2024,10,15)+TIME(10,17,35) -> 45580.429 | R29: No | Z29: Scanned | AA29: =DATE(2024,10,15)+TIME(10,17,46) -> 45580.429 | AB29: Virginia | AC29: United States | AD29: Large Solution | AE29: Yes
A30: Marco | B30: Guerrero | C30: Dani | D30: TecVeris | E30: Director, Tooling Solutions | F30: 5128297440 | G30: Taylor's iPhone (personal) | H30: Taylor | I30: Decision maker | J30: Looking for federal partners. Taylor and Kurt saw the demo of their nVeris tool that can use AI to quickly layout the business process for agencies quickly and then you can have real time interaction online with others in the org to make sure the process is fully captured | K30: 4 | M30: Reaching out to establish a partering relationship | O30: FALSE | P30: FALSE | Q30: =DATE(2024,10,14)+TIME(17,33,59) -> 45579.732 | R30: Yes | S30: Yes | Z30: Scanned | AA30: =DATE(2024,10,14)+TIME(17,34,40) -> 45579.732 | AB30: Texas | AC30: United States | AD30: Large Solution | AE30: Yes
A31: Millie | B31: Paniccia | C31: millie.paniccia@tecveris.com | D31: TecVeris | E31: Co-Founder & Managing Partner | F31: 4438037180 | G31: Taylor's iPhone (personal) | H31: Taylor | I31: Budget authority | J31: Looking for federal partners | K31: 4 | M31: Reaching out to establish a partering relationship | O31: FALSE | P31: FALSE | Q31: =DATE(2024,10,14)+TIME(17,34,46) -> 45579.732 | R31: Yes | S31: Yes | T31: Immediately | U31: Yes | V31: 4438037180 | Z31: Scanned | AA31: =DATE(2024,10,15)+TIME(11,1,39) -> 45580.459 | AB31: Maryland | AC31: United States | AD31: Large Solution | AE31: Yes
A32: Alyssa | B32: Catalano | C32: alyssa.catalano@panasonic.aero | D32: Panasonic Avionics | E32: Director -Project Management | F32: 949-690-8070 | G32: Mike's iPhone (personal) | H32: Mike | I32: Influencer | J32: Met at lunch on LPM workshop day. Panasonic , developing entertainment systems for aircraft , got a few ARTs, leadership not getting agile , competing “frameworks”, software dev using it … advised on improving principle 7 & showing success in key areas, and making it less about frameworks and more about outcomes and results .. | K32: 4 | L32: Add to Mailing List | M32: EMAIL_CLIENT_CUSTOM - Send the same LPM 2-page talkbook (National Grid) to Alyssa and see if that helps spark discussion around Panasonic pain points ; insert usual links table | N32: https://leanscaledarchitects.atlassian.net/browse/PIPE-396 | O32: TRUE | P32: TRUE | Q32: =DATE(2024,10,17)+TIME(13,1,48) -> 45582.543 | R32: Yes | S32: No | Z32: Scanned | AA32: =DATE(2024,10,17)+TIME(13,10,43) -> 45582.549 | AB32: California | AC32: United States | AD32: Large Solution | AE32: Yes
A33: Angela | B33: Campbell | C33: angela.campbell@progress.com | D33: Progress Software | E33: Senior Director of Transformation | F33: 6035828980 | G33: iPad Tiny (LSA/Mike) | H33: Hari | I33: Influencer | K33: 4 | L33: Needs Technical Data, Add to Mailing List | M33: Progress Software Corporation is an American public company that produces software for creating and deploying business applications. Founded in Burlington, Massachusetts with offices in 16 countries, the company posted revenues of $531.3 million in 2021 and employs approximately 2100 people. Send general TEMPLATE_CUSTOMER_HIGH (4/5 template) with LPM talkbook pdf Send draft to Mike/Dani for feedback | O33: FALSE | P33: FALSE | Q33: =DATE(2024,10,16)+TIME(10,8,5) -> 45581.422 | R33: Yes | S33: Yes | T33: Not Applicable | U33: Not Applicable | Z33: Scanned | AA33: =DATE(2024,10,16)+TIME(10,14,3) -> 45581.426 | AB33: Massachusetts | AC33: United States | AD33: Large Solution | AE33: Yes
A34: Fred | B34: Champlain | C34: frederic.champlain@servicenow.com | D34: Service Now | E34: Agile Evangelist SPM BU | G34: Kurt's iPhone (personal) / Mike's iPhone (personal) | H34: Craig | I34: Influencer | J34: The service now Team stopped by. They wanted to look at their EA tool that they just released and use in our portfolio management element of it along with service now. Very interested in what we have to offer. They said they’ll stop back by later (KG) Works with With dan wood at snow … connect with both about EA (MI) | K34: 4 | L34: Schedule Demo Needs Technical Data, Send Literature, Add to Mailing List, Current Customer, Schedule Demo | M34: EMAIL_PARTNER_HIGH: Send email asking for follow-up discussion. Schedule a demo and have Craig do a demo on how we can show EA capabilities. Include Mike, Craig, Kurt | O34: TRUE | P34: TRUE | Q34: =DATE(2024,10,15)+TIME(15,43,56) -> 45580.656 | R34: Yes | S34: Yes | T34: Within 3 months | U34: Not Applicable | Y34: completed | Z34: Business card | AA34: =DATE(2024,10,15)+TIME(16,48,59) -> 45580.701 | AD34: Large Solution | AE34: Yes
A35: Srinivasa | B35: Kasturi | C35: skasturi@worldbank.org | D35: The World Bank Group | E35: Senior Information Security Officer | F35: 5714369070 | G35: iPad Mini (LSA/Keith) | H35: Larry | I35: Decision maker | J35: Interested in what secure UX is. Larry talked with him a bit. Gave him copy of book. Curious on how to do the UX research; liked the templates in the book. Question asked about ‘how do we get the developer to think about how a system can be abused/hacked during the design.’ Done through task flow analysis. Help them understand why they are doing it. | K35: 4 | L35: Needs Technical Data, Schedule Demo | O35: FALSE | P35: TRUE | Q35: =DATE(2024,10,15)+TIME(11,33,33) -> 45580.482 | R35: Yes | S35: No | Z35: Scanned | AA35: =DATE(2024,10,15)+TIME(11,39,32) -> 45580.486 | AB35: Virginia | AC35: United States | AD35: Large Solution | AE35: Yes
A36: Amber | B36: O Grady | D36: US Air Force | G36: Kurt's iPhone (personal) | H36: Kurt | I36: Influencer | J36: Amber and 3 other team members stopped by the booth. The work at Wright-Patterson in the Financial Management Division. They would be good to follow-up with. Mike mentioned the work we have done with Navy FMP and they seemed interested to learn more. | K36: 4 | M36: Some interest and discussion about pain points and/or LSA solution. Setup a call to follow-up on their needs in finance at WPAFB and uncover more ways we can possibly engage. Sent email to reach out about a follow-on call. Waiting on her response and plan to follow-up Monday (10/28 if no response (KG) | O36: TRUE | P36: TRUE | Q36: =DATE(2024,10,15)+TIME(13,0,30) -> 45580.542 | R36: No | Y36: completed | Z36: Business card | AA36: =DATE(2024,10,15)+TIME(19,37,54) -> 45580.818 | AD36: Large Solution | AE36: Yes
A37: Timothy | B37: Worley | C37: tworley@twilio.com | D37: Twilio | E37: Principal Technical Program Manager | F37: 2106870800 | G37: iPad Tiny (LSA/Mike) | H37: Hari | I37: Influencer | J37: Very interested in learning more about our service details to help improve twilio scaled agile adoption | K37: 4 | L37: Send Literature, Add to Mailing List, Schedule Demo | M37: Talk to Dani about pain points relevant for this lead - template for those who want scaled agile implementation and LSA's services | O37: FALSE | P37: FALSE | Q37: =DATE(2024,10,15)+TIME(15,37,14) -> 45580.651 | R37: Yes | S37: No | Z37: Scanned | AA37: =DATE(2024,10,15)+TIME(17,46,25) -> 45580.741 | AB37: Texas | AC37: United States | AD37: Large Solution | AE37: Yes
A38: Jorge | B38: Garcia | C38: jorge.garcia1@usaa.com | D38: USAA | E38: Program Manager Lead/RTE | F38: 210-771-4845 | G38: Mike's iPhone (personal) | H38: Mike | I38: Influencer | J38: Discussed our involvement with ARIS GRC effort at USAA; they recognized the value and said it is still in use. They were in a hurry. Need more discussion to discover pain points / sell vectors | K38: 4 | L38: Add to Mailing List | M38: EMAIL_CLIENT_CUSTOM - Send the same LPM 2-page talkbook (National Grid) ; recap our discussion about ARIS and other tools can help integrate business / IT EA data to help with ompliance, better solution designs and summarized into a Lean Portfolio Canvas. cc: Bonnie Cortez | O38: TRUE | P38: TRUE | Q38: =DATE(2024,10,15)+TIME(15,20,37) -> 45580.639 | R38: Yes | S38: No | Z38: Scanned | AA38: =DATE(2024,10,15)+TIME(17,42,53) -> 45580.738 | AB38: Texas | AC38: United States | AD38: Large Solution | AE38: Yes
A39: Smita | B39: Saxena | C39: smita_x_saxena@fanniemae.com | D39: Fannie Mae | E39: Sr. Scrum Master | F39: 17039675748 | G39: iPad Mini (LSA/Mike) | H39: Larry | I39: Other: Scrum master | J39: Wants to know what we do. Interest in ux | K39: 4 | L39: Send Literature | O39: FALSE | P39: TRUE | Q39: =DATE(2024,10,16)+TIME(10,12,31) -> 45581.425 | R39: Yes | S39: No | Z39: Scanned | AA39: =DATE(2024,10,16)+TIME(10,15,53) -> 45581.428 | AB39: Virginia | AC39: United States | AD39: Large Solution | AE39: Yes
A40: James | B40: Hogan | C40: jimmy.hogan@gmail.com | D40: Samtec | E40: Director of R&D | F40: 8033512796 | G40: iPad Mini (LSA/Mike) | H40: Hari | I40: Influencer | J40: Casual interest. Keep in email list. | K40: 4 | L40: Send Literature | M40: send AFRL, R&D experience related template TEMPLATE_CLIENT_HIGH and attach LPM talkbook pdf | O40: FALSE | P40: FALSE | Q40: =DATE(2024,10,16)+TIME(10,17,26) -> 45581.429 | R40: Yes | S40: No | Z40: Scanned | AA40: =DATE(2024,10,16)+TIME(10,19,0) -> 45581.43 | AB40: South Carolina | AC40: United States | AD40: Large Solution | AE40: Yes
A41: Jamie | B41: Shopland | C41: jamie.shopland@amtrak.com | D41: Amtrak | E41: Director, Agile Transformation | F41: 3013057640 | G41: iPad Mini (LSA/Keith) | H41: Hari | I41: Other: Unknown | J41: Enter to win prize. Recorded video. | K41: 4 | L41: N/A | M41: send AFRL, R&D experience related template TEMPLATE_CLIENT_HIGH and attach LPM talkbook pdf Mention that we have experience with tranportation at California DOT, have case studies for this if interested | O41: FALSE | P41: FALSE | Q41: =DATE(2024,10,15)+TIME(7,58,41) -> 45580.332 | R41: Yes | S41: No | Z41: Scanned | AA41: =DATE(2024,10,15)+TIME(8,0,21) -> 45580.334 | AB41: Maryland | AC41: United States | AD41: Large Solution | AE41: Yes
A42: Etienne | B42: LAVERDIERE | C42: elaverdiere@digitaltango.ca | D42: DIGITAL TANGO | E42: CEO | F42: +33 7 82 55 07 78 | G42: iPad Mini (LSA/Mike) | H42: Larry | I42: Other: NA | J42: Interested in UX and design thinking | K42: 3 | L42: Other: Gave a book to him | O42: FALSE | P42: TRUE | Q42: =DATE(2024,10,15)+TIME(9,35,48) -> 45580.4 | R42: Yes | S42: No | V42: 5145163100 | Z42: Scanned | AA42: =DATE(2024,10,15)+TIME(17,43,48) -> 45580.739 | AC42: France | AD42: Large Solution | AE42: Yes
A43: Rebecca | B43: Stone | C43: rstone@tistatech.com | D43: TISTA Science & Technology Corporation | E43: Human Centered Design (HCD) – Agile Adoption Coach | F43: (580) 235-7410 | G43: iPad Mini (LSA/Keith) | H43: Larry | I43: Influencer | J43: Gave her a book | K43: 3 | L43: Other: Connect on linkedin | O43: FALSE | P43: TRUE | Q43: =DATE(2024,10,15)+TIME(10,42,37) -> 45580.446 | R43: Yes | S43: No | Z43: Scanned | AA43: =DATE(2024,10,15)+TIME(11,21,31) -> 45580.473 | AB43: Texas | AC43: United States | AD43: Large Solution | AE43: Yes
A44: Bryan | B44: Smith | C44: bsmith3@atlassian.com | D44: Atlassian | E44: Jira Align Strategic Solution Sales Account Manager | F44: 720-830-6998 | G44: Christy's iPhone (personal) | H44: Christy | I44: Other: jira align jira | J44: Spoke at lenght on JIRA Align and Atlassian suite | K44: 3 | L44: Add to Mailing List | M44: Sent Initial Email - 23 Oct | O44: TRUE | P44: TRUE | Q44: =DATE(2024,10,14)+TIME(11,15,57) -> 45579.469 | R44: Yes | S44: No | Z44: Scanned | AA44: =DATE(2024,10,14)+TIME(11,16,53) -> 45579.47 | AB44: Colorado | AC44: United States | AD44: Large Solution | AE44: Yes
A45: Hans | B45: Raj | C45: hans.raj@fepoc.com | D45: CareFirst BlueCross BlueShield (FEPOC) | E45: Lead Software Engineer/Team Coach | F45: 7038627951 | G45: iPad Mini (LSA/Mike) | H45: Larry | I45: Influencer | J45: Gave book. Interested in AI and UX | K45: 3 | L45: Add to Mailing List | O45: FALSE | P45: TRUE | Q45: =DATE(2024,10,16)+TIME(10,21,17) -> 45581.431 | R45: Yes | S45: No | Z45: Scanned | AA45: =DATE(2024,10,16)+TIME(10,30,39) -> 45581.438 | AB45: Virginia | AC45: United States | AD45: Large Solution | AE45: Yes
A46: Anitha | B46: Sankur | C46: anitha.sankur@atl.frb.org | D46: Federal Reserve Bank of Atlanta | E46: LEAN-Agile Coach | F46: 4232425695 | G46: iPad Mini (LSA/Mike) | H46: Hari | I46: Other: Unknown | J46: Work with Mike - find out who got the SAFe ARCH training | K46: 3 | L46: Add to Mailing List | O46: FALSE | P46: FALSE | Q46: =DATE(2024,10,16)+TIME(12,3,2) -> 45581.502 | R46: Yes | S46: No | Z46: Scanned | AA46: =DATE(2024,10,16)+TIME(13,42,33) -> 45581.571 | AB46: Georgia | AC46: United States | AD46: Large Solution | AE46: Yes
A47: Joshua | B47: Seckel | C47: joshua.seckel@govcio.com | D47: GovCIO | E47: Vice President | F47: 5712282878 | G47: iPad Mini (LSA/Keith) | H47: Larry | I47: Influencer | K47: 3 | L47: Other: UX curious | O47: FALSE | P47: TRUE | Q47: =DATE(2024,10,15)+TIME(10,9,53) -> 45580.424 | R47: Yes | S47: No | Z47: Scanned | AA47: =DATE(2024,10,15)+TIME(11,23,11) -> 45580.474 | AB47: Virginia | AC47: United States | AD47: Large Solution | AE47: Yes
A48: Nina | B48: Chavez | C48: nina.chavez@TSPi.net | D48: TSPi | E48: Director | F48: 970 9803825 | G48: Kurt's iPhone (personal) | H48: Kurt | I48: Decision maker | J48: Met her via Mike White. Works at TSPi. They are focused on digital transformation, IT modernization, cloud and low, no code platform development, agile development, and DFS ops, data science, human centered design and user experience, robotic process automation, cyber security, geographic information system development. They are currently on the GSA-MAS schedule, the CIO – SP3, USDA FPAC conservation software delivery services, NASA SEWP five, Seaport NXG, FAA eFast ￼ | K48: 3 | L48: Send Literature, Add to Mailing List | M48: EMAIL_PARTNER_HIGH: Send email asking for follow-up discussion; emphasize. Possible connection with us being able to partner with them on opportunites that require cybersecurity, noc-ode/low-code expertise | O48: TRUE | P48: TRUE | Q48: =DATE(2024,10,14)+TIME(22,14,28) -> 45579.927 | R48: Yes | S48: No | V48: 970 402 2951 | W48: Loveland | X48: CO | Y48: completed | Z48: Business card | AA48: =DATE(2024,10,15)+TIME(2,49,35) -> 45580.118 | AD48: Large Solution | AE48: Yes
A49: Akiyo | B49: Urano | C49: akiyo.urano@iconatg.com | D49: Icon ATG | E49: Senior agile coach | F49: 7039739033 | G49: Mike's iPhone (personal) | H49: Mike | I49: Influencer | J49: Interested in case studies, probably just learning more | K49: 3 | L49: Add to Mailing List | M49: EMAIL_PARTNER_LOW | O49: TRUE | P49: TRUE | Q49: =DATE(2024,10,15)+TIME(15,29,49) -> 45580.646 | R49: Yes | S49: No | Z49: Scanned | AA49: =DATE(2024,10,15)+TIME(17,41,17) -> 45580.737 | AB49: Virginia | AC49: United States | AD49: Large Solution | AE49: Yes
A50: Vijay | B50: Reddy | C50: vijay.reddy@infosys.com | D50: Infosys Limited | E50: Enterprise Agile Transformation Coach | F50: 8474522777 | G50: iPad Mini (LSA/Keith) | H50: Larry | I50: Influencer | J50: Larry gave website analysis for infosys.com…. Says he is also interested in EA services. Got book copy. | K50: 3 | L50: Needs Technical Data, Send Literature | O50: FALSE | P50: TRUE | Q50: =DATE(2024,10,15)+TIME(15,12,15) -> 45580.634 | R50: Yes | S50: No | Z50: Scanned | AA50: =DATE(2024,10,15)+TIME(15,18,2) -> 45580.638 | AB50: Illinois | AC50: United States | AD50: Large Solution | AE50: Yes
A51: Bruce | B51: Nix | C51: bruce.nix@nttdata.com | D51: Launch by NTT DATA | E51: Specialty Client Partner | F51: 19016056996 | G51: iPad Mini (LSA/Keith) | H51: Larry | I51: Budget authority | J51: Gave a book | K51: 3 | L51: Other: Connect | O51: FALSE | P51: TRUE | Q51: =DATE(2024,10,15)+TIME(14,13,17) -> 45580.593 | R51: Yes | S51: No | Z51: Scanned | AA51: =DATE(2024,10,15)+TIME(14,15,47) -> 45580.594 | AB51: Alabama | AC51: United States | AD51: Large Solution | AE51: Yes
A52: Ken | B52: King | C52: ken.king@expleogroup.com | D52: Expleo Group | E52: Agile Coach | G52: Kurt's iPhone (personal) | H52: Kurt | I52: Influencer | J52: He works at Expleo Group in Dublin Ireland. He also is at Bank of America. He has a SP six, RT, SDP, LPM, PMP, ACP, RS @SP, agog Coach in Bank of America in Europe. | K52: 3 | L52: Send Literature, Add to Mailing List | M52: EMAIL_PARTNER_HIGH: Send email asking for follow-up discussion; emphasize. As we connected, I found out that he had also met Mike Idengren at an event in Nashville.Nothing specific but may want to explore opportunites with him or/BoA further and share our work with FinTech | O52: TRUE | P52: TRUE | Q52: =DATE(2024,10,14)+TIME(22,20,18) -> 45579.931 | R52: Yes | S52: No | W52: Dublin | X52: IE | Y52: completed | Z52: Business card | AA52: =DATE(2024,10,15)+TIME(2,39,18) -> 45580.111 | AD52: Large Solution | AE52: Yes
A53: Peter | B53: Pendergast | C53: peter.pendergast@gd-ms.com | D53: General Dynamics Mission System | G53: Kurt's iPhone (personal) | H53: Kurt | I53: Influencer | J53: Seemed interesetd in discussing further around how we might e able to engage with GD on EA, SAFe and possibly SNOW. Nothing overly specific but may be a good way to further increase our possibility of working as a sub. | K53: 3 | L53: Send Literature, Add to Mailing List, | M53: Some interest and discussion about pain points and/or LSA solution. Possibly setup an exploration call to pull more of their requirements or pain points out. | O53: TRUE | P53: TRUE | Q53: =DATE(2024,10,15)+TIME(12,33,59) -> 45580.524 | R53: No | Y53: transcription incomplete | Z53: Business card | AA53: =DATE(2024,10,15)+TIME(12,41,56) -> 45580.529 | AD53: Large Solution | AE53: Yes
A54: Donald | B54: Brown | C54: donald.brown@prudential.com | D54: Prudential Financial | E54: Release Train Engineer | F54: 862-703-6566 | G54: iPad Tiny (LSA/Mike) | H54: Mike | I54: Other: RTE | J54: Gave copy of robins book. He is heavily focused on devops. Mike thought he was just curious and fishing for a job. | K54: 3 | L54: Send Literature | M54: EMAIL_CLIENT_LOW - Send email asking for follow-up discussion; attach usual table insert | O54: TRUE | P54: TRUE | Q54: =DATE(2024,10,16)+TIME(10,10,32) -> 45581.424 | R54: Yes | Z54: Scanned | AA54: =DATE(2024,10,16)+TIME(10,14,3) -> 45581.426 | AB54: Pennsylvania | AC54: United States | AD54: Large Solution | AE54: Yes
A55: Evan | B55: Champagne | C55: evan.champagne@gd-ms.com | D55: General Dynamics Mission Systems | E55: Advanced Systems Engineer | G55: Kurt's iPhone (personal) | H55: Kurt | I55: Influencer | J55: Seemed interesetd in discussing further around how we might e able to engage with GD on EA, SAFe and possibly SNOW. Nothing overly specific but may be a good way to further increase our possibility of working as a sub. | K55: 3 | L55: Send Literature, Add to Mailing List, | M55: See Peter Pendergast | O55: TRUE | P55: TRUE | Q55: =DATE(2024,10,15)+TIME(12,33,43) -> 45580.523 | R55: No | Y55: completed | Z55: Business card | AA55: =DATE(2024,10,15)+TIME(12,39,34) -> 45580.527 | AD55: Large Solution | AE55: Yes
A56: Todd | B56: Sheridan | C56: todd.sheridan@pnc.com | D56: PNC Bank | E56: Senior Agile Coach | F56: 720-454-6342 | G56: Christy's iPhone (personal) | H56: Christy | I56: Influencer | J56: Little initial interest, but Mike to coordinate other contacts / angles in a response with Christy | K56: 3 | L56: Add to Mailing List | M56: Sent Initial Email - 23 Oct | O56: TRUE | P56: TRUE | Q56: =DATE(2024,10,15)+TIME(13,25,2) -> 45580.559 | R56: Yes | S56: No | T56: Not Applicable | U56: Not Applicable | Z56: Scanned | AA56: =DATE(2024,10,15)+TIME(13,25,19) -> 45580.559 | AB56: Colorado | AC56: United States | AD56: Large Solution | AE56: Yes
A57: Rasheedat | B57: Osei- Acheampchg | C57: Sent LinkedIn Invite with Message | D57: IBM | E57: TSA Project Executive | G57: Kurt's iPhone (personal) | H57: Kurt | I57: Influencer | J57: We discussed that we are working to engage with IBM and recently spoke to IBM's small business liaison and there was alignment on how LSA could partner with IBM. Will likely pull in Rasheedat as needed for further opportuntiies at TSA | K57: 3 | M57: Some interest and discussion about pain points and/or LSA solution | O57: TRUE | P57: TRUE | Q57: =DATE(2024,10,15)+TIME(12,5,34) -> 45580.504 | R57: No | Y57: completed | Z57: Business card | AA57: =DATE(2024,10,15)+TIME(12,12,31) -> 45580.509 | AD57: Large Solution | AE57: Yes
A58: Daylon | B58: Walton | C58: daylon.walton@iconagility.com | D58: Icon Agility Services | E58: Enterprise Business Agility Strategist | F58: 9728396263 | G58: Kurt's iPhone (personal) | H58: Kurt | I58: Influencer | J58: Primarily works in the Fintech space in the commercial industry. Works with several large well-known companies. ￼ Their primary businesses around agile coaching, approximately 99% of their business. | K58: 3 | L58: Other: Agile coaching | M58: Some interest and discussion about pain points and/or LSA solution | O58: TRUE | P58: TRUE | Q58: =DATE(2024,10,14)+TIME(12,17,55) -> 45579.512 | R58: Yes | S58: Yes | T58: Not Applicable | U58: No | W58: Dallas | Y58: completed | Z58: Business card | AA58: =DATE(2024,10,14)+TIME(12,27,58) -> 45579.519 | AD58: Large Solution | AE58: Yes
A59: Kavitha | B59: Paramathmuni | C59: kavitarajeev@gmail.com | D59: Radus Software | E59: Principal Consultant | F59: 603-320-6703 | G59: iPad Mini (LSA/Keith) | H59: Larry | I59: Other: L | J59: Grabbed case studies. Possible partner discussions. Collaborate with Kurt on a meeting | K59: 3 | L59: Add to Mailing List | O59: FALSE | P59: FALSE | Q59: =DATE(2024,10,15)+TIME(12,51,12) -> 45580.536 | R59: Yes | S59: No | Z59: Scanned | AA59: =DATE(2024,10,15)+TIME(13,31,32) -> 45580.564 | AB59: Virginia | AC59: United States | AD59: Large Solution | AE59: Yes
A60: John | B60: Simmons | C60: john.simmons@radussoftware.com | D60: Radus Software LLC | E60: Director Business Development | F60: 7039661562 | G60: iPad Mini (LSA/Mike) | H60: Larry | I60: Influencer | J60: Gave a book. Possible partner discussions. Collaborate with Kurt on a meeting | K60: 3 | L60: Add to Mailing List | O60: FALSE | P60: TRUE | Q60: =DATE(2024,10,16)+TIME(11,24,54) -> 45581.476 | R60: Yes | S60: No | Z60: Scanned | AA60: =DATE(2024,10,16)+TIME(11,40,42) -> 45581.487 | AB60: Virginia | AC60: United States | AD60: Large Solution | AE60: Yes
A61: Ken | B61: Presutti | C61: kenneth.presutti@pnc.com | D61: PNC Bank | E61: Coach | G61: Kurt's iPhone (personal) | H61: Kurt | I61: Other: Agile Coach | J61: He works for PNC as an RTE and offered to help make connections. I mentioned we also have someone who has contacts at PNC but welcome any additional information | K61: 3 | L61: Send Literature, Add to Mailing List | M61: Some interest and discussion about pain points and/or LSA solution. Connect with him to try to get further connection and discussions at PNC. | O61: TRUE | P61: TRUE | Q61: =DATE(2024,10,14)+TIME(22,0,3) -> 45579.917 | R61: Yes | S61: No | V61: +14124070402 | Y61: completed | Z61: Business card | AA61: =DATE(2024,10,15)+TIME(2,42,20) -> 45580.113 | AD61: Large Solution | AE61: Yes
A62: Tanzeen | B62: Noori | C62: No contact info found | D62: Publicis Sapient | E62: Senior Manager | G62: Kurt's iPhone (personal) | H62: Kurt | I62: Influencer | J62: They do a lot of similar things we do. Large company with over 25k employees. Digital transformation firm. AWS, Google. Microsoft partner. They are working on getting Atlassian partnership. She is an Atlassian SME. | K62: 3 | L62: Send Literature, Add to Mailing List | M62: Some interest and discussion about pain points and/or LSA solution. Keith and I can work to connect with them and offer the ability to leverage our Atlassian Partnership and collaborate on some work together. | O62: FALSE | P62: FALSE | Q62: =DATE(2024,10,14)+TIME(17,7,55) -> 45579.714 | R62: Yes | S62: No | Y62: completed | Z62: Business card | AA62: =DATE(2024,10,14)+TIME(17,22,56) -> 45579.724 | AD62: Large Solution | AE62: Yes
A63: Jesse | B63: Johnson | C63: jesse.johnson@TSPi.net | D63: TSPi | E63: Release Train Engineer | G63: Kurt's iPhone (personal) | H63: Kurt | I63: Other: RTE | J63: Works as an RTE at TSPi. Mike White introduced me via Nina Chavez who also works there. Mainly focused on app development. | K63: 3 | L63: Send Literature, Add to Mailing List | M63: See Nina Chavez | O63: TRUE | P63: TRUE | Q63: =DATE(2024,10,14)+TIME(22,11,43) -> 45579.925 | R63: Yes | S63: No | V63: 540 338 5150 | W63: Winchester | X63: VA | Y63: completed | Z63: Business card | AA63: =DATE(2024,10,15)+TIME(2,47,31) -> 45580.116 | AD63: Large Solution | AE63: Yes
A64: Sergio | B64: Reyes | C64: sreyes@tantustech.com | D64: Tantus Technologies, Inc. | E64: Deputy Program Manager | F64: 2024927725 | G64: iPad Tiny (LSA/Mike) | H64: Hari | I64: Influencer | K64: 3 | L64: Add to Mailing List | O64: FALSE | P64: FALSE | Q64: =DATE(2024,10,15)+TIME(15,31,34) -> 45580.647 | R64: Yes | S64: No | Z64: Scanned | AA64: =DATE(2024,10,15)+TIME(17,46,25) -> 45580.741 | AB64: Virginia | AC64: United States | AD64: Large Solution | AE64: Yes
A65: Curtis | B65: Yee | C65: curtis.yee@td.com | D65: TD Bank | E65: Associate Vice President | F65: 416-508-0249 | G65: iPad Mini (LSA/Keith) | H65: Mike | J65: Messaging around GRC / compliance | K65: 3 | O65: TRUE | P65: TRUE | Q65: =DATE(2024,10,16)+TIME(14,43,22) -> 45581.613 | R65: No | Z65: Scanned | AA65: =DATE(2024,10,16)+TIME(14,43,29) -> 45581.614 | AC65: Canada | AD65: Large Solution | AE65: Yes
A66: Justin | B66: Brogden | D66: USAF | G66: Kurt's iPhone (personal) | H66: Kurt | I66: Influencer | J66: Justin and 3 other team members stopped by the booth. The work at Wright-Patterson in the Financial Management Division. They would be good to follow-up with. Mike mentioned the work we have done with Navy FMP and they seemed interested to learn more. | K66: 3 | M66: See Amber O'Grady | O66: TRUE | P66: TRUE | Q66: =DATE(2024,10,15)+TIME(12,43,14) -> 45580.53 | R66: No | W66: WPAFB | X66: OH | Y66: completed | Z66: Business card | AA66: =DATE(2024,10,15)+TIME(19,39,4) -> 45580.819 | AD66: Large Solution | AE66: Yes
A67: Harold | B67: Wagner | C67: harold.wagner@cprime.com | D67: Process Velocity, Inc. | E67: Principal Consultant | F67: 4693521366 | G67: iPad Mini (LSA/Keith) | H67: Kurt | I67: Other: SPC independent | J67: Was interested in our solutions overall. Independent safe trainer spc. Looking just to see how different companies can help on his projects when needed. | K67: 3 | L67: Add to Mailing List | M67: Email sent | O67: TRUE | P67: TRUE | Q67: =DATE(2024,10,15)+TIME(11,54,19) -> 45580.496 | R67: Yes | S67: No | Z67: Scanned | AA67: =DATE(2024,10,15)+TIME(11,58,41) -> 45580.499 | AB67: Texas | AC67: United States | AD67: Large Solution | AE67: Yes
A68: Richard | B68: Trice | C68: richard.w.trice.civ@health.mil | D68: DHMS/EIDS | E68: Product Manager | F68: 8304310550 | G68: iPad Mini (LSA/Keith) | H68: Kurt | K68: 3 | O68: TRUE | P68: TRUE | Q68: =DATE(2024,10,15)+TIME(17,47,39) -> 45580.741 | R68: No | Z68: Scanned | AA68: =DATE(2024,10,15)+TIME(17,47,51) -> 45580.742 | AB68: Texas | AC68: United States | AD68: Large Solution | AE68: Yes
A69: Horace | B69: Lynch | C69: horacelynch@hotmail.com | D69: Georgia Pacific | E69: Scrum Master | F69: 9012922083 | G69: iPad Mini (LSA/Mike) | H69: Hari | I69: Influencer | J69: (who talked to Horace Lynch?) | K69: 2 | L69: Add to Mailing List | M69: send TEMPLATE_CLIENT_LOW | O69: FALSE | P69: FALSE | Q69: =DATE(2024,10,16)+TIME(10,7,12) -> 45581.422 | R69: Yes | S69: No | Z69: Scanned | AA69: =DATE(2024,10,16)+TIME(10,32,37) -> 45581.439 | AB69: Georgia | AC69: United States | AD69: Large Solution | AE69: Yes
A70: Jacqueline | B70: Markot | C70: jackie.markot@discounttire.com | D70: Discount Tire | E70: Product Manager | F70: 4802627243 | G70: Taylor's iPhone (personal) | H70: Taylor | I70: Influencer | J70: Looking for Ada Dash boarding and UX help. Looking for a consultant to come in and work with transparency in their organization. ￼ | K70: 2 | L70: Other: Connect | O70: FALSE | P70: FALSE | Q70: =DATE(2024,10,15)+TIME(10,48,25) -> 45580.45 | R70: Yes | S70: Yes | T70: Within 3 months | U70: Yes | Z70: Scanned | AA70: =DATE(2024,10,15)+TIME(10,58,54) -> 45580.458 | AB70: Arizona | AC70: United States | AD70: Large Solution | AE70: Yes
A71: Trevor | B71: Methena | C71: trevor.methena@allegion.com | D71: Allegion | E71: Release Train Engineer | F71: 5124176356 | G71: Christy's iPhone (personal) | H71: Christy | I71: Influencer | J71: They are global company of IoT hardware and software. They are using agile practices and have done a lot of outsourcing overseas recently. | K71: 2 | L71: Add to Mailing List | M71: Sent Initial Email - 23 Oct | O71: TRUE | P71: TRUE | Q71: =DATE(2024,10,15)+TIME(10,39,50) -> 45580.444 | R71: Yes | S71: No | Z71: Scanned | AA71: =DATE(2024,10,15)+TIME(10,56,0) -> 45580.456 | AB71: Texas | AC71: United States | AD71: Large Solution | AE71: Yes
A72: Jason | B72: Morley | C72: jmorley@habitat.org | D72: Habitat for Humanity International | E72: Director, Business Intelligence | F72: 4049332885 | G72: Christy's iPhone (personal) | H72: Christy | I72: Budget authority | J72: Using Agile to manage work across franchises for H4H. | K72: 2 | L72: Add to Mailing List | M72: Sent Initial Email - 23 Oct | O72: TRUE | P72: TRUE | Q72: =DATE(2024,10,15)+TIME(13,4,27) -> 45580.545 | R72: Yes | S72: No | Z72: Scanned | AA72: =DATE(2024,10,15)+TIME(13,4,41) -> 45580.545 | AB72: Georgia | AC72: United States | AD72: Large Solution | AE72: Yes
A73: Daylon | B73: Walton | C73: daylon.walton@iconagility.com | D73: ICON Agility | E73: Agile Engagement | F73: 9728396263 | G73: Christy's iPhone (personal) | H73: Christy | I73: Influencer | J73: Company is an Atlassian Platform Partner | K73: 2 | L73: Add to Mailing List, Other: Is a lead solution person for ICON agility | M73: Sent Initial Email - 23 Oct - Meeting set for Monday 28 Oct | O73: TRUE | P73: TRUE | Q73: =DATE(2024,10,15)+TIME(9,43,21) -> 45580.405 | R73: Yes | S73: No | Z73: Scanned | AA73: =DATE(2024,10,15)+TIME(9,44,1) -> 45580.406 | AB73: Texas | AC73: United States | AD73: Large Solution | AE73: Yes
A74: Lauren | B74: Chambers | C74: lauren.e.chambers@lmco.com | D74: Lockheed Martin | E74: Release Train Engineer | F74: 7203855764 | G74: Christy's iPhone (personal) | H74: Christy | I74: Influencer | J74: Works onsite supporting customers for LM. | K74: 2 | L74: Add to Mailing List, Other: Wants slides from Eek | M74: Sent Initial Email - 23 Oct | O74: TRUE | P74: TRUE | Q74: =DATE(2024,10,14)+TIME(11,2,32) -> 45579.46 | R74: Yes | S74: No | Z74: Scanned | AA74: =DATE(2024,10,14)+TIME(11,3,30) -> 45579.461 | AB74: Colorado | AC74: United States | AD74: Large Solution | AE74: Yes
A75: Catherine | B75: Yeagle | C75: cdyeagle@gmail.com | D75: Phaedon | E75: Product Manager / Owner | F75: 5713315860 | G75: Christy's iPhone (personal) | H75: Christy | I75: Other: Agile Practitioner | J75: Spoke about company phaedon and they are using agile, so may be more of a potential for partnership/teaming later on work. | K75: 2 | M75: Sent Initial Email - 23 Oct | O75: TRUE | P75: TRUE | Q75: =DATE(2024,10,15)+TIME(10,48,35) -> 45580.45 | R75: No | Z75: Scanned | AA75: =DATE(2024,10,15)+TIME(10,55,58) -> 45580.456 | AB75: Virginia | AC75: United States | AD75: Large Solution | AE75: Yes
A76: Sheila | B76: Olds | C76: solds@newscorp.com | D76: News Corp | E76: DIRECTOR, ENTERPRISE AGILE COACH | F76: 704-609-1838 | G76: iPad Mini (LSA/Keith) | H76: Christy | K76: 2 | M76: Sent Initial Email - 23 Oct | O76: TRUE | P76: TRUE | Q76: =DATE(2024,10,16)+TIME(10,18,8) -> 45581.429 | R76: No | Z76: Scanned | AA76: =DATE(2024,10,16)+TIME(10,27,47) -> 45581.436 | AB76: North Carolina | AC76: United States | AD76: Large Solution | AE76: Yes
A77: Pras | B77: Khuon | C77: prasna.khuon@ngc.com | D77: Northrop Grumman | E77: Agile Coach | F77: 6307282488 | G77: Mike's iPhone (personal) | H77: Christy | I77: Influencer | J77: Discussion of some high level LSA services , not sure of interest - collaborate with Dani | K77: 2 | L77: Add to Mailing List | M77: Sent Initial Email - 23 Oct | O77: TRUE | P77: TRUE | Q77: =DATE(2024,10,15)+TIME(15,17,9) -> 45580.637 | R77: Yes | S77: No | Z77: Scanned | AA77: =DATE(2024,10,15)+TIME(17,40,28) -> 45580.736 | AB77: Illinois | AC77: United States | AD77: Large Solution | AE77: Yes
A78: Praveen | B78: Goel | C78: praveen.goel@cprime.com | D78: cPrime | E78: SPCT, Transformation Leader, Agile Coach | F78: 2032311857 | G78: Mike's iPhone (personal) | H78: Mike | I78: Other: SPCT learning about our approach | J78: hit-and-run, no real discussion | K78: 2 | L78: Add to Mailing List | M78: EMAIL_PARTNER_LOW - nice meeting you, happy to discuss partnership opportuniites...; attach usual table insert | N78: none | O78: TRUE | P78: TRUE | Q78: =DATE(2024,10,15)+TIME(11,22,33) -> 45580.474 | R78: Yes | S78: No | Z78: Scanned | AA78: =DATE(2024,10,15)+TIME(11,23,24) -> 45580.475 | AB78: Connecticut | AC78: United States | AD78: Large Solution | AE78: Yes
A79: Kimberly | B79: Bogden | C79: bogden_kim@hotmail.com | D79: Prudential | E79: Lead, Scrum Master | F79: 908-468-9585 | G79: Mike's iPhone (personal) | H79: Mike | I79: Other: Just chatting about their already mature ARTs | J79: Seemed to have an answer for everything , didn’t need help …? | K79: 2 | L79: Add to Mailing List, Other: AD | M79: EMAIL_CLIENT_LOW - Send email asking for follow-up discussion; attach usual table insert | O79: TRUE | P79: TRUE | Q79: =DATE(2024,10,15)+TIME(10,39,45) -> 45580.444 | R79: Yes | S79: No | Z79: Scanned | AA79: =DATE(2024,10,15)+TIME(11,5,32) -> 45580.462 | AB79: New Jersey | AC79: United States | AD79: Large Solution | AE79: Yes
A80: Bonnie | B80: Cortez | C80: bonnie.cortez@usaa.com | D80: USAA | E80: Product Owner Senior | F80: 2104780015 | G80: Mike's iPhone (personal) | H80: Mike | I80: Influencer | J80: See jorge garcia | K80: 2 | L80: Add to Mailing List | M80: cc: on email to Jorge | O80: TRUE | P80: TRUE | Q80: =DATE(2024,10,15)+TIME(15,20,42) -> 45580.639 | R80: Yes | Z80: Scanned | AA80: =DATE(2024,10,15)+TIME(17,43,29) -> 45580.739 | AB80: Texas | AC80: United States | AD80: Large Solution | AE80: Yes
A81: Melissa | B81: Grupp | C81: mrsmelissagrupp@gmail.com | D81: PULSE | E81: Senior Manager Product Owner | F81: 4074060324 | G81: iPad Mini (LSA/Keith) | H81: Hari | K81: 2 | O81: FALSE | P81: FALSE | Q81: =DATE(2024,10,16)+TIME(10,27,41) -> 45581.436 | R81: No | Z81: Scanned | AA81: =DATE(2024,10,16)+TIME(10,27,47) -> 45581.436 | AB81: Texas | AC81: United States | AD81: Large Solution | AE81: Yes
A82: Cynthia | B82: Thomas | C82: sweetlorraine82@gmail.com | D82: SAIC | E82: Program Analyst Sr Principal | F82: 5043881158 | G82: iPad Mini (LSA/Mike) | H82: Taylor | I82: Other: Na | K82: 2 | L82: N/A | O82: FALSE | P82: FALSE | Q82: =DATE(2024,10,15)+TIME(9,57,21) -> 45580.415 | R82: Yes | S82: No | Z82: Scanned | AA82: =DATE(2024,10,15)+TIME(17,43,48) -> 45580.739 | AB82: Louisiana | AC82: United States | AD82: Large Solution | AE82: Yes
A83: Tobias | B83: Schoenhaar | C83: bad email address sent LinkedIn Ivite | D83: Fast Lane | G83: Kurt's iPhone (personal) | H83: Kurt | I83: Influencer | J83: Focused on Training mostly. About 4K employeees. Provide top-notch training and consultancy in diverse domains, from cloud computing and AI to cybersecurity and software development. Fast Lane's holistic approach covers wireless, mobility, modern workplace strategies, leadership skills, IT, and project management, solidifying its position as a global leader in the industry. | K83: 2 | L83: Send Literature, Add to Mailing List | M83: Some discussion about pain points and/or LSA solutions. They cover a lot of various trainings but we may be able to add the SNOW, Software AG, Atlassian supplemental training as an option | O83: TRUE | P83: TRUE | Q83: =DATE(2024,10,15)+TIME(10,57,56) -> 45580.457 | R83: No | Y83: transcription incomplete | Z83: Business card | AA83: =DATE(2024,10,15)+TIME(12,20,39) -> 45580.514 | AD83: Large Solution | AE83: Yes
A84: Bharat | B84: Shah | D84: HCLTech | E84: Practice Lead, Agile Transformation and CoE | G84: Kurt's iPhone (personal) | H84: Kurt | I84: Other: RTE | J84: Large 220k global organization. Many areas that do a majority of what we do. | K84: 2 | L84: Send Literature, Add to Mailing List | M84: Some discussion about pain points and/or LSA solutions;. Seemed to be well covered with a large pool of resources. Best possible opportunity may be if they need additional resources | O84: TRUE | P84: TRUE | Q84: =DATE(2024,10,15)+TIME(14,58,45) -> 45580.624 | R84: Yes | S84: No | Y84: completed | Z84: Business card | AA84: =DATE(2024,10,15)+TIME(17,21,57) -> 45580.724 | AD84: Large Solution | AE84: Yes
A85: Bruce | B85: Friedman | C85: bfriedman@peraton.com | D85: Peraton | E85: Agile Coach | G85: Kurt's iPhone (personal) | H85: Kurt | I85: Other: Retired but teaches safe courses for Peraton | J85: Said Peraton is engaged with a lot of different government contracting work. He lives in Reston Virginia and said that they are doing work with NASA and Army. I will need to get a further contact to be able to connect and get a stronger lead. | K85: 2 | L85: Other: Said he could connect me to other contacts | M85: Some discussion about pain points and/or LSA solution. He really couldn't speak to what else we could help Peraton with but he may be a possible connection on helping with connecting us to Peraton as a way into the Missile Defense Agency. | O85: TRUE | P85: TRUE | Q85: =DATE(2024,10,14)+TIME(15,10,3) -> 45579.632 | R85: Yes | S85: No | Y85: completed | Z85: Business card | AA85: =DATE(2024,10,14)+TIME(16,49,8) -> 45579.701 | AD85: Large Solution | AE85: Yes
A86: Puneeta | B86: Singh | C86: pusingh@americorps.gov | D86: AmeriCorps | E86: Project Manager | F86: 202-925-7552 | G86: iPad Mini (LSA/Keith) | H86: Christy | K86: 1 | M86: Sent Initial Email - 23 Oct | O86: TRUE | P86: TRUE | Q86: =DATE(2024,10,16)+TIME(14,44,40) -> 45581.614 | R86: No | Z86: Scanned | AA86: =DATE(2024,10,16)+TIME(14,44,46) -> 45581.614 | AB86: Virginia | AC86: United States | AD86: Large Solution | AE86: Yes
A87: Rene | B87: Watts | C87: rene.watts@hcltech.com | D87: HCLTech | E87: Agile Coach | F87: 7206569957 | G87: iPad Mini (LSA/Mike) | H87: Kurt | I87: Influencer | K87: 1 | L87: Add to Mailing List | M87: Email sent | O87: TRUE | P87: TRUE | Q87: =DATE(2024,10,15)+TIME(10,39,45) -> 45580.444 | R87: Yes | S87: No | Z87: Scanned | AA87: =DATE(2024,10,15)+TIME(17,43,48) -> 45580.739 | AB87: Florida | AC87: United States | AD87: Large Solution | AE87: Yes
A88: Anastrasiia | B88: Tyshchenko | C88: atyshchenko@jackhenry.com | D88: Jack Henry | E88: Scrum Master | F88: 6158017760 | G88: iPad Mini (LSA/Mike) | H88: Hari | I88: Influencer | J88: Was recorded for interview | K88: 1 | L88: Add to Mailing List | O88: FALSE | P88: FALSE | Q88: =DATE(2024,10,15)+TIME(10,16,47) -> 45580.428 | R88: Yes | S88: No | Z88: Scanned | AA88: =DATE(2024,10,15)+TIME(17,43,48) -> 45580.739 | AB88: Colorado | AC88: United States | AD88: Large Solution | AE88: Yes
A89: Nick | B89: Reidy | C89: nick.reidy@allegion.com | D89: L3Harris | E89: Software Manager, Release Train Engineer | F89: 7196455300 | G89: iPad Mini (LSA/Keith) | H89: Dani | I89: Decision maker | J89: Video. Friend of Dani and Shawn. | K89: 1 | L89: N/A | O89: FALSE | P89: FALSE | Q89: =DATE(2024,10,15)+TIME(9,3,16) -> 45580.377 | R89: Yes | S89: No | Z89: Scanned | AA89: =DATE(2024,10,15)+TIME(9,3,47) -> 45580.378 | AB89: Colorado | AC89: United States | AD89: Large Solution | AE89: Yes
A90: Josiah | B90: Smith | C90: smith@josiahsvision.com | D90: Learning Tree International | E90: Marketing Project Manager | F90: 3018483510 | G90: iPad Mini (LSA/Keith) | H90: Taylor | I90: Influencer | K90: 1 | L90: Add to Mailing List | O90: FALSE | P90: FALSE | Q90: =DATE(2024,10,16)+TIME(12,40,27) -> 45581.528 | R90: Yes | S90: No | Z90: Scanned | AA90: =DATE(2024,10,16)+TIME(13,4,15) -> 45581.545 | AB90: Maryland | AC90: United States | AD90: Large Solution | AE90: Yes
A91: Bonnie | B91: Soto | C91: soto_bonnie@bah.com | D91: Booz Allen Hamilton | E91: Technical Team Lead | F91: 2103241023 | G91: Taylor's iPhone (personal) | H91: Taylor | K91: 1 | O91: FALSE | P91: FALSE | Q91: =DATE(2024,10,15)+TIME(13,24,0) -> 45580.558 | R91: No | Z91: Scanned | AA91: =DATE(2024,10,15)+TIME(13,56,0) -> 45580.581 | AB91: Texas | AC91: United States | AD91: Large Solution | AE91: Yes
A92: Namrata | B92: Datta | C92: namrata.d@hcl.com | D92: HCLTech | E92: Director , Agile Coach, SPCT candidate | F92: 6479364342 | G92: Taylor's iPhone (personal) | H92: Kurt | K92: 1 | M92: Email sent | O92: TRUE | P92: TRUE | Q92: =DATE(2024,10,15)+TIME(10,39,55) -> 45580.444 | R92: No | Z92: Scanned | AA92: =DATE(2024,10,15)+TIME(10,39,58) -> 45580.444 | AC92: Canada | AD92: Large Solution | AE92: Yes
A93: Takenori | B93: Osada | C93: takenori.osada@nttdata.com | D93: NTT DATA Japan Corporation | E93: Tecnical Grade | F93: +818020151828 | G93: iPad Mini (LSA/Mike) | H93: Hari | I93: Influencer | J93: Was in interview | K93: 1 | L93: Add to Mailing List | O93: FALSE | P93: FALSE | Q93: =DATE(2024,10,15)+TIME(10,33,22) -> 45580.44 | R93: Yes | S93: No | Z93: Scanned | AA93: =DATE(2024,10,15)+TIME(17,43,48) -> 45580.739 | AC93: Japan | AD93: Large Solution | AE93: Yes
A94: Henry | B94: Jiang | C94: anke.jiang@plus3it.com | D94: Plus3 IT Solutions | E94: Release Train Engineer | F94: 2024688285 | G94: iPad Mini (LSA/Keith) | H94: Hari | I94: Influencer | K94: 1 | L94: Add to Mailing List | O94: FALSE | P94: FALSE | Q94: =DATE(2024,10,16)+TIME(13,4,21) -> 45581.545 | R94: Yes | S94: No | Z94: Scanned | AA94: =DATE(2024,10,16)+TIME(13,4,35) -> 45581.545 | AB94: Virginia | AC94: United States | AD94: Large Solution | AE94: Yes
A95: Mark | B95: Moskovitz | C95: mark.moskovitz@jamf.com | D95: Jamf | E95: Director, Agile Delivery | F95: 312-718-6062 | G95: Christy's iPhone (personal) | H95: Christy | I95: Other: Jamf | J95: Security software focused on Mac OS - we used to use this. | K95: 1 | L95: Add to Mailing List | M95: Sent Initial Email - 23 Oct | O95: TRUE | P95: TRUE | Q95: =DATE(2024,10,14)+TIME(16,37,47) -> 45579.693 | R95: Yes | S95: No | Z95: Scanned | AA95: =DATE(2024,10,14)+TIME(16,38,19) -> 45579.693 | AB95: New Jersey | AC95: United States | AD95: Large Solution | AE95: Yes
A96: Alexandra | B96: Dudzinska | C96: aleksandra.dudzinska@gmail.com | D96: Independent | E96: PM | F96: 0031651133749 | G96: Taylor's iPhone (personal) | H96: Taylor | K96: 1 | O96: FALSE | P96: FALSE | Q96: =DATE(2024,10,15)+TIME(10,25,25) -> 45580.434 | R96: No | Z96: Scanned | AA96: =DATE(2024,10,15)+TIME(10,25,31) -> 45580.434 | AC96: The Netherlands | AD96: Large Solution | AE96: Yes
A97: Carmen | B97: Graver | C97: cgraver@graveragileinnovations.com | D97: Graver Agile Innovations, LLC | E97: Enterprise Agile Coach | F97: 7035595306 | G97: Mike's iPhone (personal) | H97: Mike | I97: Other: None | J97: Little interest | K97: 1 | L97: Add to Mailing List | M97: EMAIL_CLIENT_LOW - Send email asking for follow-up discussion; attach usual table insert | N97: none | O97: TRUE | P97: TRUE | Q97: =DATE(2024,10,15)+TIME(15,35,43) -> 45580.65 | R97: Yes | S97: No | V97: 7035595306 | Z97: Scanned | AA97: =DATE(2024,10,15)+TIME(17,44,1) -> 45580.739 | AB97: Virginia | AC97: United States | AD97: Large Solution | AE97: Yes
A98: Tom | B98: Hashem | C98: tom.hashem@seekquality.net | D98: Seek Quality, LLC | E98: CEO | F98: 8649401447 | G98: iPad Mini (LSA/Mike) | H98: Taylor | I98: Influencer | K98: 1 | L98: Add to Mailing List | O98: FALSE | P98: FALSE | Q98: =DATE(2024,10,15)+TIME(10,44,31) -> 45580.448 | R98: Yes | S98: No | Z98: Scanned | AA98: =DATE(2024,10,15)+TIME(17,43,48) -> 45580.739 | AB98: South Carolina | AC98: United States | AD98: Large Solution | AE98: Yes
A99: Nelson | B99: de la Cruz | C99: nelson.delacruz@softwareag.com | D99: SoftwareAG | G99: iPad Mini (LSA/Keith) | H99: Hari | I99: Budget authority | J99: Video entry | K99: 1 | L99: N/A | O99: FALSE | P99: FALSE | Q99: =DATE(2024,10,15)+TIME(9,12,58) -> 45580.384 | R99: Yes | S99: No | Z99: Scanned | AA99: =DATE(2024,10,15)+TIME(9,13,15) -> 45580.384 | AC99: United States | AD99: Large Solution | AE99: Yes
A100: Amita | B100: Koduru | C100: amitarao@yahoo.com | D100: Synchrony Financial | E100: Solution Train Engineer | F100: 77-8265345 | G100: Taylor's iPhone (personal) | H100: Taylor | K100: 1 | O100: FALSE | P100: FALSE | Q100: =DATE(2024,10,15)+TIME(13,56,0) -> 45580.581 | R100: No | Z100: Scanned | AA100: =DATE(2024,10,15)+TIME(13,56,7) -> 45580.581 | AB100: Georgia | AC100: United States | AD100: Large Solution | AE100: Yes
...

Sheet Registrant -Attendee Burndown 
A1: Company Name | B1: Title | C1: Name | D1: Scaled Agile Partner | E1: Summit Sponsor? | F1: Met Before? | G1: In Hubspot | H1: LSA Assigned POC | I1: Status on OutReach - Kurt email | J1: Status on OutReach - app | K1: Intro text | L1: Notes
A2: 76 SWEG/ 558 CL | B2: Director | G2: No
A3: 76 SWEG/ 558 MXDPA | B3: Product Manager | G3: No
A4: 76 SWEG/ 558 MXDPB | B4: Computer Scientist/Product Manager | G4: No
A5: 76 SWEG/ 558 MXDPC | B5: Lead Acquisition Program Manager | G5: No
A6: 76th Software Engineering Group (76 SWEG) | B6: Industrial Engineer | G6: No
A7: Acato Information Management, LLC | B7: CEO | G7: No
A8: Accenture Federal Services | B8: SAFe SPCT | D8: Global SPCT | G8: Yes | H8: Kurt | I8: Email Sent | J8: Sent | K8: Hello Shawn. I wanted to follow up on my previous email regarding potential opportunities to connect at the SAFe Summit. LSA Digital specializes in agility-at-scale + EA + ITSM solutions, and we’re keen to explore ways to collaborate or partner with Accenture to enhance process maturity and compliance adoption. Looking forward to hearing from you and hopefully discussing potential synergies at the Summit! | L8: Chris Palmisano David Sanvar Erica Stevens Nicole Koonce Mr Scott Frost Shelagh Worfolk STEVE "ACE" LEE
A9: Accenture Federal Services (AFS) | B9: SAFe Fellow SPCT | D9: Global SPCT | G9: No | H9: Kurt | I9: Email Sent | J9: Sent | K9: Hello Shawn. I wanted to follow up on my previous email regarding potential opportunities to connect at the SAFe Summit. LSA Digital specializes in agility-at-scale + EA + ITSM solutions, and we’re keen to explore ways to collaborate or partner with Accenture to enhance process maturity and compliance adoption. Looking forward to hearing from you and hopefully discussing potential synergies at the Summit! | L9: Shawn Lowe
A10: Adaptavist | B10: VP Enterprise Agility | D10: Gold | E10: Yes | G10: No | H10: Kurt | I10: Email Sent | J10: Sent | K10: Hello Jean. I wanted to follow up on my previous email regarding potential opportunities to connect at the SAFe Summit. LSA Digital specializes in agility-at-scale + EA + ITSM solutions, and we’re eager to explore ways to collaborate or partner with Adaptavist to enhance process maturity and compliance adoption. Looking forward to hearing from you and hopefully discussing potential synergies at the Summit! | L10: Cassandra Moll Jean Henson Lorenzo aluzzi Peter Kerigan Tina Behers Vanessa Finnie
A11: Adaptworks | B11: Chief Learning Officer | D11: Gold | G11: No | H11: Kurt | I11: Email Sent | J11: Connected / Sent | K11: Hello Roberto. I wanted to follow up on my previous email regarding potential opportunities to connect at the SAFe Summit. LSA Digital specializes in agility-at-scale + EA + ITSM solutions, and we’re eager to explore ways to collaborate or partner with Adaptworks to enhance process maturity and compliance adoption. Looking forward to hearing from you and hopefully discussing potential synergies at the Summit! | L11: Roberto Baptista, PhD
A12: Advance Agility | B12: SAFe Coach - SPCT | D12: Platinum SPCT | G12: No | H12: Dani
A13: Aedifides LLC | B13: Founder | G13: No
A14: AFSC/SWTP | B14: Electronics Engineer | G14: No
A15: Agile Agilist | B15: VP Transformation | G15: No | H15: Dani
A16: Agile Big Picture | B16: Consultant, SPCT, SAFe Fellow | G16: No | H16: Dani
A17: Agile Hive | B17: Sales Consultant | D17: Platform | E17: Yes | G17: No | H17: Dani | J17: Sent | K17: I wanted to freach out about potential opportunities to connect at the SAFe Summit. LSA Digital, like Agile Hive, is an Atlassian partner specializing in agility-at-scale + EA + ITSM solutions, and we see great potential for collaboration. We’d love to explore how our Agile transformation and enterprise architecture capabilities can complement your offerings to drive even greater value for clients. | L17: Daniel Roller Janik Röhler Joshua Brock Mr. Thomas Kretzer Veline Schroth
A18: Agile Rising | B18: CEO, SPCT | D18: Gold SPCT | G18: No | H18: Dani | J18: Sent | K18: I’m reaching out regarding potential opportunities to connect at the SAFe Summit. LSA Digital specializes in agility-at-scale + EA + ITSM solutions, and we see strong potential for collaboration with Agile Rising, given your expertise in enterprise agility and SAFe transformation. We’d love to explore how our Agile transformation and enterprise architecture capabilities can complement your offerings to drive greater value for clients. | L18: Chrstopher Ruch
A19: Agile Velocity | B19: Transformation Coach | D19: Silver | G19: No | H19: Dani | J19: Sent | K19: I’m reaching out regarding potential opportunities to connect at the SAFe Summit. LSA Digital specializes in agility-at-scale + EA + ITSM solutions, and we see strong potential for collaboration with Agile Velocity, given your expertise in Agile transformation and scaling frameworks. We’d love to explore how our Agile transformation and enterprise architecture capabilities can complement your services to drive greater value for clients. | L19: Bhavani Krishnan Dave Gipp David Pointer James Hawks
A20: AgileKlix | B20: Agile Coach | G20: No | H20: Dani
A21: AgileMindset | B21: Managing Director | G21: No | H21: Dani
A22: AgileSherpas | B22: Chief Value Officer | D22: Bronze | F22: Yes | G22: No | H22: Dani | J22: Sent | K22: I’m reaching out regarding potential opportunities to connect at the SAFe Summit. LSA Digital specializes in agility-at-scale + EA + ITSM solutions, and we see strong potential for collaboration with AgileSherpas, given your expertise in Agile marketing and transformation. We’d love to explore how our Agile transformation and enterprise architecture capabilities can complement your services to drive greater value for clients. | L22: Andrea Fyrear Ross Libby
A23: AgilityHealth | B23: VP Partners and Government | D23: Platform | E23: Yes | F23: Georgia Ouren - This is an opportunity for LSA to partner with Agility Health Radar and Scaled Agile Institute to provide training as part of gap closure from the health assessments service. | G23: Yes | H23: Dani | I23: Email Sent | J23: Connected / Sent | K23: I’m reaching out regarding potential opportunities to connect at the SAFe Summit. LSA Digital specializes in agility-at-scale + EA + ITSM solutions, and we see great potential for collaboration with AgilityHealth, given your expertise in Agile maturity assessments and transformation. We’d love to explore how our Agile transformation and enterprise architecture capabilities can complement your offerings to drive greater value for clients. | L23: Erin Rae McCaslin Georgia Ouren Mike Stoner Trisha Hal
A24: AgilityIRL, Inc. | B24: Partner | G24: No | H24: Dani
A25: Aledade | B25: Director, Agile Process | G25: No
A26: Allegion | B26: Release Train Engineer | G26: No
A27: Allegis Group, Inc. | B27: Release Train Engineer | G27: No
A28: Alliant Credit Union | B28: Project Manager | G28: No
A29: American Chemical Society | B29: Technology Strategy Analyst | G29: No
A30: American Express | B30: Director- Product Development and Integration | F30: NGLCC | G30: Yes | I30: Email Sent
A31: American Honda | B31: Enterprise SPC | G31: No
A32: American Honda Motor | B32: IT Manager | G32: No
A33: American Honda Motor Co., Inc. | B33: Director, New Business Support & Compliance | G33: No
A34: American Honda Motor Company | B34: IT Team manager | G34: No
A35: American Honda Motor Inc. | B35: Release Train Engineer (RTE) | G35: No
A36: American Integrity Insurance | B36: Project Delivery Manager | G36: No
A37: American National Insurance | B37: Agile Transformation Lead | G37: No
A38: American National Insurance Company | B38: Lead Scrum Master | G38: No
A39: American Red Cross | B39: Agile Transformation Coach | F39: NGLCC | G39: Yes | I39: Email Sent
A40: AmeriCorps | B40: Governance and Oversight Division Chief | G40: No
A41: Amex | B41: Release Train Engineer | F41: NGLCC | G41: No | H41: Kurt | I41: Email Sent
A42: Amgen | B42: Associate Vice President | F42: NGLCC | G42: Yes | I42: Email Sent
A43: Amtrak | B43: Director, Agile Transformation | F43: NGLCC / SAFe Day Gov 2024 - Jamie Shopland | G43: Yes | I43: Email Sent
A44: AnaVation | B44: Principle for Cyber Technologies | G44: No
A45: Anika Systems | B45: Agile Coach | G45: No
A46: Ansys, Inc. | B46: I.T. Manager | G46: No
A47: Appddiction Studio | B47: CEO | D47: Gold | G47: No | H47: Kurt | I47: Email Sent | J47: Sent | K47: I wanted to follow up on my previous email regarding potential opportunities to connect at the SAFe Summit. LSA Digital specializes in agility-at-scale + EA + ITSM solutions, and we’re interested in exploring ways to collaborate or partner with Appddiction Studio to enhance process maturity and compliance adoption. | L47: Timothy Porter (CEO) Anthony Ortega
A48: Applied Frameworks | B48: SVP Sales | D48: Gold SPCT | G48: No | H48: Kurt | I48: Email Sent | J48: Sent | K48: I wanted to follow up on my previous email regarding potential opportunities to connect at the SAFe Summit. LSA Digital specializes in agility-at-scale + EA + ITSM solutions, and we see a strong synergy between our capabilities and Applied Frameworks’ expertise in SAFe and Agile practices. We believe there’s a great opportunity to collaborate, combining our strengths in scaling Agile frameworks, enterprise architecture, and ITSM solutions with your proven methodologies in Agile transformation. Together, we could accelerate the adoption of mature processes and compliance for our clients. Looking forward to hearing from you and discussing potential partnership opportunities at the Summit! | L48: Luke Hohmann Laura Caldie
A49: Applied Frameworks, Inc. | B49: Chief Innovation Officer | D49: Gold SPCT | G49: No | H49: Kurt | I49: Email Sent | J49: Sent | K49: I wanted to follow up on my previous email regarding potential opportunities to connect at the SAFe Summit. LSA Digital specializes in agility-at-scale + EA + ITSM solutions, and we see a strong synergy between our capabilities and Applied Frameworks’ expertise in SAFe and Agile practices. We believe there’s a great opportunity to collaborate, combining our strengths in scaling Agile frameworks, enterprise architecture, and ITSM solutions with your proven methodologies in Agile transformation. Together, we could accelerate the adoption of mature processes and compliance for our clients. Looking forward to hearing from you and discussing potential partnership opportunities at the Summit! | L49: Luke Hohmann Laura Caldie
A50: ibm | B50: Solutions Architect | D50: Platform Plus | E50: Yes | G50: No | H50: Craig
A51: ArcBest Technologies | B51: Associate Director | G51: No
A52: Ariel Partners | B52: CTO | D52: Silver | F52: NDA Partners / Craeg Strong CTO | G52: Yes | H52: Kurt | I52: NDA Partners / Email Sent | J52: Sent | K52: Hey Craeg. looking forward to seeing you at the summit and exploring more ways we can partner together | L52: Craeg Strong
A53: Armstrong Fluid Technology | B53: Director, Agile Portfolio Management | G53: No
A54: Army | B54: Requirements Manager/APM Intern | G54: No
A55: Army CHESS | B55: Technical Director | G55: No
A56: Arvest | B56: IT Manager | F56: NGLCC | G56: Yes
A57: Arvest Bank | B57: Senior Manager | F57: Unknown | G57: Yes
A58: Ascend SC | B58: Release Train Engineer | G58: No
A59: Ascendant Agility | B59: SAFe Fellow | G59: No | H59: Dani
A60: Ascension Health | B60: Director Technology | G60: No
A61: Aspen Technology | B61: Sr. Engineer | G61: No
A62: Assurant | B62: Director of Agile Enablement Office | G62: No
A63: AstraZeneca | B63: IT Patient Platform Delivery Lead, RTE | F63: NGLCC | G63: Yes | I63: Email Sent
A64: AT&T | B64: Agile Coach | F64: NGLCC | G64: Yes | I64: Email Sent
A65: Atlas Revolutions | B65: CIO | G65: No
A66: Atlassian | B66: Field Marketing Manager | C66: Charlee Chayatanan | D66: Platform | E66: Yes | F66: Partners | G66: Yes | H66: Keith | I66: Sent | J66: Sent | K66: Hi Charlee, | L66: Charlene
A67: Bank of Industry Limited | B67: Senior Manager/Scrum Master | G67: No
A68: BCBSND | B68: Sr. System Delivery Analyst | G68: No | K68: I’ll be at the Summit and would love to connect if you have a few minutes? LSA Digital is an Atlassian Silver Partner, working with clients in implementation and best practices.
A69: BCforward | B69: SPC, Release Train Engineer | D69: Bronze | G69: No | H69: Kurt | I69: Email Sent | J69: Sent | K69: I wanted to follow up on my previous email regarding potential opportunities to connect at the SAFe Summit. LSA Digital specializes in agility-at-scale + EA + ITSM solutions, and we see potential for strong collaboration with BCforward, leveraging our combined strengths to enhance process maturity and compliance adoption for clients. We’d love to explore how our expertise in scaling Agile frameworks and enterprise architecture could complement your delivery capabilities | L69: Carla Uycoque Elizabeth German Jeremy Wheratt Jospeh Haskins
A70: Bell Canada | B70: Agile Coach | G70: No | K70: I’d love to hear from you on how we can best market & work with the Atlassian team to deliver results to our current mutual clients and potential ones.
A71: Beyond Enough | B71: Principal Consultant | G71: No
A72: Biogen | B72: Director, ITSM & DevOps Processes | G72: No | K72: I’ll be there all week (Monday AM to Friday AM).
A73: Blackbaud | B73: Manager, PMO | G73: No
A74: Blackbaud, inc | B74: SPC | G74: No | K74: Cheers,
A75: Bloomberg | B75: Product Delivery Manager | F75: RocketReach | G75: Yes | I75: Email Sent | K75: Keith
A76: Bloomberg LP | B76: ENG Core Group PDM Manager | F76: NGLCC | G76: Yes | I76: Email Sent
A77: Blue Cross Blue Shield Association | B77: Managing Director, Digital Design Program | F77: NGLCC | G77: No | H77: Kurt | I77: Email Sent
A78: Blue Shield of California | B78: Executive Agile Coach | G78: No
A79: BlueShield of California | B79: Sr. Manager Program Management | G79: No
A80: Bobcat | B80: Scrum Master | G80: No
A81: Bobcat Company | B81: Digital Products RTE and DXP Program Manager | G81: No
A82: Booz Allen | B82: Senior Enterprise Coach | D82: Government Elite | F82: NGLCC / Registered in Portal | G82: No | H82: Kurt | I82: Email Sent
A83: Booz Allen Hamilton | B83: Principal/Director | D83: Government Elite | F83: NGLCC / Registered in Portal | G83: No | H83: Kurt | I83: Email Sent
A84: Brightlens Group | B84: VP, Change | G84: No
A85: Broadcom | B85: Product Manager | D85: Gold & Platform | E85: Yes | G85: No | H85: Kurt | I85: Email Sent | J85: Sent | K85: I wanted to follow up on my previous email regarding potential opportunities to connect at the SAFe Summit. LSA Digital specializes in agility-at-scale + EA + ITSM solutions, and we see a great opportunity to collaborate with Broadcom, combining our expertise in enterprise architecture and Agile transformation with your robust portfolio of enterprise solutions. We believe working together could accelerate process maturity, compliance adoption, and agility efforts. | L85: Bill Bunce Brad Kistler Emma Price Jennifer Castro Marie Kalliney Matthew Gorbsky Pamela Meredith
A86: CACI | B86: Agile Coach | D86: Gold | G86: No | H86: Kurt | I86: Email Sent | J86: Sent | K86: I wanted to follow up on my previous email regarding potential opportunities to connect at the SAFe Summit. LSA Digital specializes in agility-at-scale + EA + ITSM solutions, and we see great alignment with CACI’s mission-critical technology solutions. We’d love to explore how our expertise in Agile transformation and IT service management can complement CACI’s strengths in cybersecurity and enterprise IT to drive impactful outcomes for government clients. | L86: Anju Baraya Chris Ham Steve Brylski
A87: CACI Inc. | B87: Agile Solution Factory Director | D87: Gold | G87: No | H87: Kurt | I87: Email Sent | J87: Sent | K87: I wanted to follow up on my previous email regarding potential opportunities to connect at the SAFe Summit. LSA Digital specializes in agility-at-scale + EA + ITSM solutions, and we see great alignment with CACI’s mission-critical technology solutions. We’d love to explore how our expertise in Agile transformation and IT service management can complement CACI’s strengths in cybersecurity and enterprise IT to drive impactful outcomes for government clients. | L87: Anju Baraya Chris Ham Steve Brylski
A88: Campbell Soup Company | B88: Sr. Manager, Digital Partner | G88: No
A89: Canada Goose | B89: Senior Director, Agile COE | G89: No
A90: Capco | B90: Principal Consultant | F90: NGLCC | G90: Yes | I90: Email Sent
A91: Capgemini | B91: Engagement Director | D91: Gold SPCT | F91: NGLCC | G91: Yes | H91: Kurt | I91: Email Sent
A92: CapTech Consulting | B92: Senior Manager | D92: Silver | F92: RR Lead | G92: Yes | H92: Kurt | I92: Email Sent | J92: Sent | K92: I wanted to follow up on my previous email regarding potential opportunities to connect at the SAFe Summit. LSA Digital specializes in agility-at-scale + EA + ITSM solutions, and we see strong alignment with CapTech’s focus on delivering innovative digital solutions. We’d love to explore how our expertise in Agile transformation and enterprise architecture can complement CapTech’s capabilities to drive better outcomes for our clients. | L92: MC Moore Virginia Madigan
A93: Carefirst | B93: Release Train Engineer | G93: No
A94: Carefirst/FEPOC | B94: RTE | G94: No
A95: Cascades | B95: IT Director | G95: No
A96: Caterpillar Financial | B96: Project Manager | G96: No
A97: Caterpillar, Inc. | B97: Digital Product Manager | G97: No
A98: catworkx | B98: Global Chief Delivery Officer | D98: Silver | F98: German Company | G98: Yes | H98: Kurt | I98: No email sent | J98: Sent | K98: I wanted to follow up on my previous email regarding potential opportunities to connect at the SAFe Summit. LSA Digital, like Catworkx, is an Atlassian partner specializing in agility-at-scale + EA + ITSM solutions, and we see great potential for collaboration. We’d love to explore how our Agile transformation and enterprise architecture expertise can complement your Atlassian services to drive better outcomes for our clients. | L98: Marco W. Steinborn
A99: catworkx GmbH | B99: CEO | D99: Silver | F99: German Company | G99: Yes | H99: Kurt | I99: No email sent | J99: sent | K99: I wanted to follow up on my previous email regarding potential opportunities to connect at the SAFe Summit. LSA Digital, like Catworkx, is an Atlassian partner specializing in agility-at-scale + EA + ITSM solutions, and we see great potential for collaboration. We’d love to explore how our Agile transformation and enterprise architecture expertise can complement your Atlassian services to drive better outcomes for our clients. | L99: Michael Luer
A100: Cencora | B100: Lead Agile Coach | F100: NGLCC | G100: Yes
...

Sheet Contact Hit List
A1: Priority of Contact | B1: First Name | C1: Last Name | D1: Title | E1: Company | F1: Comments | G1: LSA POC
A2: High | B2: James | C2: Hawk | D2: Chief Strategy Officer | E2: Agile Velocity | F2: I would love to get together explore potential partnering. | G2: Kurt
A3: High | B3: Erin Rae | C3: McClasin | D3: VP Partner Development | E3: Agility Health | F3: Hi Kurt, would love to connect at the event. We‚Äôre looking for strategic partners and see synergies. Should we schedule a time for a conversation? | G3: Kurt
A4: High | B4: ROBERTO | C4: BAPTISTA | D4: Chief Learning Officer | E4: Adaptworks | F4: Hi Kurt, yes, I'd be glad to talk about it at the Summit. | G4: Kurt
A5: High | B5: Ross | C5: Libby | D5: Chief Value Officer | E5: AgileSherpas | F5: Hi Kurt, great to connect and talk about collaboration opportunities. Will you be there for Partner Day? | G5: Kurt
A6: High | B6: Nadia | C6: Kouri | D6: CSPO, Director of Growth | E6: Praecipio | F6: Are you attending the SAFe Summit? I'd love to connect, discuss potential collaborations. | G6: Kurt
A7: High | B7: Luke | C7: Hohmann | D7: Chief Innovation Officer | E7: Applied Frameworks, Inc. | F7: I‚Äôd love to connect. Best options are the euchre and Profit Streams party on Monday or my presentation Wednesday. | G7: Kurt
A8: High | B8: Andrea | C8: Fryrear | D8: CEO | E8: AgileSherpas | F8: Hi Kurt, happy to chat while we're at the Summit. I am getting in Monday. | G8: Kurt
A9: High | B9: William | C9: Leach | D9: Director | E9: National Grid | F9: Very interested to know if you've done anything in the large-scale renewables space. | G9: Kurt
A10: High | B10: Michael | C10: Lüer | D10: CEO | E10: catworkx GmbH | F10: Hi Kurt, nice to meet you virtually. Then let's try physically. Any ideas? | G10: Kurt
A11: High | B11: Stella | C11: O'Brien | D11: Sr. VP Sales | E11: Icon Agility Services | F11: Thanks Kurt! Yes, let‚ try to meet up. Would you want an invite to our Lean Coffee on AI? It's on Wednesday at 10:15 AM with Steve Mayner, SAI. Please send me your email and I'l invite you! | G11: Kurt
A12: Low | B12: Amanda | C12: Balliet | D12: Agile Coach/SPC | E12: IBM | F12: Looking forward to it! | G12: Kurt
... A25: Medium | B25: Jorge | C25: Garcia | D25: Program Manager Lead/RTE | E25: USAA | F25: Thanks for the connect! | G25: Mike

Sheet Original - Registrant Details
A1: Company Name | B1: Title | C1: Last Registration Date (GMT-07:00) Mountain [US & Canada] | D1: Scaled Agile Partner | E1: Met Before? | F1: In Hubspot
A2: 76 SWEG/ 558 CL | B2: Director | C2: =DATE(2024,7,25)+TIME(10,49,41) -> 45498.451 | F2: =VLOOKUP(Table1[[#This Row],[Company Name]],Sheet1!B:B,1,FALSE) -> #N/A
A3: 76 SWEG/ 558 MXDPA | B3: Product Manager | C3: =DATE(2024,7,25)+TIME(10,49,42) -> 45498.451 | F3: =VLOOKUP(Table1[[#This Row],[Company Name]],Sheet1!B:B,1,FALSE) -> #N/A
A4: 76 SWEG/ 558 MXDPB | B4: Computer Scientist/Product Manager | C4: =DATE(2024,7,25)+TIME(10,49,42) -> 45498.451 | F4: =VLOOKUP(Table1[[#This Row],[Company Name]],Sheet1!B:B,1,FALSE) -> #N/A
A5: 76 SWEG/ 558 MXDPB | B5: Electronics Engineer | C5: =DATE(2024,7,25)+TIME(10,49,41) -> 45498.451 | F5: =VLOOKUP(Table1[[#This Row],[Company Name]],Sheet1!B:B,1,FALSE) -> #N/A
A6: 76 SWEG/ 558 MXDPC | B6: Lead Acquisition Program Manager | C6: =DATE(2024,7,25)+TIME(10,49,42) -> 45498.451 | F6: =VLOOKUP(Table1[[#This Row],[Company Name]],Sheet1!B:B,1,FALSE) -> #N/A
A7: 76 SWEG/ 558 MXDPC | B7: Electronics Engineer(Technical Specialist)/RTE | C7: =DATE(2024,7,25)+TIME(10,49,42) -> 45498.451 | F7: =VLOOKUP(Table1[[#This Row],[Company Name]],Sheet1!B:B,1,FALSE) -> #N/A
A8: 76 SWEG/ 558 MXDPC | B8: Electronics Engineer | C8: =DATE(2024,7,25)+TIME(10,49,41) -> 45498.451 | F8: =VLOOKUP(Table1[[#This Row],[Company Name]],Sheet1!B:B,1,FALSE) -> #N/A
A9: 76th Software Engineering Group (76 SWEG) | B9: Industrial Engineer | C9: =DATE(2024,7,1)+TIME(14,31,27) -> 45474.605 | F9: =VLOOKUP(Table1[[#This Row],[Company Name]],Sheet1!B:B,1,FALSE) -> #N/A
A10: 76th Software Engineering Group (76 SWEG) | B10: Computer Scientist | C10: =DATE(2024,7,1)+TIME(14,31,26) -> 45474.605 | F10: =VLOOKUP(Table1[[#This Row],[Company Name]],Sheet1!B:B,1,FALSE) -> #N/A
A11: Acato Information Management, LLC | B11: CEO | C11: =DATE(2024,8,19)+TIME(12,10,58) -> 45523.508 | F11: =VLOOKUP(Table1[[#This Row],[Company Name]],Sheet1!B:B,1,FALSE) -> #N/A
A12: Acato Information Management, LLC | B12: Senior Advisor | C12: =DATE(2024,8,19)+TIME(12,10,58) -> 45523.508 | F12: =VLOOKUP(Table1[[#This Row],[Company Name]],Sheet1!B:B,1,FALSE) -> #N/A
A13: Accenture Federal Services | B13: SAFe SPCT | C13: =DATE(2024,7,26)+TIME(9,34,44) -> 45499.399 | D13: x | F13: Yes
A14: Accenture Federal Services (AFS) | B14: SAFe Fellow SPCT | C14: =DATE(2024,7,26)+TIME(9,10,7) -> 45499.382 | D14: x | F14: =VLOOKUP(Table1[[#This Row],[Company Name]],Sheet1!B:B,1,FALSE) -> #N/A
A15: Adaptavist | B15: VP Enterprise Agility | C15: =DATE(2024,9,2)+TIME(2,46,34) -> 45537.116 | D15: x | F15: =VLOOKUP(Table1[[#This Row],[Company Name]],Sheet1!B:B,1,FALSE) -> #N/A
A16: Adaptavist | B16: Director, Business Agility | C16: =DATE(2024,9,2)+TIME(4,52,50) -> 45537.203 | D16: x | F16: =VLOOKUP(Table1[[#This Row],[Company Name]],Sheet1!B:B,1,FALSE) -> #N/A
A17: Adaptavist | B17: Public Sector Account Executive | C17: =DATE(2024,9,2)+TIME(12,2,4) -> 45537.501 | D17: x | F17: =VLOOKUP(Table1[[#This Row],[Company Name]],Sheet1!B:B,1,FALSE) -> #N/A
A18: Adaptavist | B18: Business Development Representative | C18: =DATE(2024,9,6)+TIME(8,44,54) -> 45541.365 | D18: x | F18: =VLOOKUP(Table1[[#This Row],[Company Name]],Sheet1!B:B,1,FALSE) -> #N/A
A19: Adaptavist | B19: Field Marketing Manager | C19: =DATE(2024,9,6)+TIME(8,42,59) -> 45541.363 | D19: x | F19: =VLOOKUP(Table1[[#This Row],[Company Name]],Sheet1!B:B,1,FALSE) -> #N/A
A20: Adaptworks | B20: Chief Learning Officer | C20: =DATE(2024,8,15)+TIME(13,0,29) -> 45519.542 | D20: x | F20: =VLOOKUP(Table1[[#This Row],[Company Name]],Sheet1!B:B,1,FALSE) -> #N/A
A21: Advance Agility | B21: SAFe Coach - SPCT | C21: =DATE(2024,9,26)+TIME(4,0,4) -> 45561.167 | D21: x | F21: =VLOOKUP(Table1[[#This Row],[Company Name]],Sheet1!B:B,1,FALSE) -> #N/A
A22: Aedifides LLC | B22: Founder | C22: =DATE(2024,9,17)+TIME(19,16,27) -> 45552.803 | F22: =VLOOKUP(Table1[[#This Row],[Company Name]],Sheet1!B:B,1,FALSE) -> #N/A
A23: AFSC/SWTP | B23: Electronics Engineer | C23: =DATE(2024,7,1)+TIME(14,31,27) -> 45474.605 | F23: =VLOOKUP(Table1[[#This Row],[Company Name]],Sheet1!B:B,1,FALSE) -> #N/A
A24: Agile Agilist | B24: VP Transformation | C24: =DATE(2024,8,26)+TIME(8,19,54) -> 45530.347 | F24: =VLOOKUP(Table1[[#This Row],[Company Name]],Sheet1!B:B,1,FALSE) -> #N/A
A25: Agile Agilist | B25: SPCT-Candidate Agility Advisor Expert | C25: =DATE(2024,8,30)+TIME(12,40,42) -> 45534.528 | F25: =VLOOKUP(Table1[[#This Row],[Company Name]],Sheet1!B:B,1,FALSE) -> #N/A
A26: Agile Big Picture | B26: Consultant, SPCT, SAFe Fellow | C26: =DATE(2024,8,22)+TIME(17,14,12) -> 45526.718 | F26: =VLOOKUP(Table1[[#This Row],[Company Name]],Sheet1!B:B,1,FALSE) -> #N/A
A27: Agile Hive | B27: Sales Consultant | C27: =DATE(2024,7,2)+TIME(8,26,9) -> 45475.351 | D27: x | F27: =VLOOKUP(Table1[[#This Row],[Company Name]],Sheet1!B:B,1,FALSE) -> #N/A
A28: Agile Hive | B28: Sales Consultant | C28: =DATE(2024,7,2)+TIME(1,57,1) -> 45475.081 | D28: x | F28: =VLOOKUP(Table1[[#This Row],[Company Name]],Sheet1!B:B,1,FALSE) -> #N/A
A29: Agile Hive | B29: Product Marketing Manager | C29: =DATE(2024,7,26)+TIME(3,10,8) -> 45499.132 | D29: x | F29: =VLOOKUP(Table1[[#This Row],[Company Name]],Sheet1!B:B,1,FALSE) -> #N/A
A30: Agile Hive | B30: Product Owner | C30: =DATE(2024,7,2)+TIME(3,32,17) -> 45475.147 | D30: x | F30: =VLOOKUP(Table1[[#This Row],[Company Name]],Sheet1!B:B,1,FALSE) -> #N/A
A31: Agile Hive | B31: Technical Content Writer | C31: =DATE(2024,7,2)+TIME(3,21,31) -> 45475.14 | D31: x | F31: =VLOOKUP(Table1[[#This Row],[Company Name]],Sheet1!B:B,1,FALSE) -> #N/A
A32: Agile Rising | B32: CEO, SPCT | C32: =DATE(2024,7,15)+TIME(17,2,37) -> 45488.71 | D32: x | F32: =VLOOKUP(Table1[[#This Row],[Company Name]],Sheet1!B:B,1,FALSE) -> #N/A
A33: Agile Velocity | B33: Transformation Coach | C33: =DATE(2024,9,2)+TIME(10,17,56) -> 45537.429 | D33: x | F33: =VLOOKUP(Table1[[#This Row],[Company Name]],Sheet1!B:B,1,FALSE) -> #N/A
A34: Agile Velocity | B34: Agile Coach | C34: =DATE(2024,9,4)+TIME(9,53,8) -> 45539.412 | D34: x | F34: =VLOOKUP(Table1[[#This Row],[Company Name]],Sheet1!B:B,1,FALSE) -> #N/A
A35: Agile Velocity | B35: CSO | C35: =DATE(2024,9,6)+TIME(11,3,43) -> 45541.461 | D35: x | F35: =VLOOKUP(Table1[[#This Row],[Company Name]],Sheet1!B:B,1,FALSE) -> #N/A
A36: Agile Velocity | B36: Enterprise Agile Coach | C36: =DATE(2024,8,29)+TIME(6,21,54) -> 45533.265 | D36: x | F36: =VLOOKUP(Table1[[#This Row],[Company Name]],Sheet1!B:B,1,FALSE) -> #N/A
A37: AgileKlix | B37: Agile Coach | C37: =DATE(2024,9,15)+TIME(10,19,7) -> 45550.43 | F37: =VLOOKUP(Table1[[#This Row],[Company Name]],Sheet1!B:B,1,FALSE) -> #N/A
A38: AgileMindset | B38: Managing Director | C38: =DATE(2024,6,21)+TIME(7,34,33) -> 45464.316 | F38: =VLOOKUP(Table1[[#This Row],[Company Name]],Sheet1!B:B,1,FALSE) -> #N/A
A39: AgileSherpas | B39: Chief Value Officer | C39: =DATE(2024,9,23)+TIME(9,46,11) -> 45558.407 | D39: x | E39: Yes | F39: =VLOOKUP(Table1[[#This Row],[Company Name]],Sheet1!B:B,1,FALSE) -> #N/A
A40: AgileSherpas | B40: CEO | C40: =DATE(2024,9,23)+TIME(11,22,32) -> 45558.474 | D40: x | E40: Yes | F40: =VLOOKUP(Table1[[#This Row],[Company Name]],Sheet1!B:B,1,FALSE) -> #N/A
A41: AgilityHealth | B41: VP Partners and Government | C41: =DATE(2024,8,22)+TIME(9,7,34) -> 45526.38 | D41: x | E41: Georgia Ouren - This is an opportunity for LSA to partner with Agility Health Radar and Scaled Agile Institute to provide training as part of gap closure from the health assessments service. | F41: Yes
A42: AgilityHealth | B42: VP Enterprise Solutions | C42: =DATE(2024,8,21)+TIME(10,56,16) -> 45525.456 | D42: x | E42: Yes | F42: Yes
A43: AgilityHealth | B43: VP Partner Development | C43: =DATE(2024,8,22)+TIME(9,25,21) -> 45526.393 | D43: x | E43: Yes | F43: Yes
A44: AgilityHealth | B44: VP Sales | C44: =DATE(2024,8,22)+TIME(9,25,21) -> 45526.393 | D44: x | E44: Yes | F44: Yes
A45: AgilityIRL, Inc. | B45: Partner | C45: =DATE(2024,8,1)+TIME(11,16,55) -> 45505.47 | F45: =VLOOKUP(Table1[[#This Row],[Company Name]],Sheet1!B:B,1,FALSE) -> #N/A
A46: Aledade | B46: Director, Agile Process | C46: =DATE(2024,9,5)+TIME(8,44,28) -> 45540.364 | F46: =VLOOKUP(Table1[[#This Row],[Company Name]],Sheet1!B:B,1,FALSE) -> #N/A
A47: Allegion | B47: Release Train Engineer | C47: =DATE(2024,7,3)+TIME(9,46,33) -> 45476.407 | F47: =VLOOKUP(Table1[[#This Row],[Company Name]],Sheet1!B:B,1,FALSE) -> #N/A
A48: Allegis Group, Inc. | B48: Release Train Engineer | C48: =DATE(2024,7,12)+TIME(8,43,45) -> 45485.364 | F48: =VLOOKUP(Table1[[#This Row],[Company Name]],Sheet1!B:B,1,FALSE) -> #N/A
A49: Alliant Credit Union | B49: Project Manager | C49: =DATE(2024,9,26)+TIME(11,23,34) -> 45561.475 | F49: =VLOOKUP(Table1[[#This Row],[Company Name]],Sheet1!B:B,1,FALSE) -> #N/A
A50: American Chemical Society | B50: Technology Strategy Analyst | C50: =DATE(2024,8,21)+TIME(10,56,40) -> 45525.456 | F50: =VLOOKUP(Table1[[#This Row],[Company Name]],Sheet1!B:B,1,FALSE) -> #N/A
A51: American Express | B51: Director- Product Development and Integration | C51: =DATE(2024,9,25)+TIME(18,36,3) -> 45560.775 | E51: NGLCC | F51: Yes
A52: American Express | B52: SR MANAGER-DIGITAL PORTFOLIO MGMT, EFFICIENCY CONSULTING | C52: =DATE(2024,9,13)+TIME(9,22,16) -> 45548.39 | E52: NGLCC | F52: Yes
A53: American Express | B53: Senior Technical Program Manager | C53: =DATE(2024,8,26)+TIME(12,36,18) -> 45530.525 | E53: NGLCC | F53: Yes
A54: American Express | B54: Director, Portfolio & Investments | C54: =DATE(2024,9,13)+TIME(9,7,50) -> 45548.38 | E54: NGLCC | F54: Yes
A55: American Express | B55: Senior Manager, Agile Transformation | C55: =DATE(2024,9,26)+TIME(14,13,16) -> 45561.593 | E55: NGLCC | F55: Yes
A56: American Honda | B56: Enterprise SPC | C56: =DATE(2024,8,26)+TIME(9,51,50) -> 45530.411 | F56: =VLOOKUP(Table1[[#This Row],[Company Name]],Sheet1!B:B,1,FALSE) -> #N/A
A57: American Honda Motor | B57: IT Manager | C57: =DATE(2024,6,13)+TIME(13,21,57) -> 45456.557 | F57: =VLOOKUP(Table1[[#This Row],[Company Name]],Sheet1!B:B,1,FALSE) -> #N/A
A58: American Honda Motor Co., Inc. | B58: Director, New Business Support & Compliance | C58: =DATE(2024,6,6)+TIME(13,41,57) -> 45449.571 | F58: =VLOOKUP(Table1[[#This Row],[Company Name]],Sheet1!B:B,1,FALSE) -> #N/A
A59: American Honda Motor Co., Inc. | B59: SPC | C59: =DATE(2024,7,31)+TIME(8,45,41) -> 45504.365 | F59: =VLOOKUP(Table1[[#This Row],[Company Name]],Sheet1!B:B,1,FALSE) -> #N/A
A60: American Honda Motor Co., Inc. | B60: SAFe Agile Coach | C60: =DATE(2024,7,31)+TIME(8,46,41) -> 45504.366 | F60: =VLOOKUP(Table1[[#This Row],[Company Name]],Sheet1!B:B,1,FALSE) -> #N/A
A61: American Honda Motor Company | B61: IT Team manager | C61: =DATE(2024,8,1)+TIME(6,30,16) -> 45505.271 | F61: =VLOOKUP(Table1[[#This Row],[Company Name]],Sheet1!B:B,1,FALSE) -> #N/A
A62: American Honda Motor Inc. | B62: Release Train Engineer (RTE) | C62: =DATE(2024,9,4)+TIME(7,42,46) -> 45539.321 | F62: =VLOOKUP(Table1[[#This Row],[Company Name]],Sheet1!B:B,1,FALSE) -> #N/A
A63: American Integrity Insurance | B63: Project Delivery Manager | C63: =DATE(2024,7,11)+TIME(9,10,1) -> 45484.382 | F63: =VLOOKUP(Table1[[#This Row],[Company Name]],Sheet1!B:B,1,FALSE) -> #N/A
A64: American Integrity Insurance | B64: Project Delivery Manager | C64: =DATE(2024,7,11)+TIME(9,10,2) -> 45484.382 | F64: =VLOOKUP(Table1[[#This Row],[Company Name]],Sheet1!B:B,1,FALSE) -> #N/A
A65: American National Insurance | B65: Agile Transformation Lead | C65: =DATE(2024,9,23)+TIME(9,25,44) -> 45558.393 | F65: =VLOOKUP(Table1[[#This Row],[Company Name]],Sheet1!B:B,1,FALSE) -> #N/A
A66: American National Insurance | B66: AVP, Solution Architecture | C66: =DATE(2024,8,15)+TIME(14,26,54) -> 45519.602 | F66: =VLOOKUP(Table1[[#This Row],[Company Name]],Sheet1!B:B,1,FALSE) -> #N/A
A67: American National Insurance Company | B67: Lead Scrum Master | C67: =DATE(2024,8,20)+TIME(15,25,18) -> 45524.643 | F67: =VLOOKUP(Table1[[#This Row],[Company Name]],Sheet1!B:B,1,FALSE) -> #N/A
A68: American Red Cross | B68: Agile Transformation Coach | C68: =DATE(2024,9,17)+TIME(6,53,25) -> 45552.287 | E68: NGLCC | F68: Yes
A69: AmeriCorps | B69: Governance and Oversight Division Chief | C69: =DATE(2024,8,12)+TIME(8,40,0) -> 45516.361 | F69: =VLOOKUP(Table1[[#This Row],[Company Name]],Sheet1!B:B,1,FALSE) -> #N/A
A70: AmeriCorps | B70: IT Project Manager | C70: =DATE(2024,9,9)+TIME(14,12,57) -> 45544.592 | F70: =VLOOKUP(Table1[[#This Row],[Company Name]],Sheet1!B:B,1,FALSE) -> #N/A
A71: AmeriCorps | B71: Project Manager | C71: =DATE(2024,8,9)+TIME(11,45,29) -> 45513.49 | F71: =VLOOKUP(Table1[[#This Row],[Company Name]],Sheet1!B:B,1,FALSE) -> #N/A
A72: Amex | B72: Release Train Engineer | C72: =DATE(2024,8,29)+TIME(13,10,47) -> 45533.549 | E72: NGLCC | F72: =VLOOKUP(Table1[[#This Row],[Company Name]],Sheet1!B:B,1,FALSE) -> #N/A
A73: Amgen | B73: Associate Vice President | C73: =DATE(2024,7,21)+TIME(18,45,38) -> 45494.782 | E73: NGLCC | F73: Yes
A74: Amtrak | B74: Director, Agile Transformation | C74: =DATE(2024,9,19)+TIME(11,45,5) -> 45554.49 | E74: NGLCC / SAFe Day Gov 2024 - Jamie Shopland | F74: Yes
A75: AMTRAK | B75: Senior Director, Organizational Change Management | C75: =DATE(2024,9,18)+TIME(14,1,5) -> 45553.584 | E75: NGLCC | F75: Yes
A76: Amtrak | B76: SAFe Coach | C76: =DATE(2024,8,7)+TIME(9,32,20) -> 45511.397 | E76: NGLCC | F76: Yes
A77: Amtrak | B77: Director | C77: =DATE(2024,9,23)+TIME(11,3,4) -> 45558.46 | E77: NGLCC | F77: Yes
A78: AMTRAK | B78: AVP, Operations Management and Tech | C78: =DATE(2024,9,17)+TIME(5,45,17) -> 45552.24 | E78: NGLCC | F78: Yes
A79: AMTRAK | B79: Senior Director, Lean Portfolio Management | C79: =DATE(2024,8,26)+TIME(8,55,25) -> 45530.372 | E79: NGLCC | F79: Yes
A80: AMTRAK | B80: Vice President, DT Technology Operations | C80: =DATE(2024,9,17)+TIME(5,50,4) -> 45552.243 | E80: NGLCC | F80: Yes
A81: AMTRAK | B81: Vice President, Chief Digital Officer | C81: =DATE(2024,9,17)+TIME(5,31,20) -> 45552.23 | E81: NGLCC | F81: Yes
A82: AnaVation | B82: Principle for Cyber Technologies | C82: =DATE(2024,7,26)+TIME(12,15,42) -> 45499.511 | F82: =VLOOKUP(Table1[[#This Row],[Company Name]],Sheet1!B:B,1,FALSE) -> #N/A
A83: Anika Systems | B83: Agile Coach | C83: =DATE(2024,6,2)+TIME(8,8,33) -> 45445.339 | F83: =VLOOKUP(Table1[[#This Row],[Company Name]],Sheet1!B:B,1,FALSE) -> #N/A
A84: Ansys, Inc. | B84: I.T. Manager | C84: =DATE(2024,7,9)+TIME(13,37,53) -> 45482.568 | F84: =VLOOKUP(Table1[[#This Row],[Company Name]],Sheet1!B:B,1,FALSE) -> #N/A
A85: Appddiction Studio | B85: CEO | C85: =DATE(2024,8,16)+TIME(10,40,44) -> 45520.445 | D85: x | F85: =VLOOKUP(Table1[[#This Row],[Company Name]],Sheet1!B:B,1,FALSE) -> #N/A
A86: Appddiction Studio | B86: Sr Solution Architect | C86: =DATE(2024,8,16)+TIME(10,40,45) -> 45520.445 | D86: x | F86: =VLOOKUP(Table1[[#This Row],[Company Name]],Sheet1!B:B,1,FALSE) -> #N/A
A87: Applied Frameworks | B87: SVP Sales | C87: =DATE(2024,9,5)+TIME(8,43,25) -> 45540.363 | D87: x | F87: =VLOOKUP(Table1[[#This Row],[Company Name]],Sheet1!B:B,1,FALSE) -> #N/A
A88: Applied Frameworks, Inc. | B88: Chief Innovation Officer | C88: =DATE(2024,7,29)+TIME(16,1,5) -> 45502.667 | D88: x | F88: =VLOOKUP(Table1[[#This Row],[Company Name]],Sheet1!B:B,1,FALSE) -> #N/A
A89: Apptio, an IBM Company | B89: Solutions Architect | C89: =DATE(2024,9,19)+TIME(7,38,37) -> 45554.318 | D89: x | F89: =VLOOKUP(Table1[[#This Row],[Company Name]],Sheet1!B:B,1,FALSE) -> #N/A
A90: Apptio, an IBM Company | B90: Sr. Solutions Consultant | C90: =DATE(2024,8,21)+TIME(12,43,50) -> 45525.53 | D90: x | F90: =VLOOKUP(Table1[[#This Row],[Company Name]],Sheet1!B:B,1,FALSE) -> #N/A
A91: Apptio, an IBM Company | B91: Partner Sales Manager Americas ATP | C91: =DATE(2024,9,16)+TIME(9,19,11) -> 45551.388 | D91: x | F91: =VLOOKUP(Table1[[#This Row],[Company Name]],Sheet1!B:B,1,FALSE) -> #N/A
A92: ArcBest Technologies | B92: Associate Director | C92: =DATE(2024,9,13)+TIME(9,11,59) -> 45548.383 | F92: =VLOOKUP(Table1[[#This Row],[Company Name]],Sheet1!B:B,1,FALSE) -> #N/A
A93: Ariel Partners | B93: CTO | C93: =DATE(2024,8,9)+TIME(10,15,7) -> 45513.427 | D93: x | E93: NDA Partners / Craeg Strong CTO | F93: Yes
A94: Ariel Partners | B94: President | C94: =DATE(2024,8,9)+TIME(16,2,35) -> 45513.668 | D94: x | E94: NDA Partners / Craeg Strong CTO | F94: Yes
A95: Armstrong Fluid Technology | B95: Director, Agile Portfolio Management | C95: =DATE(2024,7,30)+TIME(14,7,3) -> 45503.588 | F95: =VLOOKUP(Table1[[#This Row],[Company Name]],Sheet1!B:B,1,FALSE) -> #N/A
A96: Army | B96: Requirements Manager/APM Intern | C96: =DATE(2024,9,18)+TIME(15,44,15) -> 45553.656 | F96: =VLOOKUP(Table1[[#This Row],[Company Name]],Sheet1!B:B,1,FALSE) -> #N/A
A97: Army CHESS | B97: Technical Director | C97: =DATE(2024,9,9)+TIME(12,19,43) -> 45544.514 | F97: =VLOOKUP(Table1[[#This Row],[Company Name]],Sheet1!B:B,1,FALSE) -> #N/A
A98: Army CHESS | B98: Product Lead | C98: =DATE(2024,9,9)+TIME(12,19,43) -> 45544.514 | F98: =VLOOKUP(Table1[[#This Row],[Company Name]],Sheet1!B:B,1,FALSE) -> #N/A
A99: Arvest | B99: IT Manager | C99: =DATE(2024,6,5)+TIME(13,49,10) -> 45448.576 | E99: NGLCC | F99: =VLOOKUP(Table1[[#This Row],[Company Name]],Sheet1!B:B,1,FALSE) -> #N/A
A100: Arvest | B100: Principal Operational Strategist | C100: =DATE(2024,7,24)+TIME(13,15,11) -> 45497.552 | E100: NGLCC | F100: =VLOOKUP(Table1[[#This Row],[Company Name]],Sheet1!B:B,1,FALSE) -> #N/A
...

Sheet Sheet1
A1: Record ID | B1: Company name | C1: NDA Status | D1: Socio-Economic Profile | E1: Certifications | F1: Capabilities | G1: List of Current Contracts and Contract Vehicles | H1: Current Customers | I1: Supplier Portal Registration Complete? | J1: Website URL | K1: Industry | L1: Type | M1: Create Date | N1: Description | O1: Phone Number | P1: Associated Deal | Q1: Number of Associated Deals | R1: Partner Name | S1: Associated Deal IDs
A2: 22391464521 | J2: qulaitresources.com | M2: 45517.416
A3: 21647513699 | B3: Aarnest | J3: aarnest.com | K3: Computer Software | M3: 45471.567 | N3: Aarnest Inc is a technology company that provides a broad suite of services to address the challenges organizations face in the 21st century. They offer robust software solutions, state-of-the-art cybersecurity, IT development, data migration, and digi...
A4: 22702849321 | B4: AARP | J4: aarp.org | K4: Consumer Services | M4: 45534.874 | N4: AARP is dedicated to empowering individuals aged 50 and older by providing resources, advocacy, and benefits that enhance their quality of life and promote active engagement in their communities. | O4: +1 202-434-3220
A5: 20157158027 | B5: AARP | J5: www.aarp.com | K5: Consumer Services | M5: 45390.608 | N5: Helping Asian American & Pacific Islander Families Get More Out of Life | O5: 866-448-3614
A6: 20157166461 | B6: Abbott Laboratories | I6: Yes | J6: www.abbott.com | K6: Hospital & Health Care | M6: 45390.608 | N6: Abbott is a global healthcare leader that provides innovative medical devices and health care solutions for cardiovascular health, diabetes management, diagnostic testing, nutrition, chronic pain, and more. With a diverse portfolio of life-changing tec... | O6: Some questions are needed to be answered. Suggest to get input from Mike to get the best answers
A7: 20157204915 | B7: AbbVie | I7: Yes | J7: www.abbvie.com | K7: Construction | M7: 45390.608 | N7: AbbVie is a global biopharmaceutical company dedicated to developing innovative therapies for serious diseases, striving to impact lives through advanced medicines in key therapeutic areas. | O7: 1 (800) 255-5162
A8: 23461423745 | B8: ABN AMRO Bank N.V. | J8: http://www.abnamro.nl | K8: Banking | M8: 45565.657 | N8: ABN AMRO Bank is a leading Dutch financial institution that offers a wide range of banking services including retail banking, private banking, and corporate banking. With a focus on sustainability, ABN AMRO aims to support customers in transitioning to more sustainable ways of living and working. The bank has a strong online presence and a dedicated team available 24/7 to assist customers with their financial needs.
A9: 23465122480 | B9: ACA Compliance Group | J9: https://www.acaglobal.com | K9: Professional Training & Coaching | M9: 45565.693 | N9: ACA Group is the leading governance, risk, and compliance advisor in the financial services industry, offering scalable solutions to protect peace of mind. Their services cover regulatory compliance, cybersecurity, privacy, ESG, investment performance, and financial crimes, empowering clients to make confident decisions and maximize efficiency through innovative GRC solutions. | O9: +1 212-951-1030
A10: 23453381223 | B10: ACA Group | J10: acacompliancegroup.com | K10: Professional Training & Coaching | M10: 45565.693 | N10: ACA Compliance Group is a leading provider of risk management and technology solutions that focus on regulatory compliance, performance, financial crime, and cybersecurity.
A11: 19816075548 | B11: ACC | J11: acc.af.mil | K11: Defense & Space | M11: 45384.562 | N11: The United States Air Force provides air, space, and cyber capabilities for use by the combatant commanders. | P11: AIR FORCE TECHNICAL APPLICATION CENTER CYBER ENTERPRISE SUPPORT 2 (ACES) | Q11: 1 | S11: 18380514630
A12: 20317182273 | B12: Accenture | I12: Yes | J12: accenture.com | K12: Information Technology and Services | M12: 45399.555 | N12: Accenture strives to maximize the value of our supplier relationships and places a high value on diversity as evidenced by our ongoing programs to attract, retain and advance women, minorities and other diverse groups. Since 2002, when Accenture’s Supplier Diversity Program was formalized, we have focused on expanding our source of diverse suppliers while maintaining our standards for providing high-quality service delivery. It is the policy of Accenture that diverse suppliers should have equal opportunity to participate in the procurement sourcing process. Suppliers interested in doing business with Accenture in the United States should register their capabilities online by visiting the Accenture Supplier Portal at www.accenture.com/vendor, clicking on the Supplier Portal link and completing the online profile. Once completed, their information will be submitted to our database for review by our sourcing and commodity managers and other buying groups for future procurement needs. If there is a business fit, they may be contacted. Please note that registration does not guarantee business with Accenture. Accenture recommends that suppliers obtain certification from the following certifying agencies or their regional affiliates: the National Minority Supplier Development Council (NMSDC), the Women’s Business Enterprise National Council (WBENC) or the National Gay and Lesbian Chamber of Commerce (NGLCC). | O12: +353 1 646 2000
A13: 23109080912 | B13: Accenture Federal Services | J13: http://www.accenturefederal.com | K13: Legal Services | M13: 45554.479 | N13: Accenture Federal Services is a subsidiary of Accenture that provides consulting, technology, and outsourcing services to the U.S. federal government.
A14: 20752866476 | B14: Accenture Federal Services | M14: 45422.896
A15: 20752829856 | B15: ADEPT Force Group | M15: 45422.896
A16: 20315980911 | B16: Adobe | I16: Yes | M16: 45399.555
A17: 20157273859 | B17: ADP | J17: www.adp.com | M17: 45390.608 | N17: ADP is a global leader in business outsourcing solutions, specializing in HR, payroll, tax, and benefits administration services to enhance workplace productivity and happiness. | O17: +1 973-974-5000
A18: 22703512491 | B18: Advanced Technology Consulting | C18: In-Progress | J18: 4atc.com | K18: Computer Software | M18: 45534.956 | N18: Advanced Technology Consulting (ATC) is an independent IT consulting firm specializing in Digital Transformation (DX) in voice, network, cloud, and cybersecurity. ATC's Delta Model simplifies the process of implementing next-gen IT technologies for bus... | O18: +1 513-299-1177
A19: 20157294851 | B19: Advantage Solutions | J19: www.advantagesolutions.net | K19: Computer Software | M19: 45390.608 | N19: This page uses frames, but your browser doesn't support them. IT Services and IT Consulting | O19: +1 212-429-2211
A20: 20317516570 | B20: AEG | I20: Yes | J20: aegworldwide.com | K20: Entertainment | M20: 45399.555 | N20: AEG's Supplier Diversity Team works to encourage the utilization and development of diverse suppliers in our procurement processes. We collaborate with chambers of commerce and business associations to help us identify qualified, competitive suppliers through trade shows, match making events, and other networking opportunities. Together, we help create mutually beneficial business relationships with diverse suppliers that strengthen the communities we serve. | O20: +1 213-337-4855
A21: 23447300024 | B21: Aegon Asset Management | J21: https://www.aegonam.com | K21: Investment Management | M21: 45565.657 | N21: Aegon Asset Management is a global investment firm that offers a wide range of financial services, including fixed income, equities, real assets, and multi-asset solutions. They cater to a diverse client base, including pension plans, insurance companies, banks, and family offices, with a focus on sustainable and responsible investing practices.
A22: 23438056051 | B22: aegonusa.com | J22: aegonusa.com | M22: 45565.567
A23: 20157149821 | B23: Aetna Supplier Diversity Program | J23: www.aetna.com | K23: Insurance | M23: 45390.608 | N23: Aetna Inc., a CVS Health® company, is a diversified healthcare benefits provider offering health, dental, pharmacy, group life, disability, and long-term care insurance products. With a focus on making healthcare easy, affordable, and personalized, Aet... | O23: +1 860-273-0123
A24: 22812225461 | B24: AFCyberworx | J24: afcyberworx.org | K24: Computer Software | M24: 45540.806 | N24: AF CyberWorx is an innovation lab focused on optimizing products, processes, and policies using Human Centered Design best practices. They are the Air Force's leading problem-solving hub, working on solving problems using Human Centered Design, acceler...
A25: 22248974407 | B25: AFIMSC/SB | J25: www.afimsc.af.mil | K25: Defense & Space | M25: 45509.718 | N25: The United States Air Force provides air, space, and cyber capabilities for use by the combatant commanders.
A26: 22248936297 | B26: AFIMSC/SB | M26: 45509.718
A27: 20316644118 | B27: Aflac | I27: Yes | J27: aflac.com | K27: Insurance | M27: 45399.555 | N27: Aflac is America’s most recognized supplemental insurance company, offering coverage to help with out-of-pocket expenses not covered by major medical insurance. With a commitment to providing financial services that support individuals and businesses, ... | O27: +1 706-323-3431
A28: 22249037617 | B28: AFLCMC/RO | J28: https://www.aflcmc.af.mil/Small-Business-Office/ | K28: Defense & Space | M28: 45509.718 | N28: The United States Air Force provides air, space, and cyber capabilities for use by the combatant commanders.
A29: 22249151915 | B29: AFLCMC/SB | J29: https://www.aflcmc.af.mil/Small-Business-Office/ | K29: Defense & Space | M29: 45509.718 | N29: The United States Air Force provides air, space, and cyber capabilities for use by the combatant commanders.
A30: 22248990317 | B30: AFLCMC/WI | M30: 45509.718
A31: 22249120696 | B31: AFLCMC/WI | M31: 45509.718
A32: 22249194376 | B32: AFLCMC/WL | M32: 45509.718
A33: 22249116282 | B33: AFLCMC/WN | M33: 45509.718
A34: 22248891696 | B34: AFLCMC/XP | M34: 45509.718
A35: 22248847433 | B35: AFMC/SB | M35: 45509.718
A36: 22248955780 | B36: AFNWC | M36: 45509.718
A37: 22249042750 | B37: AFNWC/SB | M37: 45509.718
A38: 16038144822 | B38: AFRL/RQ | J38: afrl.af.mil | K38: Defense & Space | L38: Prospect | M38: 45089.452 | N38: The Aerospace Systems Directorate brings together world-class facilities including a fuels research facility, structural testing labs, compressor research facility, rocket testing facilities, supersonic and subsonic wind tunnels, flight simulation lab, and many other cutting-edge research labs. Among the technologies in development in the Aerospace Systems Directorate are scramjet engines, alternative fuels, unmanned vehicles, hypersonic vehicles, collision avoidance and aircraft energy optimization. | O38: 7036145746 | P38: AFRL/RQ - EA / SAFe Support | Q38: 1 | R38: Air Force Research Labs | S38: 13678356064
A39: 20752383335 | B39: AFRL/RVIS | J39: afrl.af.mil | K39: Defense & Space | L39: Prospect | M39: 45422.912 | N39: The United States Air Force provides air, space, and cyber capabilities for use by the combatant commanders.
A40: 18640511351 | B40: AFRL/RW | J40: afrl.af.mil | K40: Government Administration | L40: Other | M40: 45299.326 | N40: The United States Air Force provides air, space, and cyber capabilities for use by the combatant commanders. The primary mission of Security Forces units is to provide force protection to ensure operational readiness and to protect war fighting resourc... | O40: 7036145746
A41: 16065800059 | B41: AFRL/RY | J41: afrl.af.mil | K41: Defense & Space | L41: Prospect | M41: 45091.406 | N41: The United States Air Force is the air service branch of the United States Armed Forces, and is one of the eight US uniformed services. | O41: 7036145746 | P41: AFRL/RY Proposal (Revisit FY26 Q1) | Q41: 1 | S41: 18801665338
A42: 22249060360 | B42: AFRL/SB | M42: 45509.718
A43: 22249091484 | B43: AFSC/SB | M43: 45509.718
A44: 22249151914 | B44: AFWERX | M44: 45509.718
A45: 17151893673 | B45: Agility Consulting LLC | C45: Active | D45: Women Owned Small Business (WOSB) | J45: agilityconsultinginternational.com | K45: Education Management | M45: 45167.669 | N45: 8a Agility Consulting's Agile training, transformation, and coaching services will allow your organization to thrive and adapt.
A46: 20805157031 | B46: AgilityHealth | J46: agilityhealthradar.com | K46: Management Consulting | M46: 45426.492 | N46: Enterprise agility team management and continuous improvement Measure maturity performance and outcomes at every level using the leading enterprise agility team management software platform The most powerful Agile Assessment Tool has arrived! AgilityHe... | P46: Agility Health Radar & SAI | Q46: 1 | S46: 15705011865
A47: 20315701587 | B47: Ahold Delhaize USA | J47: peapoddigitallabs.com | M47: 45399.555 | N47: Ahold Delhaize is committed to developing mutually beneficial and successful partnerships with diverse suppliers both nationally and with businesses headquartered in our geographic footprint. We develop these relationships by incorporating diverse-owned businesses into the everyday process of category reviews and product/service bids.Our supplier diversity program enhances the procurement process by developing strong business relationships with a talented group of diverse-owned businesses that offer quality products and services, excellent customer service, and competitive costs.
A48: 20315694485 | B48: AIG | I48: Yes | J48: cvmas21.cvmsolutions.com | K48: Computer Software | M48: 45399.555 | N48: It is AIGs policy to proactively seek out diverse-owned enterprises and ensure opportunities for these businesses to participate in the bidding and procurement process. Supplier Diversity is a strategic business initiative, aligned with the goals of AIG Global Sourcing &amp; Procurement Services (GS&amp;PS). AIGs commitment to Supplier Diversity is grounded in sound business strategy. The utilization of diverse suppliers provides AIG access to the widest possible selection of qualified suppliers, innovative solutions and is a driver of our cost reduction efforts. Engaging economically with diverse-owned businesses demonstrates the companys resolve to support the growth of the communities in which it conducts business.
A49: 20157354585 | B49: AIG | J49: www.aig.com | K49: Insurance | M49: 45390.608 | N49: American International Group, Inc. (AIG) is a leading global insurance organization providing a wide range of property casualty insurance, life insurance, retirement solutions, and other financial services to customers in approximately 70 countries and... | O49: https://leanscaledarchitects.atlassian.net/browse/PIPE-102
A50: 16171832749 | B50: Air Force Life Cycle Management Center Command (AFLCMC) | J50: aflcmc.af.mil | K50: Government Administration | L50: Prospect | M50: 45097.645 | N50: The United States Air Force is the air service branch of the United States Armed Forces, and is one of the eight US uniformed services. | O50: 7036145746 | P50: Air Force LCMC - Cloud One Next Environment and Common Shared Services Performance Work Statement (PWS) | Q50: 1 | S50: 13796285733
A51: 15871833163 | B51: Air Force Research Labs | J51: https://www.afrl.af.mil | K51: Defense & Space | L51: Prospect | M51: 45072.713 | N51: The United States Air Force provides air, space, and cyber capabilities for use by the combatant commanders. | P51: AFRL Digital Capabilities Directorate (DCD) RFI Response | Q51: 1 | S51: 18476174468
A52: 20157438875 | B52: Air Products | J52: www.airproducts.com | K52: Chemicals | M52: 45390.608 | N52: Air Products & Chemicals, Inc. is a global industrial gases company providing essential gases, equipment, and expertise to diverse industries. They lead in sustainability, supplying clean hydrogen and LNG technology globally. | O52: +1 610-481-4911
A53: 20159064854 | B53: AirBnB | J53: www.airbnb.com | K53: Computer Software | M53: 45390.608 | N53: Airbnb is the world's largest community-driven hospitality company, offering homes and experiences in 191 countries. It is an online marketplace connecting people to unique accommodations and experiences globally. | O53: +1 415-800-5959
A54: 20159103130 | B54: AirBus | J54: www.airbus.com | K54: Aviation & Aerospace | M54: 45390.608 | N54: Airbus is a global leader in aeronautics, space, and related services, providing a wide range of aircraft and space solutions with a focus on sustainability and customer satisfaction.
A55: 20316644120 | B55: AJ Gallagher | J55: ajg.com | K55: Capital Markets | M55: 45399.555 | N55: For more than 90 years, Gallagher has provided insurance, risk management and consulting services to businesses and communities around the globe. We live in a culture defined by our people, over 32,000 strong, serving our clients with custom solutions that will protect them and fuel their futures.Our supplier diversity network, Gallagher Connect Partners, is an inclusive community of minority-owned, woman-owned, veteran-owned, and other diverse, certified insurance firms that were strategically selected based on their unique specializations, shared values and proven ability to best serve our clients’ risk management, insurance and supplier diversity needs. As a team, we support the growth of Minority/Women-owned Business Enterprises (MWBEs) in insurance and help attract more diverse talent to the industry. | O55: +1 630-773-3800
A56: 23124506468 | B56: Akima | J56: http://www.akima.com/ | K56: Computer Software | M56: 45554.476 | N56: Akima is a government contractor that enhances federal missions through a diverse portfolio of specialized 8(a) companies, focusing on IT, logistics, and other critical services while proudly representing its Alaskan heritage. | O56: +1 571-323-5473
A57: 23458169183 | B57: Al Ghurair Investment | J57: http://www.al-ghurair.com | M57: 45565.571 | N57: Al Ghurair Investment LLC, also known as Abdulla Al Ghurair Group of Companies, is a diversified industrial group based in Dubai. With operations in seven industry sectors including foods, resources, properties, construction, energy, transportation, and ventures, the company has a global presence spanning over 50 countries. Established in 1960, Al Ghurair is a prominent player in the Middle East with a rich history of innovation and entrepreneurship.
A58: 20315737464 | B58: Albemarle | J58: albemarle.com | K58: Chemicals | M58: 45399.555 | N58: Albemarle Corporation is a global specialty chemicals company with leading positions in lithium, bromine, refining catalysts, and applied surface treatments. They partner with customers in various industries to develop customized solutions that enhance... | O58: +1 980-299-5700
A59: 20316787748 | B59: Alight Solutions LLC | J59: alight.com | K59: Apparel & Fashion | M59: 45399.555 | N59: Alight Solutions is a cloud-based provider of benefits administration and HR solutions, empowering organizations and individuals with data-driven insights and a seamless user experience. | O59: +1 702-323-7330
A60: 23463983421 | B60: ALKAMI | J60: alkamitech.com | K60: Banking | M60: 45565.697 | N60: Alkami Technology is a software company that provides e-banking solutions to the financial services industry. | O60: +1 972-200-1937
A61: 23455829603 | B61: Alkami Technology | J61: http://www.alkami.com | K61: Computer Software | M61: 45565.697 | N61: Alkami Technology, Inc. is a leading cloud-based digital banking solutions provider based in Plano, Texas. They offer the ORB Platform, a flagship product that delivers secure, flexible, and customizable online and mobile banking solutions for credit unions and banks. Alkami's focus on transforming ordinary online and mobile banking into valuable experiences for financial institutions and end-users sets them apart in the industry. | O61: +1 972-200-1937
A62: 22417167875 | B62: All Native Group | J62: allnativegroup.com | K62: Professional Training & Coaching | L62: Partner | M62: 45518.831 | N62: All Native Group is a federal government contractor that has been providing world-class services, equipment, and training to our Federal Government clients for over 15 years. We are a Native-owned company and hold certifications such as SBA 8(a), HUBZo...
A63: 23464292455 | B63: AllianceBernstein | J63: https://www.alliancebernstein.com/?r=no | K63: Investment Management | M63: 45565.699 | N63: AllianceBernstein is a leading global investment management and research firm that provides a wide range of investment services, including equity and fixed income strategies, alternative investments, and multi-asset solutions, catering to a diverse clientele from individual investors to large institutions. | O63: +1 914-259-7788
A64: 20317398146 | B64: Alliant | M64: 45399.555
A65: 23449471235 | B65: Allianz | J65: https://www.allianz.com/en.html | K65: Insurance | M65: 45565.645 | N65: Allianz is a global financial services provider offering insurance and asset management solutions to millions worldwide, emphasizing sustainability and employee care. | O65: +49 89 38000
A66: 20157259630 | B66: Allstate Insurance Company | I66: Yes | J66: http://www.allstate.com | K66: Insurance | M66: 45390.608 | N66: Our Supplier Diversity Program Policy is to ensure inclusion of minority-, woman- and veteran-owned businesses in the competitive bidding process at Allstate in support of our commitment to provide quality products and services to our customers while delivering outstanding value to our shareholders. The Supplier Diversity Program was established in 2003, and since then, we have steadily increased the procurement of goods and services with diverse suppliers. In 2012, Allstate spent $304.4 million with these diverse businesses. We are committed to increasing our spend with diverse suppliers again in 2013 and encourage diverse suppliers to complete the Prospective Supplier Registration process. | O66: 800-255-7828
A67: 23455666689 | B67: Alpha Bank | J67: http://www.alpha.gr | K67: Banking | M67: 45565.65 | N67: Alpha Bank is a Greece-based company founded in 1879, offering a wide range of financial products and services. It provides corporate and retail banking, financial services, investment banking, brokerage services, insurance services, real estate management, and hotel services. With a strong presence in Greece, Cyprus, Romania, Albania, and the UK, Alpha Bank is known for its high capital adequacy ratio and employs 8,500 employees internationally. | O67: +30 21 0326 0000
A68: 20159038742 | B68: Altria Group | M68: 45390.608 | O68: (800) 872-3777
A69: 20315654565 | B69: Altria Group, Inc. | I69: Yes | J69: altria.com | K69: Tobacco | M69: 45399.555 | N69: Altria Group, Inc. is a leading holding company in the tobacco industry, with subsidiaries like Philip Morris USA, U.S. Smokeless Tobacco Co., and John Middleton. They offer a diverse portfolio of tobacco products for adult consumers, including cigaret... | O69: +1 804-274-2200
A70: 20157361698 | B70: Amazon | K70: Computer Software | M70: 45390.608 | O70: +1 206-266-1000
A71: 20316657002 | B71: Amazon.com | I71: Yes | J71: amazonsupplierdiversity.com | K71: Professional Training & Coaching | M71: 45399.555
A72: 19816359808 | B72: AMC | J72: afmc.af.mil | K72: Defense & Space | M72: 45384.561 | N72: The United States Air Force provides air, space, and cyber capabilities for use by the combatant commanders. | P72: CLOUD ONE NEXT ARCHITECTURE AND COMMON SHARED SERVICES (C1N ACSS) | Q72: 1 | S72: 18380564496
A73: 20316657001 | B73: AMC Networks | J73: amcnetworks.com | K73: Entertainment | M73: 45399.555 | N73: Invoicing- Please include the cycle time (ex. June 2022--May 2023) so it's clear that it's for 12 months | O73: +1 212-324-8500
A74: 20159012989 | B74: American Airlines | J74: americanairlines.com | K74: Leisure, Travel & Tourism | M74: 45390.608 | N74: American Airlines is a major American airline headquartered in Fort Worth, Texas. It is one of the largest airlines in the world, operating an extensive network of domestic and international flights. American Airlines offers a wide range of products an... | O74: (495)-287-3359
A75: 20317024768 | B75: American Association of Medical Colleges | M75: 45399.555
A76: 20316806284 | B76: American Axle & Manufacturing (AAM) | J76: aam.com | K76: Automotive | M76: 45399.555 | N76: AAM is a global automotive supplier specializing in driveline and metal forming technologies for various vehicles, emphasizing quality and technology leadership. | O76: +1 313-758-3600
A77: 20317091488 | B77: American Cancer Society Inc | J77: cancer.org | K77: Non-Profit Organization Management | M77: 45399.555 | N77: The American Cancer Society is a nationwide voluntary health organization dedicated to eliminating cancer in the United States. They provide information, resources, and support for various types of cancer including breast, colon, lung, prostate, and sk... | O77: +1 404-329-5757
A78: 20317182274 | B78: American Express | I78: Yes | J78: americanexpress.com | K78: Financial Services | M78: 45399.555 | N78: At American Express, we recognize that winning strategies, products, and services require diversity of thought, perspectives, and contributions. Inclusion is a practice and commitment that we are proud to stand behind; it is integral to maintaining our position as one of the top payments solution providers. As part of our Supply Chain Inclusion Initiative, American Express monitors our annual spend with suppliers that are certified business enterprises with protected-class owners and operators. | O78: +1 212-640-2000
A79: 20156182641 | B79: American Express | J79: americanexpress.com | K79: Insurance | M79: 45390.608 | N79: American Family Mutual Insurance Company, American Family Life Insurance Company, American Standard Insurance Company of Wisconsin, 6000 American Parkway, Madison WI 53783 | O79: https://leanscaledarchitects.atlassian.net/browse/PIPE-102
A80: 20317105946 | B80: American Family Insurance | I80: Yes | J80: amfam.com | K80: Insurance | M80: 45399.555 | N80: Today, American Family Insurance group is the nation’s 13th-largest property/casualty insurance group, ranking No. 254 on the Fortune 500 list. The group sells American Family-brand products, primarily through exclusive agency owners in 19 states. The American Family Insurance group also includes CONNECT, powered by American Family Insurance (formerly Ameriprise Auto &amp; Home), The General, Homesite and Main Street America. Across these companies the group has more than 13,500 employees nationwide. | O80: +1 800-692-6326
A81: 20159073164 | B81: American Family Insurance | M81: 45390.608 | O81: 1 800-692-6326
A82: 23455820670 | B82: American Financial Network | J82: https://www.afncorp.com/ | K82: Banking | M82: 45565.65 | N82: American Financial Network, Inc. is a leading mortgage banker in the United States, established in 2001 with over 100 branches nationwide. Specializing in serving real estate professionals, builders, and individual homebuyers, AFN offers a wide range of loan products including FHA, USDA, VA, and Jumbo loans. With a focus on efficient operations and exceptional customer service, AFN provides regular loan updates and online application services to make the lending process seamless and personalized for each client. | O82: +1 909-606-3905
A83: 20317168191 | B83: American Meetings, Inc. | J83: americanmeetings.com | K83: Management Consulting | M83: 45399.555 | N83: American Meetings, Inc. (AMI) has been providing the highest level of live, virtual, and hybrid meetings services for over 20 years. They are the premier partner to organizations worldwide for virtual and live meetings and events. Their global network ...
A84: 20316871263 | B84: American Red Cross | J84: redcross.org | K84: Individual & Family Services | M84: 45399.555 | N84: The American Red Cross prevents and alleviates human suffering in the face of emergencies by mobilizing the power of volunteers and the generosity of donors.​﻿ | O84: +1 800-733-2767
A85: 22702769733 | B85: AMERICAN SYSTEMS | J85: americansystems.com | K85: Civil Engineering | M85: 45534.874 | N85: AMERICAN SYSTEMS, a top employee-owned federal government contractor, delivers innovative IT and Engineering solutions to national priority programs with a focus on Defense, Intelligence, Law Enforcement, Outreach, and Healthcare. | O85: +1 703-968-6300
A86: 20317091487 | B86: American Tower Corp | J86: americantower.com | K86: Telecommunications | M86: 45399.555 | N86: American Tower: Global wireless infrastructure provider supporting connectivity worldwide through innovative real estate solutions. | O86: +1 617-375-7500
A87: 20317450859 | B87: American Water Works Company, Inc. | J87: amwater.com | M87: 45399.555 | N87: We are a regulated water utility. American Water is the largest most geographically diverse water and wastewater service provider. | O87: +1 856-955-4001
A88: 20315899762 | B88: Ameriprise Financial | J88: https://www.ameriprise.com/ | K88: Investment Management | M88: 45399.555 | N88: At Ameriprise Financial, diversity is reflected in everything that drives our success, our people, our corporate values, our business strategy, our culture, and our investment in the communities in which we live and work. Through our commitment to diversity, we access innovative ideas and varied perspectives to help us deliver financial solutions that meet our clients' needs and make a difference in their lives.Ameriprise Financial is committed to supporting supplier diversity. Our company encourages all suppliers, including certified minority-owned, woman-owned, disabilities-owned, veteran-owned, LGBT-owned, HUBZone or small business enterprises, to participate, monitor, and support our program with products and services.Products and services purchased by Ameriprise Financial include:Financial and Insurance servicesTechnology and IT InfrastructureContingent laborMarketingFacilities/Real EstateOther | O88: +1 612-671-8001
A89: 23459568989 | B89: Ameriprise Financial, | J89: ampf.com | K89: Investment Management | M89: 45565.665 | N89: AMPF.com is an online platform that provides a variety of financial services such as investment advice, retirement planning, and wealth management. They offer user-friendly tools that allow customers to manage their finances with ease and access to highly-rated financial advisors. Additionally, they provide unbiased research for investors to make informed decisions. With AMPF.com, customers can achieve their financial goals with confidence. | O89: +1 612-671-8001
A90: 23465426452 | B90: Ameris Bank | J90: http://www.amerisbank.com | K90: Banking | M90: 45565.674 | N90: Ameris Bancorp, through its banking subsidiary Ameris Bank, offers a wide range of financial services to retail and commercial customers. With divisions specializing in banking, mortgage, warehouse lending, and SBA loans, Ameris Bank aims to provide financial peace of mind to individuals and businesses by turning money questions into solid financial plans and helping achieve their financial goals. | O90: +1 404-639-6500
A91: 20315763635 | B91: Amgen | J91: wwwext.amgen.com | K91: Pharmaceuticals | M91: 45399.555 | N91: Amgen’s Supplier Diversity Program, managed by Global Strategic Sourcing, provides opportunities to small and diverse businesses to supply goods and services to Amgen. Amgen’s Supplier Diversity Program is governed by the Supplier Diversity Policy and is consistent with Amgen’s Diversity and Inclusion strategies. A supplier diversity course is available to Amgen’s staff through Amgen’s on-line training system. Amgen strives in its procurement program to identify, develop, and utilize small business concerns, including those that are disadvantaged, veteran-owned, service-disabled veteran-owned, women-owned, as well as Historically Underutilized Business Zones (HUBZones). Amgen’s intent is to support economic development efforts to the extent that jobs may be provided, entrepreneurship may be advanced, and useful goods and/or services may be procured at competitive prices. | O91: +1 805-447-1000
A92: 20753175613 | B92: Amtrak | J92: amtrak.com | K92: Maritime | M92: 45422.896 | N92: Amtrak is America's leading provider of intercity passenger rail services, connecting over 500 destinations in 46 states and Canada with a focus on safety, efficiency, and customer experience. | O92: +1 202-906-2272
A93: 23454056210 | B93: ANZ | J93: http://www.anz.com | K93: Banking | M93: 45565.571 | N93: ANZ provides a range of banking and financial products and services. The Company's operations span Australia, New Zealand, and several countries in the Asia Pacific region, the United Kingdom, France, Germany, and the United States. ANZ offers retail banking, private banking, commercial banking, wealth management, and institutional banking services. The company has a proud heritage of over 180 years and aims to create a balanced, sustainable economy where everyone can thrive. | O93: +61 3 9273 1597
A94: 22703098403 | B94: AOL | J94: aol.co.uk | K94: Computer Software | M94: 45534.874 | N94: AOL is a global advertising-supported web company that provides breaking news, sports, entertainment, lifestyle, finance, and more. With a display advertising network in the U.S. and a substantial worldwide audience, AOL UK delivers the latest articles...
A95: 23446998195 | B95: Apollo Global Management, Inc. | J95: http://www.apollo.com | K95: Capital Markets | M95: 45565.685 | N95: Apollo Global Management is a leading provider of alternative asset management and retirement solutions, empowering retirees and financing businesses with innovative capital solutions for growth and financial security. | O95: +1 212-515-3200
A96: 20159087280 | B96: Apple | J96: apple.com | K96: Computer Software | M96: 45390.608 | N96: Apple is a multinational corporation known for designing, manufacturing, and marketing consumer electronics, personal computers, and software. Their innovative product development and world-class operations have made them a leader in the industry, with... | O96: +1 408-996-1010
A97: 20316563616 | B97: Apple Inc. | I97: Yes | M97: 45399.555
A98: 22703009344 | B98: Applied Federal Solutions | C98: Active | D98: Service Disabled Veteran Owned Small Business (SDVOSB) | E98: Not available | F98: Management, IT, Cybersecurity, Operational Improvement, Federal and State Client Solutions, Clinical Staffing, Project Management, Health IT, Software Development | G98: VA Integrated Critical Staffing Program (ICSP), Various Federal Contracts | H98: Veteran Affairs, USSOCOM, Federal Bureau of Investigation, US Air Force, State of Florida, University of Florida, US Department of Agriculture (USDA) | J98: appliedfederalsolutions.com | K98: Computer Software | M98: 45534.874 | N98: Applied Federal Solutions is a full service Management, IT, and Cybersecurity firm providing effective and efficient solutions to Federal and State clients. As a registered SDVOSB, we know that the mission is paramount. Our team of experienced professi...
A99: 20398983331 | B99: ARCYBER | J99: arcyber.army.mil | K99: Government Administration | M99: 45404.501 | N99: The United States Army is dedicated to fighting and winning the nation's wars by providing land dominance across various military operations. They offer career opportunities in armed forces, administrative support, arts & media, intelligence, legal, co... | O99: 3302626136 | P99: ARMY DEPARTMENT OF DEFENSE INFORMATION NETWORK ARMY CYBERSECURITY AND NETWORK OPERATIONS MISSION SUPPORT (ADCNOMS) | Q99: 1 | S99: 18380671400
